Workbook

Sheet Cost Build-up
A1: COST BUILD-UP / RATE BREAKDOWN — Sections 3, 4 & 5
A2: Project: CAG Workers Dormitory | Basis: Singapore 2026 D&B Rates | All amounts in S$
A4: SECTION 3.2 — DORMITORY BLOCKS (8 nos × 4 storeys, GFA 47,420 m²)
A5: BOQ Ref | B5: Description / Sub-component | C5: Qty | D5: Unit | E5: Rate (S$) | F5: Amount (S$) | G5: Remarks
A6: 3.2/1.1 | B6: Substructure — Earthworks & Waterproofing (8 blocks)
B7: Bituminous WP membrane to slab on grade, 1.5mm SBS | C7: 11856 | D7: m² | E7: 30 | F7: =C7*E7 -> 355680 | G7: Footprint 1,482 m² × 8 blocks
B8: Anti-termite chemical treatment to soil | C8: 11856 | D8: m² | E8: 22.5 | F8: =C8*E8 -> 266760 | G8: TM4083 compliant
B9: Excavation to reduced level, average 1.2m depth | C9: 14227 | D9: m³ | E9: 28 | F9: =C9*E9 -> 398356 | G9: Mech excavation incl spoil to dump
B10: Backfill with approved granular material | C10: 4742 | D10: m³ | E10: 35 | F10: =C10*E10 -> 165970 | G10: Compacted in 150mm layers
B11: Cart away surplus to off-site disposal | C11: 9485 | D11: m³ | E11: 45 | F11: =C11*E11 -> 426825 | G11: Lorry transport + tipping fee
B12: Subtotal — Substructure Earthworks (×2 phases) | F12: =SUM(F6:F11) -> 1613591
A13: 3.2/1.2 | B13: Raft Foundation (8 blocks)
B14: Lean concrete blinding 50mm thick, Grade C20 | C14: 593 | D14: m³ | E14: 280 | F14: =C14*E14 -> 166040 | G14: 11,856 m² × 0.05m
B15: Hardcore bedding 150mm compacted | C15: 1778 | D15: m³ | E15: 90 | F15: =C15*E15 -> 160020 | G15: Crushed stone 40mm down
B16: Reinforced concrete raft slab, 600mm thick, Grade C40 | C16: 7114 | D16: m³ | E16: 380 | F16: =C16*E16 -> 2703320 | G16: Ready-mix incl pump
B17: Sawn formwork to raft edges | C17: 4800 | D17: m² | E17: 65 | F17: =C17*E17 -> 312000 | G17: Perimeter & construction joints
B18: High-yield reinforcement T20-T25, BS500B | C18: 854 | D18: tonne | E18: 1750 | F18: =C18*E18 -> 1494500 | G18: 120 kg/m³ raft slab
B19: Plate load test | C19: 16 | D19: no | E19: 1800 | F19: =C19*E19 -> 28800 | G19: 2 tests per block
B20: Subtotal — Raft Foundation (×2 phases) | F20: =SUM(F13:F19) -> 4864680
A21: 3.2/2.1 | B21: Superstructure — Frame (8 blocks × 4 storeys)
B22: Reinforced concrete columns C40 | C22: 1422 | D22: m³ | E22: 580 | F22: =C22*E22 -> 824760 | G22: ~30 m³/storey × 4 × 8 blocks
B23: Formwork to columns | C23: 9484 | D23: m² | E23: 70 | F23: =C23*E23 -> 663880 | G23: 8x perimeter coverage
B24: Reinforcement to columns T20-T32 | C24: 256 | D24: tonne | E24: 1900 | F24: =C24*E24 -> 486400 | G24: 180 kg/m³
B25: RC beams C40 | C25: 1896 | D25: m³ | E25: 620 | F25: =C25*E25 -> 1175520 | G25: Tie beams + main beams
B26: Formwork to beams (soffit + sides) | C26: 12640 | D26: m² | E26: 80 | F26: =C26*E26 -> 1011200 | G26: Includes propping
B27: Reinforcement to beams T16-T25 | C27: 380 | D27: tonne | E27: 1850 | F27: =C27*E27 -> 703000 | G27: 200 kg/m³
B28: Subtotal — Superstructure Frame (×2 phases) | F28: =SUM(F21:F27) -> 4864760
A29: 3.2/2.2 | B29: Upper Floor Slabs (3 elevated levels × 8 blocks)
B30: RC slab 175mm thick, C40 | C30: 6224 | D30: m³ | E30: 410 | F30: =C30*E30 -> 2551840 | G30: 1,482 m² × 3 floors × 8 × 0.175m
B31: Formwork & propping to soffit | C31: 35568 | D31: m² | E31: 55 | F31: =C31*E31 -> 1956240 | G31: Hire system formwork
B32: Reinforcement to slabs T10-T16 | C32: 747 | D32: tonne | E32: 1800 | F32: =C32*E32 -> 1344600 | G32: 120 kg/m³
B33: Cast iron rainwater pipes DN100 to corridor | C33: 960 | D33: m | E33: 175 | F33: =C33*E33 -> 168000 | G33: 30m × 8 blocks × 4 floors
B34: Floor outlets stainless steel 100mm | C34: 384 | D34: no | E34: 220 | F34: =C34*E34 -> 84480 | G34: 12 nos × 8 blocks × 4 floors
B35: Subtotal — Upper Floor Slabs (×2 phases) | F35: =SUM(F29:F34) -> 6105160
A36: 3.2/2.3 | B36: Roof — Pitched & Flat (8 blocks)
B37: Pitched roof structure: steel purlins on RC beams | C37: 11856 | D37: m² | E37: 95 | F37: =C37*E37 -> 1126320 | G37: Roof plan area
B38: Flat roof structure to plant areas | C38: 2400 | D38: m² | E38: 165 | F38: =C38*E38 -> 396000 | G38: RC slab + screed to falls
B39: Zincalume metal sheet roofing 0.50mm | C39: 11856 | D39: m² | E39: 75 | F39: =C39*E39 -> 889200 | G39: Colour-coated, AZ150 coating
B40: PPGI flashings, ridge caps, eaves trims | C40: 2400 | D40: m | E40: 60 | F40: =C40*E40 -> 144000 | G40: Perimeter + ridges
B41: Aluminium box gutters 200×150mm | C41: 1920 | D41: m | E41: 110 | F41: =C41*E41 -> 211200 | G41: 240m per block × 8
B42: UPVC rainwater downpipes DN150 | C42: 768 | D42: m | E42: 95 | F42: =C42*E42 -> 72960 | G42: External downpipes
B43: Subtotal — Roof (×2 phases) | F43: =SUM(F36:F42) -> 2839680
A44: 3.2/2.4 | B44: Stairs and Ramps (2 cores per block × 8)
B45: RC stair flights & landings, C40 | C45: 614 | D45: m³ | E45: 720 | F45: =C45*E45 -> 442080 | G45: 2 cores × 4 flights × 8 blocks
B46: Formwork to stairs (sloping) | C46: 4915 | D46: m² | E46: 95 | F46: =C46*E46 -> 466925 | G46: Complex geometry
B47: Reinforcement to stairs T12-T16 | C47: 86 | D47: tonne | E47: 2000 | F47: =C47*E47 -> 172000 | G47: 140 kg/m³
B48: RC ramp structure (DDA access) | C48: 192 | D48: m³ | E48: 680 | F48: =C48*E48 -> 130560 | G48: 1 per block × 8
B49: Non-slip cement tile finish to stairs | C49: 4915 | D49: m² | E49: 95 | F49: =C49*E49 -> 466925 | G49: With nosings
B50: Granolithic finish to ramps | C50: 1536 | D50: m² | E50: 80 | F50: =C50*E50 -> 122880 | G50: Trowel finish
B51: MS balustrade & handrails to stairs, 1m H | C51: 3072 | D51: m | E51: 145 | F51: =C51*E51 -> 445440 | G51: 12m × 4 flights × 8 × 8 blocks
B52: MS balustrade & handrails to ramps | C52: 768 | D52: m | E52: 145 | F52: =C52*E52 -> 111360 | G52: 12m × 8 ramps
B53: Cat ladders to plant rooms | C53: 16 | D53: no | E53: 4500 | F53: =C53*E53 -> 72000 | G53: 2 per block
B54: Subtotal — Stairs and Ramps (×2 phases) | F54: =SUM(F44:F53) -> 2430170
A55: 3.2/2.5 | B55: External Walls and Cladding
B56: Lightweight concrete panel walls (PPVC compatible) | C56: 22272 | D56: m² | E56: 280 | F56: =C56*E56 -> 6236160 | G56: ~58 m²/storey perimeter × 4 × 8 × 2 phases base
B57: External cement render 15mm + skim coat | C57: 22272 | D57: m² | E57: 38 | F57: =C57*E57 -> 846336 | G57: 2 coats
B58: Weatherproof external paint | C58: 22272 | D58: m² | E58: 18 | F58: =C58*E58 -> 400896 | G58: Acrylic emulsion 3 coats
B59: Perforated aluminium screen to corridor | C59: 4800 | D59: m² | E59: 180 | F59: =C59*E59 -> 864000 | G59: 60m × 4 storey × 5 × 4 blocks per phase
B60: Corrugated steel cladding to stair cores | C60: 1920 | D60: m² | E60: 145 | F60: =C60*E60 -> 278400 | G60: Galv steel sheet
B61: Subtotal — External Walls (×2 phases) | F61: =SUM(F55:F60) -> 8625792
A62: 3.2/2.6 | B62: Windows and External Doors
B63: Aluminium framed windows w/ 6mm tinted glass | C63: 4800 | D63: m² | E63: 525 | F63: =C63*E63 -> 2520000 | G63: 60% facade window ratio
B64: Aluminium louvres to common areas | C64: 2400 | D64: m² | E64: 380 | F64: =C64*E64 -> 912000 | G64: 30% facade as louvre
B65: External metal/timber flush doors w/ frame | C65: 320 | D65: no | E65: 1500 | F65: =C65*E65 -> 480000 | G65: 5 nos × 8 storeys × 8 blocks
B66: Heavy duty roller shutters to service entries | C66: 16 | D66: no | E66: 12000 | F66: =C66*E66 -> 192000 | G66: 2 per block × 8
B67: Subtotal — Windows & External Doors (×2 phases) | F67: =SUM(F62:F66) -> 4104000
A68: 3.2/2.7 | B68: Internal Walls and Partitions
B69: Lightweight concrete panel partition 100mm | C69: 32000 | D69: m² | E69: 110 | F69: =C69*E69 -> 3520000 | G69: Bedroom + corridor walls
B70: Phenolic toilet cubicles w/ doors | C70: 480 | D70: no | E70: 1500 | F70: =C70*E70 -> 720000 | G70: 60 cubicles × 8 blocks
B71: Subtotal — Internal Walls (×2 phases) | F71: =SUM(F68:F70) -> 4240000
A72: 3.2/2.8 | B72: Internal Doors
B73: Timber flush doors w/ HM frame & ironmongery | C73: 960 | D73: no | E73: 950 | F73: =C73*E73 -> 912000 | G73: Bedroom doors
B74: Toilet entrance doors HM w/ louvre | C74: 240 | D74: no | E74: 1100 | F74: =C74*E74 -> 264000 | G74: 30 per block × 8
B75: Subtotal — Internal Doors (×2 phases) | F75: =SUM(F72:F74) -> 1176000
A76: 3.2/3.1 | B76: Floor Finishes
B77: Heavy duty homogeneous vinyl sheet flooring to bedrooms | C77: 30000 | D77: m² | E77: 65 | F77: =C77*E77 -> 1950000 | G77: ~80% of GFA × 47,420 m²
B78: Non-slip ceramic floor tiles to toilets | C78: 6000 | D78: m² | E78: 95 | F78: =C78*E78 -> 570000 | G78: Wet areas
B79: Homogeneous floor tiles to corridors | C79: 11400 | D79: m² | E79: 110 | F79: =C79*E79 -> 1254000 | G79: Common areas
B80: PVC skirtings 100mm H | C80: 24000 | D80: m | E80: 18 | F80: =C80*E80 -> 432000 | G80: All bedrooms
B81: Subtotal — Floor Finishes (×2 phases) | F81: =SUM(F76:F80) -> 4206000
A82: 3.2/3.2 | B82: Wall Finishes
B83: Low VOC emulsion paint to bedrooms/corridors | C83: 96000 | D83: m² | E83: 14 | F83: =C83*E83 -> 1344000 | G83: Internal walls 2 coats
B84: Glazed ceramic wall tiles to toilets, full height | C84: 14400 | D84: m² | E84: 95 | F84: =C84*E84 -> 1368000 | G84: Wet area walls
B85: Weather/impact resistant finish to corridor walls | C85: 12000 | D85: m² | E85: 38 | F85: =C85*E85 -> 456000 | G85: High-traffic areas
B86: Subtotal — Wall Finishes (×2 phases) | F86: =SUM(F82:F85) -> 3168000
A87: 3.2/3.3 | B87: Ceiling Finishes
B88: Mineral fibre suspended ceiling 600×600 | C88: 30000 | D88: m² | E88: 42 | F88: =C88*E88 -> 1260000 | G88: Bedrooms + corridors
B89: Moisture resistant suspended ceiling to toilets | C89: 6000 | D89: m² | E89: 58 | F89: =C89*E89 -> 348000 | G89: MR gypsum board
B90: Aluminium access hatches 600×600 | C90: 240 | D90: no | E90: 380 | F90: =C90*E90 -> 91200 | G90: 30 nos per block
B91: Subtotal — Ceiling Finishes (×2 phases) | F91: =SUM(F87:F90) -> 1699200
A92: 3.2/4.1 | B92: Dormitory Bedroom Fittings
B93: Double bunk beds w/ mattresses (powder coated steel) | C93: 1920 | D93: no | E93: 850 | F93: =C93*E93 -> 1632000 | G93: 240 beds per block × 8
B94: Lockable steel storage cabinets (per bed) | C94: 1920 | D94: no | E94: 420 | F94: =C94*E94 -> 806400 | G94: 1 per bed
B95: Ceiling/standing fans 60" industrial | C95: 480 | D95: no | E95: 750 | F95: =C95*E95 -> 360000 | G95: 60 per block × 8
B96: Subtotal — Bedroom Fittings (×2 phases) | F96: =SUM(F92:F95) -> 2798400
A97: 3.2/4.2 | B97: Dormitory Unit Toilet Fittings
B98: WC pan w/ cistern, stainless steel grade | C98: 240 | D98: no | E98: 580 | F98: =C98*E98 -> 139200 | G98: 30 per block × 8
B99: Wash basin w/ tap & trap | C99: 192 | D99: no | E99: 380 | F99: =C99*E99 -> 72960 | G99: 24 per block × 8
B100: Shower mixer w/ rose & arm | C100: 240 | D100: no | E100: 280 | F100: =C100*E100 -> 67200 | G100: 30 per block × 8
B101: Urinals w/ sensor flush | C101: 48 | D101: no | E101: 750 | F101: =C101*E101 -> 36000 | G101: 6 per block × 8
...

Sheet FS
A1: DESIGN AND BUILD OF COASTAL DORMITORY EXPANSION CHANGI EAST DEVELOPMENT – TENDER REF: CE/25/T5/P/896
A4: FINAL SUMMARY FOR THE SCHEDULE OF WORKS | H4: SUBMISSION COST
A5: Section | B5: Description | D5: Page | E5: Phase A (S$) | F5: Phase B (S$) | H5: Phase A (S$) | I5: Phase B (S$)
A6: 1 | B6: Preliminaries and General | D6: SECT 1/53 | E6: =+'1_Prelim'!J536 -> 0 | F6: =+'1_Prelim'!N536 -> 0 | H6: 0 | I6: 0
A7: 2 | B7: Professional Fees | D7: SECT 2.SUM/1 | E7: ='2_Professional Fees'!K265 -> 0 | F7: ='2_Professional Fees'!N265 -> 0 | H7: ='2_Professional Fees'!R265 -> 0 | I7: =+'2_Professional Fees'!S92 -> 0
A8: 3 | B8: Building Works | D8: SECT 3.SUM/1 | E8: ='Sec 3 - Building Works'!O502 -> 0 | F8: ='Sec 3 - Building Works'!V502 -> 0 | H8: ='Sec 3 - Building Works'!Y502 -> 0 | I8: ='Sec 3 - Building Works'!Z502 -> 0
A9: 4 | B9: External Works | D9: SECT 4.SUM/1 | E9: =+'Sec 4 - External Works'!K68 -> 0 | F9: =+'Sec 4 - External Works'!N68 -> 0 | H9: =+'Sec 4 - External Works'!Q68 -> 0 | I9: =+'Sec 4 - External Works'!R68 -> 0
A10: 5 | B10: Mechanical & Electrical Works | D10: SECT 5.SUM/1 | H10: =+E10 -> 0 | I10: =+F10 -> 0
A12: ADD | B12: Insurance
A14: ADD | B14: Security Deposit
A16: TOTAL FOR WORKS CARRIED TO FORM OF TENDER (excluding GST) | E16: =SUM(E6:E15) -> 0 | F16: =SUM(F6:F15) -> 0 | H16: =SUM(H6:H15) -> 0 | I16: =SUM(I6:I15) -> 0

Sheet 1_Prelim
A1: DESIGN AND BUILD OF COASTAL DORMITORY EXPANSION FOR CHANGI EAST DEVELOPMENT
A2: REFERENCE NO.: CE/25/T5/P/896 SECTION 1 - PRELIMINARIES AND GENERAL
A3: CODE | B3: PAGE | C3: ITEM | D3: CLAUSE /REF | E3: DESCRIPTION | F3: UNIT | G3: U/RATE (S$) | H3: PHASE A (S$) | L3: PHASE B (S$)
H4: QTY | I4: AMOUNT (S$) | J4: AMT TO COLL (S$) | K4: REMARKS | L4: QTY | M4: AMOUNT (S$) | N4: AMT TO COLL (S$) | O4: REMARKS
A5: Prelim | B5: Sec1/1 | D5: A | E5: GENERAL MATTERS AND OBLIGATIONS | I5: =ROUND(H5*G5,2) -> 0 | J5: =ROUNDUP(I5,0) -> 0 | M5: =ROUND(L5*G5,2) -> 0 | N5: =ROUNDUP(M5,0) -> 0
A6: Prelim | B6: Sec1/1 | D6: 1 | E6: GENERAL | I6: =ROUND(H6*G6,2) -> 0 | J6: =ROUNDUP(I6,0) -> 0 | M6: =ROUND(L6*G6,2) -> 0 | N6: =ROUNDUP(M6,0) -> 0
A7: Prelim | B7: Sec1/1 | E7: The Preliminaries and General Section and the prices entered therein by the Contractor shall apply to the whole of the Works. | I7: =ROUND(H7*G7,2) -> 0 | J7: =ROUNDUP(I7,0) -> 0 | M7: =ROUND(L7*G7,2) -> 0 | N7: =ROUNDUP(M7,0) -> 0
A8: Prelim | B8: Sec1/1 | E8: The Contractor shall be deemed to have satisfied himself as to the sufficiency of his tender and of the prices in these Sections, all of which shall cover his obligations under the Contract and all work and expenditure necessary to carry out and bring the Works to completion. | I8: =ROUND(H8*G8,2) -> 0 | J8: =ROUNDUP(I8,0) -> 0 | M8: =ROUND(L8*G8,2) -> 0 | N8: =ROUNDUP(M8,0) -> 0
A9: Prelim | B9: Sec1/1 | E9: Without limitation to the Contractor's obligations under Clause 4.4 of the Conditions, any discrepancy brought forth after submission of the tender shall be interpreted at the sole discretion of the Superintending Officer whose decisions shall be final and binding and the Contractor shall deemed to have made all due allowances for the item or proposed work of better quality, greater quantity, or higher cost in the Contract Sum. | I9: =ROUND(H9*G9,2) -> 0 | J9: =ROUNDUP(I9,0) -> 0 | M9: =ROUND(L9*G9,2) -> 0 | N9: =ROUNDUP(M9,0) -> 0
A10: Prelim | B10: Sec1/1 | E10: Works not explicitly mentioned in the Contract Documents but are obviously necessary for the efficiency, stability and completion of the Works shall be included in the Contract Sum by the Contractor. | I10: =ROUND(H10*G10,2) -> 0 | J10: =ROUNDUP(I10,0) -> 0 | M10: =ROUND(L10*G10,2) -> 0 | N10: =ROUNDUP(M10,0) -> 0
A11: Prelim | B11: Sec1/1 | E11: Works mentioned in the Specifications but not shown in the Contract Drawings and vice versa will be nevertheless be deemed to be included in the Contract and shall be included in the Contract Sum. | I11: =ROUND(H11*G11,2) -> 0 | J11: =ROUNDUP(I11,0) -> 0 | M11: =ROUND(L11*G11,2) -> 0 | N11: =ROUNDUP(M11,0) -> 0
A12: Prelim | B12: Sec1/1 | D12: 2 | E12: ALTERATION TO TEXT | I12: =ROUND(H12*G12,2) -> 0 | J12: =ROUNDUP(I12,0) -> 0 | M12: =ROUND(L12*G12,2) -> 0 | N12: =ROUNDUP(M12,0) -> 0
A13: Prelim | B13: Sec1/1 | E13: The Tenderer shall study carefully the requirements of the Specifications, Conditions of Contract and all other parts of the Tender Documents and submit his Tender Offer only after he is satisfied with himself that he can meet all the requirements of this Invitation to Tender. | I13: =ROUND(H13*G13,2) -> 0 | J13: =ROUNDUP(I13,0) -> 0 | M13: =ROUND(L13*G13,2) -> 0 | N13: =ROUNDUP(M13,0) -> 0
A14: Prelim | B14: Sec1/1 | E14: No alterations or amendments shall be made to the Contract Documents unless authorised in writing by the Superintending Officer. The original text shall be adhered to if unauthorised alterations or amendments have been made by the Contractor. | I14: =ROUND(H14*G14,2) -> 0 | J14: =ROUNDUP(I14,0) -> 0 | M14: =ROUND(L14*G14,2) -> 0 | N14: =ROUNDUP(M14,0) -> 0
A15: Collection | B15: =+B14 -> Sec1/1 | E15: To Collection S$ | J15: =SUBTOTAL(9,J5:J14) -> 0 | N15: =SUBTOTAL(9,N5:N14) -> 0
A16: Prelim | B16: Sec1/2 | D16: A | E16: GENERAL MATTERS AND OBLIGATIONS (CONT'D) | I16: =ROUND(H16*G16,2) -> 0 | J16: =ROUNDUP(I16,0) -> 0 | M16: =ROUND(L16*G16,2) -> 0 | N16: =ROUNDUP(M16,0) -> 0
A17: Prelim | B17: Sec1/2 | D17: 3 | E17: CONDITIONS OF CONTRACT | I17: =ROUND(H17*G17,2) -> 0 | J17: =ROUNDUP(I17,0) -> 0 | M17: =ROUND(L17*G17,2) -> 0 | N17: =ROUNDUP(M17,0) -> 0
A18: Prelim | B18: Sec1/2 | E18: The Conditions of Contract to be used shall be the latest edition of the Public Sector Standard Conditions of Contract (PSSCOC) for Design and Build 2020 issued by the Building and Construction Authority (BCA), including List of Amendments, Appendix, any Option Modules and Particular Conditions of Contract and Particular Conditions of Contract for Contingency Works. | I18: =ROUND(H18*G18,2) -> 0 | J18: =ROUNDUP(I18,0) -> 0 | M18: =ROUND(L18*G18,2) -> 0 | N18: =ROUNDUP(M18,0) -> 0
A19: Prelim | B19: Sec1/2 | E19: The Contractor shall be bound by all the documents forming this Contract and he shall be deemed to have acquainted himself with all such documents before tendering as the Employer shall not entertain any claim for extra payment or time for the lack of knowledge. | I19: =ROUND(H19*G19,2) -> 0 | J19: =ROUNDUP(I19,0) -> 0 | M19: =ROUND(L19*G19,2) -> 0 | N19: =ROUNDUP(M19,0) -> 0
A20: Prelim | B20: Sec1/2 | D20: 4 | E20: FIRM PRICE CONTRACT | I20: =ROUND(H20*G20,2) -> 0 | J20: =ROUNDUP(I20,0) -> 0 | M20: =ROUND(L20*G20,2) -> 0 | N20: =ROUNDUP(M20,0) -> 0
A21: Prelim | B21: Sec1/2 | E21: This is a Lump Sum Contract without adjustments due to any fluctuations in the cost of labour, materials, plant, equipment, tools, transport, exchange rates and/or taxation. | I21: =ROUND(H21*G21,2) -> 0 | J21: =ROUNDUP(I21,0) -> 0 | M21: =ROUND(L21*G21,2) -> 0 | N21: =ROUNDUP(M21,0) -> 0
A22: Prelim | B22: Sec1/2 | E22: The Contract or the Contract Sum shall only be adjusted in accordance with the provisions of the Contract Documents. | I22: =ROUND(H22*G22,2) -> 0 | J22: =ROUNDUP(I22,0) -> 0 | M22: =ROUND(L22*G22,2) -> 0 | N22: =ROUNDUP(M22,0) -> 0
A23: Prelim | B23: Sec1/2 | E23: Any variations requring the omission of work, materials or goods shall be valued by measurement in accordance with Clause 20.1 of the Conditions of Contract, applying the relevant unit rates (or pro-rated unit rates, as the case may be) found in the Schedule of Works and/or Schedule of Rates. | I23: =ROUND(H23*G23,2) -> 0 | J23: =ROUNDUP(I23,0) -> 0 | M23: =ROUND(L23*G23,2) -> 0 | N23: =ROUNDUP(M23,0) -> 0
A24: Prelim | B24: Sec1/2 | E24: The Contractor shall provide everything necessary for the proper execution of the Works according to the true intent and meaning of the documents forming this Contract. Unless otherwise specifically stated, the following shall be deemed to be included in the Contract Sum: (a) Labour and all costs in connection therewith and any items of expenditure which are not allowed for elsewhere such as holidays with pay, Central Provident Fund contributions, Workers' Levy, Payroll Tax, travelling time and fares and any costs arising from recruiting foreign labourers, bonuses, preparatory and temporary work and all prefabrication work, and for delays due to exceptionally adverse weather conditions, and for working on shifts and/or overtime (if permitted by the SO); | I24: =ROUND(H24*G24,2) -> 0 | J24: =ROUNDUP(I24,0) -> 0 | M24: =ROUND(L24*G24,2) -> 0 | N24: =ROUNDUP(M24,0) -> 0
A25: Prelim | B25: Sec1/2 | E25: (b) Materials/goods/Plant and costs in connection therewith, including preparatory and temporary works and fittings and fixing goods/materials/Plant in position, wastage, fabrication costs, delivering, unloading, transferring, storing, returning packaging, handling, hoisting and lowering etc. inclusive of adequate protection; | I25: =ROUND(H25*G25,2) -> 0 | J25: =ROUNDUP(I25,0) -> 0 | M25: =ROUND(L25*G25,2) -> 0 | N25: =ROUNDUP(M25,0) -> 0
A26: Collection | B26: =+B25 -> Sec1/2 | E26: To Collection S$ | J26: =SUBTOTAL(9,J16:J25) -> 0 | N26: =SUBTOTAL(9,N16:N25) -> 0
A27: Prelim | B27: Sec1/3 | D27: A | E27: GENERAL MATTERS AND OBLIGATIONS (CONT'D) | I27: =ROUND(H27*G27,2) -> 0 | J27: =ROUNDUP(I27,0) -> 0 | M27: =ROUND(L27*G27,2) -> 0 | N27: =ROUNDUP(M27,0) -> 0
A28: Prelim | B28: Sec1/3 | D28: 4 | E28: FIRM PRICE CONTRACT (CONT'D) | I28: =ROUND(H28*G28,2) -> 0 | J28: =ROUNDUP(I28,0) -> 0 | M28: =ROUND(L28*G28,2) -> 0 | N28: =ROUNDUP(M28,0) -> 0
A29: Prelim | B29: Sec1/3 | E29: (c) Use of Construction Equipment, tools and vehicles, including maintenance and supply of fuel and other equipment necessary for the proper execution and completion of the Works, and all idle time, dismantling and removal of Construction Equipment, etc. off the site; | I29: =ROUND(H29*G29,2) -> 0 | J29: =ROUNDUP(I29,0) -> 0 | M29: =ROUND(L29*G29,2) -> 0 | N29: =ROUNDUP(M29,0) -> 0
A30: Prelim | B30: Sec1/3 | E30: (d) Complying with all the requirements of the Contract Documents, whether any requirement may or may not be particularly shown or described, provided that the same can be reasonably inferred therefrom, and any other obligations necessary for the proper execution, completion and maintenance of the Works. | I30: =ROUND(H30*G30,2) -> 0 | J30: =ROUNDUP(I30,0) -> 0 | M30: =ROUND(L30*G30,2) -> 0 | N30: =ROUNDUP(M30,0) -> 0
A31: Prelim | B31: Sec1/3 | E31: The onus of investigating and ascertaining the actual extent and nature of the Works contained in this Contract, prior to submission of the Tender, is solely with the Contractor. Any doubt as to the actual extent or nature of the Works should be clarified before the submission of Tender, as no subsequent claim arising out of lack of clarity or availability of information in respect of the Contract Documents shall be entertained. The Contractor shall be deemed to have made the necessary allowance for all and any contingency on account of this provision in the Contract Sum. | I31: =ROUND(H31*G31,2) -> 0 | J31: =ROUNDUP(I31,0) -> 0 | M31: =ROUND(L31*G31,2) -> 0 | N31: =ROUNDUP(M31,0) -> 0
A32: Prelim | B32: Sec1/3 | D32: 5 | E32: DISCREPANCIES IN DRAWINGS AND SPECIFICATIONS | I32: =ROUND(H32*G32,2) -> 0 | J32: =ROUNDUP(I32,0) -> 0 | M32: =ROUND(L32*G32,2) -> 0 | N32: =ROUNDUP(M32,0) -> 0
A33: Prelim | B33: Sec1/3 | E33: The Works shall be carried out in accordance with the Specifications and Drawings and such further instructions as may from time to time be issued by the SO. | I33: =ROUND(H33*G33,2) -> 0 | J33: =ROUNDUP(I33,0) -> 0 | M33: =ROUND(L33*G33,2) -> 0 | N33: =ROUNDUP(M33,0) -> 0
A34: Prelim | B34: Sec1/3 | E34: Where Works are not specified but shown on the Drawings, or can reasonably be inferred to be part of the Contract, and vice-versa, they shall be carried out as directed and to the entire satisfaction of the SO for the proper execution and completion of the Contract. The Contractor shall be deemed to have allowed for any additional costs and expenses incurred for complying with this provision. | I34: =ROUND(H34*G34,2) -> 0 | J34: =ROUNDUP(I34,0) -> 0 | M34: =ROUND(L34*G34,2) -> 0 | N34: =ROUNDUP(M34,0) -> 0
A35: Prelim | B35: Sec1/3 | E35: The Contractor shall check and verify all dimensions in the Drawings before commencement of Works. Engineering Drawings shall be verified against each other and against Architectural Drawings. | I35: =ROUND(H35*G35,2) -> 0 | J35: =ROUNDUP(I35,0) -> 0 | M35: =ROUND(L35*G35,2) -> 0 | N35: =ROUNDUP(M35,0) -> 0
A36: Prelim | B36: Sec1/3 | E36: In case of discrepancy between the figured dimensions and scaled dimensions, the figured dimensions shall prevail and the Contractor shall notify the SO in writing of such discrepancy. | I36: =ROUND(H36*G36,2) -> 0 | J36: =ROUNDUP(I36,0) -> 0 | M36: =ROUND(L36*G36,2) -> 0 | N36: =ROUNDUP(M36,0) -> 0
A37: Prelim | B37: Sec1/3 | E37: If the Works are completed without the discrepancies being brought to the attention of the SO for his decision, the Works shall then be deemed to be constructed in error by the Contractor who shall bear all costs of rectification. No claims for extension of time shall be entertained. | I37: =ROUND(H37*G37,2) -> 0 | J37: =ROUNDUP(I37,0) -> 0 | M37: =ROUND(L37*G37,2) -> 0 | N37: =ROUNDUP(M37,0) -> 0
A38: Collection | B38: =+B37 -> Sec1/3 | E38: To Collection S$ | J38: =SUBTOTAL(9,J27:J37) -> 0 | N38: =SUBTOTAL(9,N27:N37) -> 0
A39: Prelim | B39: Sec1/4 | D39: A | E39: GENERAL MATTERS AND OBLIGATIONS (CONT'D) | I39: =ROUND(H39*G39,2) -> 0 | J39: =ROUNDUP(I39,0) -> 0 | M39: =ROUND(L39*G39,2) -> 0 | N39: =ROUNDUP(M39,0) -> 0
A40: Prelim | B40: Sec1/4 | D40: 6 | E40: LABOUR, PLANT AND TOOLS | I40: =ROUND(H40*G40,2) -> 0 | J40: =ROUNDUP(I40,0) -> 0 | M40: =ROUND(L40*G40,2) -> 0 | N40: =ROUNDUP(M40,0) -> 0
A41: Prelim | B41: Sec1/4 | E41: The Contractor shall provide all necessary labour, plant and tools for the proper and efficient execution of the Works. He shall provide for any transport for labour and for the movement of plant and equipment to and from site, erection, dismantling, moving about site as necessary and including allowance for all idle time. | I41: =ROUND(H41*G41,2) -> 0 | J41: =ROUNDUP(I41,0) -> 0 | M41: =ROUND(L41*G41,2) -> 0 | N41: =ROUNDUP(M41,0) -> 0
A42: Prelim | B42: Sec1/4 | E42: The Contractor shall not install and/or use any electrical installation, machines or apparatus that may cause heavy power surge, high frequency voltage and current, air borne noise, vibration or any electrical or mechanical interference or disturbance whatsoever which may prevent in any way the service or use of any communication system or affect the operation of other equipment, installations, machinery, apparatus or plant. | I42: =ROUND(H42*G42,2) -> 0 | J42: =ROUNDUP(I42,0) -> 0 | M42: =ROUND(L42*G42,2) -> 0 | N42: =ROUNDUP(M42,0) -> 0
A43: Prelim | B43: Sec1/4 | E43: All high-rise equipment shall be lighted in accordance with the Authorities’ requirements and standards during the Works, including non-operational hours. | I43: =ROUND(H43*G43,2) -> 0 | J43: =ROUNDUP(I43,0) -> 0 | M43: =ROUND(L43*G43,2) -> 0 | N43: =ROUNDUP(M43,0) -> 0
A44: Prelim | B44: Sec1/4 | E44: The Contractor shall complete in detail the Schedule of Plant in the Appendix TSR/4. Any item listed shall be available for inspection by the Superintending Officer, either prior to or after acceptance of the tender. | I44: =ROUND(H44*G44,2) -> 0 | J44: =ROUNDUP(I44,0) -> 0 | M44: =ROUND(L44*G44,2) -> 0 | N44: =ROUNDUP(M44,0) -> 0
A45: Prelim | B45: Sec1/4 | D45: 7 | E45: WORKING DAYS AND WORKING HOURS | I45: =ROUND(H45*G45,2) -> 0 | J45: =ROUNDUP(I45,0) -> 0 | M45: =ROUND(L45*G45,2) -> 0 | N45: =ROUNDUP(M45,0) -> 0
A46: Prelim | B46: Sec1/4 | E46: The Contractor shall comply with the rules and regulations affecting work hours on Site and noise level control as required by the | I46: =ROUND(H46*G46,2) -> 0 | J46: =ROUNDUP(I46,0) -> 0 | M46: =ROUND(L46*G46,2) -> 0 | N46: =ROUNDUP(M46,0) -> 0
A47: Prelim | B47: Sec1/4 | E47: Normal working hours shall be as follows, work beyond this hour is subject to Superintending Officer’s approval. | I47: =ROUND(H47*G47,2) -> 0 | J47: =ROUNDUP(I47,0) -> 0 | M47: =ROUND(L47*G47,2) -> 0 | N47: =ROUNDUP(M47,0) -> 0
A48: Prelim | B48: Sec1/4 | E48: Monday to Friday : 8.30am to 5.30pm Saturday : 8.30am to 12.30pm | I48: =ROUND(H48*G48,2) -> 0 | J48: =ROUNDUP(I48,0) -> 0 | M48: =ROUND(L48*G48,2) -> 0 | N48: =ROUNDUP(M48,0) -> 0
A49: Prelim | B49: Sec1/4 | E49: Work can only be performed during the working hours permitted by the Authorities. No work shall be executed on the Site within such periods as prohibited by the Authorities. | I49: =ROUND(H49*G49,2) -> 0 | J49: =ROUNDUP(I49,0) -> 0 | M49: =ROUND(L49*G49,2) -> 0 | N49: =ROUNDUP(M49,0) -> 0
A50: Collection | B50: =+B49 -> Sec1/4 | E50: To Collection S$ | J50: =SUBTOTAL(9,J39:J49) -> 0 | N50: =SUBTOTAL(9,N39:N49) -> 0
A51: Prelim | B51: Sec1/5 | D51: A | E51: GENERAL MATTERS AND OBLIGATIONS (CONT'D) | I51: =ROUND(H51*G51,2) -> 0 | J51: =ROUNDUP(I51,0) -> 0 | M51: =ROUND(L51*G51,2) -> 0 | N51: =ROUNDUP(M51,0) -> 0
A52: Prelim | B52: Sec1/5 | D52: 8 | E52: OVERTIME AND BONUS PAYMENTS | I52: =ROUND(H52*G52,2) -> 0 | J52: =ROUNDUP(I52,0) -> 0 | M52: =ROUND(L52*G52,2) -> 0 | N52: =ROUNDUP(M52,0) -> 0
A53: Prelim | B53: Sec1/5 | E53: The Contractor shall allow in his tender for all bonus payments, other incentive payment schemes and payment for overtime work. | I53: =ROUND(H53*G53,2) -> 0 | J53: =ROUNDUP(I53,0) -> 0 | M53: =ROUND(L53*G53,2) -> 0 | N53: =ROUNDUP(M53,0) -> 0
A54: Prelim | B54: Sec1/5 | E54: Overtime shall not be ordered on this Contract by the Superintending Officer to assist the Contractor to obtain or retain labour or to assist the Contractor to catch up on delays in the progress of his works. The Contractor, if he considers that overtime is necessary to complete the Contract by the Time for Completion, shall allow for such a contingency in his tender price and/or to bear all such costs as may become necessary. | I54: =ROUND(H54*G54,2) -> 0 | J54: =ROUNDUP(I54,0) -> 0 | M54: =ROUND(L54*G54,2) -> 0 | N54: =ROUNDUP(M54,0) -> 0
A55: Prelim | B55: Sec1/5 | E55: In any event, all overtime works shall be approved by the Superintending Officer and when such permission has been granted, it shall not entitle the Contractor to claim any extra costs whatsoever. | I55: =ROUND(H55*G55,2) -> 0 | J55: =ROUNDUP(I55,0) -> 0 | M55: =ROUND(L55*G55,2) -> 0 | N55: =ROUNDUP(M55,0) -> 0
A56: Prelim | B56: Sec1/5 | D56: 9 | E56: CLOSED-CIRCUIT TELEVISION CAMERAS (CCTV) FOR | I56: =ROUND(H56*G56,2) -> 0 | J56: =ROUNDUP(I56,0) -> 0 | M56: =ROUND(L56*G56,2) -> 0 | N56: =ROUNDUP(M56,0) -> 0
A57: Prelim | B57: Sec1/5 | E57: DEMOLITION WORKS | I57: =ROUND(H57*G57,2) -> 0 | J57: =ROUNDUP(I57,0) -> 0 | M57: =ROUND(L57*G57,2) -> 0 | N57: =ROUNDUP(M57,0) -> 0
A58: Prelim | B58: Sec1/5 | E58: The Contractor shall provide and maintain all necessary closed-circuit television cameras (CCTV) in accordance with the requirements of the Building Control Act (Cap. 29) or any subsequent amendment thereof and the Regulations made under the Building Control Act for the purpose of monitoring progress of the demolition works. | I58: =ROUND(H58*G58,2) -> 0 | J58: =ROUNDUP(I58,0) -> 0 | M58: =ROUND(L58*G58,2) -> 0 | N58: =ROUNDUP(M58,0) -> 0
A59: Prelim | B59: Sec1/5 | E59: The CCTV videos (in DVD) shall be submitted to the Superintending Officer in duplicate at weekly intervals (or at such intervals as the Superintending Officer may require), and also in such further number of copies as the Superintending Officer may direct for the Commissioner of Building Control. | I59: =ROUND(H59*G59,2) -> 0 | J59: =ROUNDUP(I59,0) -> 0 | M59: =ROUND(L59*G59,2) -> 0 | N59: =ROUNDUP(M59,0) -> 0
A60: Prelim | B60: Sec1/5 | D60: 10 | E60: MATERIALS AND GOODS | I60: =ROUND(H60*G60,2) -> 0 | J60: =ROUNDUP(I60,0) -> 0 | M60: =ROUND(L60*G60,2) -> 0 | N60: =ROUNDUP(M60,0) -> 0
A61: Prelim | B61: Sec1/5 | E61: All materials and goods shall be the best of their described kinds and shall in all cases be in exact conformity with any specification and/or as described in the Contract Documents. | I61: =ROUND(H61*G61,2) -> 0 | J61: =ROUNDUP(I61,0) -> 0 | M61: =ROUND(L61*G61,2) -> 0 | N61: =ROUNDUP(M61,0) -> 0
A62: Prelim | B62: Sec1/5 | E62: All materials and fittings shall be in strict accordance with the latest revised Singapore Standards (SS), Eurocodes (EN / SS EN) and/or British Standards (BS). | I62: =ROUND(H62*G62,2) -> 0 | J62: =ROUNDUP(I62,0) -> 0 | M62: =ROUND(L62*G62,2) -> 0 | N62: =ROUNDUP(M62,0) -> 0
A63: Prelim | B63: Sec1/5 | E63: The Contractor shall be responsible for all import and export regulations and shall pay all fees, taxes and charges in connection | I63: =ROUND(H63*G63,2) -> 0 | J63: =ROUNDUP(I63,0) -> 0 | M63: =ROUND(L63*G63,2) -> 0 | N63: =ROUNDUP(M63,0) -> 0
A64: Collection | B64: =+B63 -> Sec1/5 | E64: To Collection S$ | J64: =SUBTOTAL(9,J51:J63) -> 0 | N64: =SUBTOTAL(9,N51:N63) -> 0
A65: Prelim | B65: Sec1/6 | D65: A | E65: GENERAL MATTERS AND OBLIGATIONS (CONT'D) | I65: =ROUND(H65*G65,2) -> 0 | J65: =ROUNDUP(I65,0) -> 0 | M65: =ROUND(L65*G65,2) -> 0 | N65: =ROUNDUP(M65,0) -> 0
A66: Prelim | B66: Sec1/6 | D66: 11 | E66: SINGAPORE GREEN BUILDING PRODUCTS | I66: =ROUND(H66*G66,2) -> 0 | J66: =ROUNDUP(I66,0) -> 0 | M66: =ROUND(L66*G66,2) -> 0 | N66: =ROUNDUP(M66,0) -> 0
A67: Prelim | B67: Sec1/6 | E67: The Contractor shall ensure that all relevant products and materials used and/or incorporated in the Works have been certified under the Singapore Green Building Product Certification (SGBPC) scheme implemented by the Singapore Green Building Council through SGBC Pte Ltd (SGBC). | I67: =ROUND(H67*G67,2) -> 0 | J67: =ROUNDUP(I67,0) -> 0 | M67: =ROUND(L67*G67,2) -> 0 | N67: =ROUNDUP(M67,0) -> 0
A68: Prelim | B68: Sec1/6 | E68: Where the SGBPC scheme is not applicable for the relevant product or material, the Contractor shall comply with the Singapore Green Labelling Scheme (SGLS) administered by the Singapore Environment Council (SEC) or such other associated eco-labelling schemes as specified and/or approved by the Superintending Officer including but not limited to the Singapore Energy Efficiency Scheme administered by the National Environment Agency and the Mandatory Water Efficiency Labelling Scheme (WELS) administered by the Public Utilities Board (PUB). | I68: =ROUND(H68*G68,2) -> 0 | J68: =ROUNDUP(I68,0) -> 0 | M68: =ROUND(L68*G68,2) -> 0 | N68: =ROUNDUP(M68,0) -> 0
A69: Prelim | B69: Sec1/6 | E69: The Contractor shall submit documentary evidence of certification in respect of the certified materials and products to the Superintending Officer and shall further ensure that where appropriate, such materials and/or products are identified and affixed with the appropriate SGBC – SGBPC label, GreenLabel and/or such other eco-labels issued by the relevant bodies or agencies. | I69: =ROUND(H69*G69,2) -> 0 | J69: =ROUNDUP(I69,0) -> 0 | M69: =ROUND(L69*G69,2) -> 0 | N69: =ROUNDUP(M69,0) -> 0
A70: Prelim | B70: Sec1/6 | E70: In the event a material or product with a lower rating / level awarded by the relevant bodies or agencies under the appropriate eco-labelling scheme has been specified for the Works, the Contractor shall assist to propose alternative materials or products with a higher rating / level which are likely to offer cost benefits for consideration by the Superintending Officer. | I70: =ROUND(H70*G70,2) -> 0 | J70: =ROUNDUP(I70,0) -> 0 | M70: =ROUND(L70*G70,2) -> 0 | N70: =ROUNDUP(M70,0) -> 0
A71: Prelim | B71: Sec1/6 | E71: If the Superintending Officer requests, the Contractor shall provide, at his own cost, a full proposal complete with details and samples of the material and/or product with the higher rating / level than that specified, the time and cost implications and benefits (including any cost savings) arising from the proposal. The Superintending Officer shall consider, but is not bound to accept, the Contractor’s proposal. In the event that the Superintending Officer rejects the proposal, the Contractor shall not be entitled to claim any extension of time and/or additional payment. | I71: =ROUND(H71*G71,2) -> 0 | J71: =ROUNDUP(I71,0) -> 0 | M71: =ROUND(L71*G71,2) -> 0 | N71: =ROUNDUP(M71,0) -> 0
A72: Collection | B72: =+B71 -> Sec1/6 | E72: To Collection S$ | J72: =SUBTOTAL(9,J65:J71) -> 0 | N72: =SUBTOTAL(9,N65:N71) -> 0
A73: Prelim | B73: Sec1/7 | D73: A | E73: GENERAL MATTERS AND OBLIGATIONS (CONT'D) | I73: =ROUND(H73*G73,2) -> 0 | J73: =ROUNDUP(I73,0) -> 0 | M73: =ROUND(L73*G73,2) -> 0 | N73: =ROUNDUP(M73,0) -> 0
A74: Prelim | B74: Sec1/7 | D74: 11 | E74: SINGAPORE GREEN BUILDING PRODUCTS | I74: =ROUND(H74*G74,2) -> 0 | J74: =ROUNDUP(I74,0) -> 0 | M74: =ROUND(L74*G74,2) -> 0 | N74: =ROUNDUP(M74,0) -> 0
A75: Prelim | B75: Sec1/7 | E75: The Contractor’s proposal may be accepted in whole, any part or with modifications. If the Contractor’s proposal, whether with or without any modifications, is accepted, the Superintending Officer shall issue an instruction requiring all or part of the proposal, modified as necessary, to be used and/or incorporated in the Works and the Contractor shall comply with such instruction accordingly. | I75: =ROUND(H75*G75,2) -> 0 | J75: =ROUNDUP(I75,0) -> 0 | M75: =ROUND(L75*G75,2) -> 0 | N75: =ROUNDUP(M75,0) -> 0
A76: Prelim | B76: Sec1/7 | E76: The actual cost savings shall be valued in accordance with Clause 19 of the Conditions of Contract. The Contractor shall not be entitled to any additional payment or compensation and/or any extension of time arising from the acceptance of the proposal. | I76: =ROUND(H76*G76,2) -> 0 | J76: =ROUNDUP(I76,0) -> 0 | M76: =ROUND(L76*G76,2) -> 0 | N76: =ROUNDUP(M76,0) -> 0
A77: Prelim | B77: Sec1/7 | D77: 12 | E77: SUBSTITUTION OF MATERIALS WITH APPROVAL | I77: =ROUND(H77*G77,2) -> 0 | J77: =ROUNDUP(I77,0) -> 0 | M77: =ROUND(L77*G77,2) -> 0 | N77: =ROUNDUP(M77,0) -> 0
A78: Prelim | B78: Sec1/7 | E78: Unless the Contractor can provide documentary evidence to the Superintending Officer that the proprietary materials and/or goods referenced in the manufacturers’ catalogues and specified in the Contract Documents are no longer available and/or not possible to procure, the specified materials and/or goods shall be used under all circumstances. The Contractor may propose alternative materials and/or goods for substitution where the specified materials and/or goods are no longer available and/or not possible to procure provided they are equal or better in all respects to the specified materials and/or goods, and are approved by the Superintending Officer. | I78: =ROUND(H78*G78,2) -> 0 | J78: =ROUNDUP(I78,0) -> 0 | M78: =ROUND(L78*G78,2) -> 0 | N78: =ROUNDUP(M78,0) -> 0
A79: Prelim | B79: Sec1/7 | E79: For materials and/or goods offered for substitution or where the phrases "equal and approved" or "approved equivalent" appear after a material or product specified by trade name or the manufacturer's catalogue reference, the Contractor shall submit the proposal to the Superintending Officer for consideration, in advance of time (minimum 3 months) stating the credit or extra expenditure to be incurred and providing the supporting data and samples should he propose to use a material or product other than that specified by the trade name or the manufacturer's catalogue reference. | I79: =ROUND(H79*G79,2) -> 0 | J79: =ROUNDUP(I79,0) -> 0 | M79: =ROUND(L79*G79,2) -> 0 | N79: =ROUNDUP(M79,0) -> 0
A80: Prelim | B80: Sec1/7 | E80: The Superintending Officer may but shall not be obliged to accept any such proposals. | I80: =ROUND(H80*G80,2) -> 0 | J80: =ROUNDUP(I80,0) -> 0 | M80: =ROUND(L80*G80,2) -> 0 | N80: =ROUNDUP(M80,0) -> 0
A81: Prelim | B81: Sec1/7 | E81: Any acceptance of substitution by the Superintending Officer shall not relieve the Contractor from his responsibility for compliance with all the requirements under the Contract nor shall prejudice any subsequent claims by the Employer against the Contractor at any time in respect of the Works which are not in accordance with the Contract. | I81: =ROUND(H81*G81,2) -> 0 | J81: =ROUNDUP(I81,0) -> 0 | M81: =ROUND(L81*G81,2) -> 0 | N81: =ROUNDUP(M81,0) -> 0
A82: Collection | B82: =+B81 -> Sec1/7 | E82: To Collection S$ | J82: =SUBTOTAL(9,J73:J81) -> 0 | N82: =SUBTOTAL(9,N73:N81) -> 0
A83: Prelim | B83: Sec1/8 | D83: A | E83: GENERAL MATTERS AND OBLIGATIONS (CONT'D) | I83: =ROUND(H83*G83,2) -> 0 | J83: =ROUNDUP(I83,0) -> 0 | M83: =ROUND(L83*G83,2) -> 0 | N83: =ROUNDUP(M83,0) -> 0
A84: Prelim | B84: Sec1/8 | D84: 12 | E84: SUBSTITUTION OF MATERIALS WITH APPROVAL | I84: =ROUND(H84*G84,2) -> 0 | J84: =ROUNDUP(I84,0) -> 0 | M84: =ROUND(L84*G84,2) -> 0 | N84: =ROUNDUP(M84,0) -> 0
A85: Prelim | B85: Sec1/8 | E85: For the avoidance of doubt, any extra expenditure arising from the substitution including any changes to other parts of the Works caused by the substitution shall be borne by the Contractor. However, in the case of any credit expenditure arising from the substitution, this credit shall be returned to the Employer. | I85: =ROUND(H85*G85,2) -> 0 | J85: =ROUNDUP(I85,0) -> 0 | M85: =ROUND(L85*G85,2) -> 0 | N85: =ROUNDUP(M85,0) -> 0
A86: Prelim | B86: Sec1/8 | E86: Any delay in the Works due to late ordering or delivery of the materials and arising from substitution by the Contractor shall be the Contractor's responsibility and there shall be no entitlement to any extension of time or cost arising out of and in connection with such materials substitution. | I86: =ROUND(H86*G86,2) -> 0 | J86: =ROUNDUP(I86,0) -> 0 | M86: =ROUND(L86*G86,2) -> 0 | N86: =ROUNDUP(M86,0) -> 0
A87: Prelim | B87: Sec1/8 | D87: 13 | E87: ORDERING OF MATERIALS | I87: =ROUND(H87*G87,2) -> 0 | J87: =ROUNDUP(I87,0) -> 0 | M87: =ROUND(L87*G87,2) -> 0 | N87: =ROUNDUP(M87,0) -> 0
A88: Prelim | B88: Sec1/8 | E88: The Contractor shall place his orders for specified materials at the earliest possible date after notification of acceptance of tender or at such time as may be specifically stated elsewhere herein for any particular materials. The Contractor shall be responsible for any delays occasioned through any failure to do so. | I88: =ROUND(H88*G88,2) -> 0 | J88: =ROUNDUP(I88,0) -> 0 | M88: =ROUND(L88*G88,2) -> 0 | N88: =ROUNDUP(M88,0) -> 0
A89: Prelim | B89: Sec1/8 | E89: The Contractor shall not order materials from the quantities or sizes stated in these documents but shall be solely responsible for himself the quantities required for the Works. All dimensions shall be checked and verified by the Contractor on the Site before ordering. | I89: =ROUND(H89*G89,2) -> 0 | J89: =ROUNDUP(I89,0) -> 0 | M89: =ROUND(L89*G89,2) -> 0 | N89: =ROUNDUP(M89,0) -> 0
A90: Prelim | B90: Sec1/8 | E90: The Contractor shall not enter into any agreement for the supply of materials to the Site unless written approval has been given by the Superintending Officer on those materials which are required to have the approval of the Superintending Officer. In addition, the Employer shall not be held responsible for rejected materials delivered to Site and for materials which have been over ordered by the Contractor. | I90: =ROUND(H90*G90,2) -> 0 | J90: =ROUNDUP(I90,0) -> 0 | M90: =ROUND(L90*G90,2) -> 0 | N90: =ROUNDUP(M90,0) -> 0
A91: Prelim | B91: Sec1/8 | E91: Where a choice of manufacturer or source of supply is allowed for any particular product or material, the whole quantity required to complete the Works shall be of the same type, manufacture or source. | I91: =ROUND(H91*G91,2) -> 0 | J91: =ROUNDUP(I91,0) -> 0 | M91: =ROUND(L91*G91,2) -> 0 | N91: =ROUNDUP(M91,0) -> 0
A92: Prelim | B92: Sec1/8 | E92: Where the Contract is based on “provisional quantities” and the quantities are to be measured for the Statement of Final Account or the quantities are marked as "provisional", the Contractor shall take even greater discretion than usual when ordering. No entitlement to extra payment will be allowed due to loss in over or under ordering. | I92: =ROUND(H92*G92,2) -> 0 | J92: =ROUNDUP(I92,0) -> 0 | M92: =ROUND(L92*G92,2) -> 0 | N92: =ROUNDUP(M92,0) -> 0
A93: Collection | B93: =+B92 -> Sec1/8 | E93: To Collection S$ | J93: =SUBTOTAL(9,J83:J92) -> 0 | N93: =SUBTOTAL(9,N83:N92) -> 0
A94: Prelim | B94: Sec1/9 | D94: A | E94: GENERAL MATTERS AND OBLIGATIONS (CONT'D) | I94: =ROUND(H94*G94,2) -> 0 | J94: =ROUNDUP(I94,0) -> 0 | M94: =ROUND(L94*G94,2) -> 0 | N94: =ROUNDUP(M94,0) -> 0
A95: Prelim | B95: Sec1/9 | D95: 14 | E95: WARRANTY OF TITLE | I95: =ROUND(H95*G95,2) -> 0 | J95: =ROUNDUP(I95,0) -> 0 | M95: =ROUND(L95*G95,2) -> 0 | N95: =ROUNDUP(M95,0) -> 0
A96: Prelim | B96: Sec1/9 | E96: No materials and equipment for the Works shall be purchased subject to any chattel mortgage or under a conditional sale or other agreement by which an interest therein or in any part thereof is retained by the seller or supplier. | I96: =ROUND(H96*G96,2) -> 0 | J96: =ROUNDUP(I96,0) -> 0 | M96: =ROUND(L96*G96,2) -> 0 | N96: =ROUNDUP(M96,0) -> 0
A97: Prelim | B97: Sec1/9 | E97: The Contractor warrants good title to all materials and equipment installed or incorporated in the Works, and agrees, upon completion of all works, to deliver the premises together with all improvements constructed or placed thereon by him to the Employer free from any claims, lien or charges. | I97: =ROUND(H97*G97,2) -> 0 | J97: =ROUNDUP(I97,0) -> 0 | M97: =ROUND(L97*G97,2) -> 0 | N97: =ROUNDUP(M97,0) -> 0
A98: Prelim | B98: Sec1/9 | D98: 15 | E98: BRANCH OFFICE CONTRACTORS | I98: =ROUND(H98*G98,2) -> 0 | J98: =ROUNDUP(I98,0) -> 0 | M98: =ROUND(L98*G98,2) -> 0 | N98: =ROUNDUP(M98,0) -> 0
A99: Prelim | B99: Sec1/9 | E99: Where the Contractor is a Branch Office whose Main/ Head Office is incorporated outside of Singapore, the Contractor shall provide the following document upon award. | I99: =ROUND(H99*G99,2) -> 0 | J99: =ROUNDUP(I99,0) -> 0 | M99: =ROUND(L99*G99,2) -> 0 | N99: =ROUNDUP(M99,0) -> 0
A100: Prelim | B100: Sec1/9 | E100: 1. Power of Attorney and Board of Directors’ Resolutions authorising Branch Office authorised agents to enter into Contract. | I100: =ROUND(H100*G100,2) -> 0 | J100: =ROUNDUP(I100,0) -> 0 | M100: =ROUND(L100*G100,2) -> 0 | N100: =ROUNDUP(M100,0) -> 0
...

Sheet 2_Professional Fees
A1: Tender No: CE/25/T5/P/896 | L1: Generally | R1: Markup
R2: A | S2: 0.2
A3: SECTION 2 | R3: B | S3: 0.1 | T3: PC rate
A4: DESIGN AND BUILD OF COASTAL DORMITORY EXPANSION FOR CHANGI EAST DEVELOPMENT | R4: C
A6: CODE | B6: PAGE | C6: ITEM | D6: DESCRIPTION | E6: UNIT | F6: Material (S$) | G6: Labour (S$) | H6: U/RATE (S$) | I6: Phase A Qty | J6: Phase A Sub-Total | K6: Phase A Amount (S$) | L6: Phase B Qty | M6: Phase B Sub-Total | N6: Phase B Amount (S$) | O6: REMARKS | Q6: MARKUP CODE | R6: SUBMISSION AMOUNT (S$) | S6: SUBMISSION AMOUNT (S$)
A7: Architect | B7: Sec 2.1/1 | D7: SECTION NO 2.1 - PROFESSIONAL FEES | H7: =+SUM(F7:G7) -> 0 | J7: =+ROUND(I7*H7,2) -> 0 | M7: =+ROUND(L7*H7,2) -> 0 | Q7: A | R7: =+ROUND((K7)*(1+SUMIF($R$2:$R$4,Q7,$S$2:$S$4)),0) -> 0 | S7: =+ROUND((N7)*(1+SUMIF($R$2:$R$4,Q7,$S$2:$S$4)),0) -> 0
A8: Architect | B8: =+B7 -> Sec 2.1/1 | H8: =+SUM(F8:G8) -> 0 | J8: =+ROUND(I8*H8,2) -> 0 | M8: =+ROUND(L8*H8,2) -> 0 | Q8: A | R8: =+ROUND((K8)*(1+SUMIF($R$2:$R$4,Q8,$S$2:$S$4)),0) -> 0 | S8: =+ROUND((N8)*(1+SUMIF($R$2:$R$4,Q8,$S$2:$S$4)),0) -> 0
A9: Architect | B9: =+B8 -> Sec 2.1/1 | C9: 1 | D9: ARCHITECT | H9: =+SUM(F9:G9) -> 0 | J9: =+ROUND(I9*H9,2) -> 0 | M9: =+ROUND(L9*H9,2) -> 0 | Q9: A | R9: =+ROUND((K9)*(1+SUMIF($R$2:$R$4,Q9,$S$2:$S$4)),0) -> 0 | S9: =+ROUND((N9)*(1+SUMIF($R$2:$R$4,Q9,$S$2:$S$4)),0) -> 0
A10: Architect | B10: =+B9 -> Sec 2.1/1 | H10: =+SUM(F10:G10) -> 0 | J10: =+ROUND(I10*H10,2) -> 0 | M10: =+ROUND(L10*H10,2) -> 0 | Q10: A | R10: =+ROUND((K10)*(1+SUMIF($R$2:$R$4,Q10,$S$2:$S$4)),0) -> 0 | S10: =+ROUND((N10)*(1+SUMIF($R$2:$R$4,Q10,$S$2:$S$4)),0) -> 0
A11: Architect | B11: =+B10 -> Sec 2.1/1 | C11: 1.1 | D11: Design Development Stage | H11: =+SUM(F11:G11) -> 0 | J11: =+ROUND(I11*H11,2) -> 0 | M11: =+ROUND(L11*H11,2) -> 0 | Q11: A | R11: =+ROUND((K11)*(1+SUMIF($R$2:$R$4,Q11,$S$2:$S$4)),0) -> 0 | S11: =+ROUND((N11)*(1+SUMIF($R$2:$R$4,Q11,$S$2:$S$4)),0) -> 0
A12: Architect | B12: =+B11 -> Sec 2.1/1 | H12: =+SUM(F12:G12) -> 0 | J12: =+ROUND(I12*H12,2) -> 0 | M12: =+ROUND(L12*H12,2) -> 0 | Q12: A | R12: =+ROUND((K12)*(1+SUMIF($R$2:$R$4,Q12,$S$2:$S$4)),0) -> 0 | S12: =+ROUND((N12)*(1+SUMIF($R$2:$R$4,Q12,$S$2:$S$4)),0) -> 0
A13: Architect | B13: =+B12 -> Sec 2.1/1 | C13: a | D13: Make submissions such as Development Control (DC) submission (where applicable) to relevant technical departments (for architectural works) for clearance | E13: 0.15 | G13: 0 | H13: =+SUM(F13:G13) -> 0 | J13: =+ROUND(I13*H13,2) -> 0 | K13: =SUM(J13:J13) -> 0 | M13: =+ROUND(L13*H13,2) -> 0 | N13: =SUM(M13:M13) -> 0 | Q13: A | R13: =+ROUND((K13)*(1+SUMIF($R$2:$R$4,Q13,$S$2:$S$4)),0) -> 0 | S13: =+ROUND((N13)*(1+SUMIF($R$2:$R$4,Q13,$S$2:$S$4)),0) -> 0
A14: Architect | B14: =+B13 -> Sec 2.1/1 | H14: =+SUM(F14:G14) -> 0 | J14: =+ROUND(I14*H14,2) -> 0 | M14: =+ROUND(L14*H14,2) -> 0 | Q14: A | R14: =+ROUND((K14)*(1+SUMIF($R$2:$R$4,Q14,$S$2:$S$4)),0) -> 0 | S14: =+ROUND((N14)*(1+SUMIF($R$2:$R$4,Q14,$S$2:$S$4)),0) -> 0
A15: Architect | B15: =+B14 -> Sec 2.1/1 | C15: b | D15: Obtain clearances (DC clearance) from relevant technical departments (for architectural works) | E15: 0.1 | G15: 0 | H15: =+SUM(F15:G15) -> 0 | J15: =+ROUND(I15*H15,2) -> 0 | K15: =SUM(J15:J15) -> 0 | M15: =+ROUND(L15*H15,2) -> 0 | N15: =SUM(M15:M15) -> 0 | Q15: A | R15: =+ROUND((K15)*(1+SUMIF($R$2:$R$4,Q15,$S$2:$S$4)),0) -> 0 | S15: =+ROUND((N15)*(1+SUMIF($R$2:$R$4,Q15,$S$2:$S$4)),0) -> 0
A16: Architect | B16: =+B15 -> Sec 2.1/1 | H16: =+SUM(F16:G16) -> 0 | J16: =+ROUND(I16*H16,2) -> 0 | M16: =+ROUND(L16*H16,2) -> 0 | Q16: A | R16: =+ROUND((K16)*(1+SUMIF($R$2:$R$4,Q16,$S$2:$S$4)),0) -> 0 | S16: =+ROUND((N16)*(1+SUMIF($R$2:$R$4,Q16,$S$2:$S$4)),0) -> 0
A17: Architect | B17: =+B16 -> Sec 2.1/1 | C17: c | D17: Obtain Building Plan approval from relevant technical departments (for architectural works) | E17: 0.05 | G17: 0 | H17: =+SUM(F17:G17) -> 0 | J17: =+ROUND(I17*H17,2) -> 0 | K17: =SUM(J17:J17) -> 0 | M17: =+ROUND(L17*H17,2) -> 0 | N17: =SUM(M17:M17) -> 0 | Q17: A | R17: =+ROUND((K17)*(1+SUMIF($R$2:$R$4,Q17,$S$2:$S$4)),0) -> 0 | S17: =+ROUND((N17)*(1+SUMIF($R$2:$R$4,Q17,$S$2:$S$4)),0) -> 0
A18: Architect | B18: =+B17 -> Sec 2.1/1 | H18: =+SUM(F18:G18) -> 0 | J18: =+ROUND(I18*H18,2) -> 0 | M18: =+ROUND(L18*H18,2) -> 0 | Q18: A | R18: =+ROUND((K18)*(1+SUMIF($R$2:$R$4,Q18,$S$2:$S$4)),0) -> 0 | S18: =+ROUND((N18)*(1+SUMIF($R$2:$R$4,Q18,$S$2:$S$4)),0) -> 0
A19: Architect | B19: =+B18 -> Sec 2.1/1 | C19: 1.2 | D19: Construction | H19: =+SUM(F19:G19) -> 0 | J19: =+ROUND(I19*H19,2) -> 0 | M19: =+ROUND(L19*H19,2) -> 0 | Q19: A | R19: =+ROUND((K19)*(1+SUMIF($R$2:$R$4,Q19,$S$2:$S$4)),0) -> 0 | S19: =+ROUND((N19)*(1+SUMIF($R$2:$R$4,Q19,$S$2:$S$4)),0) -> 0
A20: Architect | B20: =+B19 -> Sec 2.1/1 | H20: =+SUM(F20:G20) -> 0 | J20: =+ROUND(I20*H20,2) -> 0 | M20: =+ROUND(L20*H20,2) -> 0 | Q20: A | R20: =+ROUND((K20)*(1+SUMIF($R$2:$R$4,Q20,$S$2:$S$4)),0) -> 0 | S20: =+ROUND((N20)*(1+SUMIF($R$2:$R$4,Q20,$S$2:$S$4)),0) -> 0
A21: Architect | B21: =+B20 -> Sec 2.1/1 | C21: a | D21: During construction period in monthly instalments | E21: 0.5 | G21: 0 | H21: =+SUM(F21:G21) -> 0 | J21: =+ROUND(I21*H21,2) -> 0 | K21: =SUM(J21:J21) -> 0 | M21: =+ROUND(L21*H21,2) -> 0 | N21: =SUM(M21:M21) -> 0 | Q21: A | R21: =+ROUND((K21)*(1+SUMIF($R$2:$R$4,Q21,$S$2:$S$4)),0) -> 0 | S21: =+ROUND((N21)*(1+SUMIF($R$2:$R$4,Q21,$S$2:$S$4)),0) -> 0
A22: Architect | B22: =+B21 -> Sec 2.1/1 | H22: =+SUM(F22:G22) -> 0 | J22: =+ROUND(I22*H22,2) -> 0 | M22: =+ROUND(L22*H22,2) -> 0 | Q22: A | R22: =+ROUND((K22)*(1+SUMIF($R$2:$R$4,Q22,$S$2:$S$4)),0) -> 0 | S22: =+ROUND((N22)*(1+SUMIF($R$2:$R$4,Q22,$S$2:$S$4)),0) -> 0
A23: Architect | B23: =+B22 -> Sec 2.1/1 | C23: 1.3 | D23: Completion | H23: =+SUM(F23:G23) -> 0 | J23: =+ROUND(I23*H23,2) -> 0 | M23: =+ROUND(L23*H23,2) -> 0 | Q23: A | R23: =+ROUND((K23)*(1+SUMIF($R$2:$R$4,Q23,$S$2:$S$4)),0) -> 0 | S23: =+ROUND((N23)*(1+SUMIF($R$2:$R$4,Q23,$S$2:$S$4)),0) -> 0
A24: Architect | B24: =+B23 -> Sec 2.1/1 | H24: =+SUM(F24:G24) -> 0 | J24: =+ROUND(I24*H24,2) -> 0 | M24: =+ROUND(L24*H24,2) -> 0 | Q24: A | R24: =+ROUND((K24)*(1+SUMIF($R$2:$R$4,Q24,$S$2:$S$4)),0) -> 0 | S24: =+ROUND((N24)*(1+SUMIF($R$2:$R$4,Q24,$S$2:$S$4)),0) -> 0
A25: Architect | B25: =+B24 -> Sec 2.1/1 | C25: a | D25: Upon substantial completion and obtain Temporary Occupation Permit (TOP) | E25: 0.1 | G25: 0 | H25: =+SUM(F25:G25) -> 0 | J25: =+ROUND(I25*H25,2) -> 0 | K25: =SUM(J25:J25) -> 0 | M25: =+ROUND(L25*H25,2) -> 0 | N25: =SUM(M25:M25) -> 0 | Q25: A | R25: =+ROUND((K25)*(1+SUMIF($R$2:$R$4,Q25,$S$2:$S$4)),0) -> 0 | S25: =+ROUND((N25)*(1+SUMIF($R$2:$R$4,Q25,$S$2:$S$4)),0) -> 0
A26: Architect | B26: =+B25 -> Sec 2.1/1 | H26: =+SUM(F26:G26) -> 0 | J26: =+ROUND(I26*H26,2) -> 0 | M26: =+ROUND(L26*H26,2) -> 0 | Q26: A | R26: =+ROUND((K26)*(1+SUMIF($R$2:$R$4,Q26,$S$2:$S$4)),0) -> 0 | S26: =+ROUND((N26)*(1+SUMIF($R$2:$R$4,Q26,$S$2:$S$4)),0) -> 0
A27: Architect | B27: =+B26 -> Sec 2.1/1 | C27: b | D27: Verifying defects rectification and submission of documents (warranties, manuals, as-built drawings) | E27: 0.05 | G27: 0 | H27: =+SUM(F27:G27) -> 0 | J27: =+ROUND(I27*H27,2) -> 0 | K27: =SUM(J27:J27) -> 0 | M27: =+ROUND(L27*H27,2) -> 0 | N27: =SUM(M27:M27) -> 0 | Q27: A | R27: =+ROUND((K27)*(1+SUMIF($R$2:$R$4,Q27,$S$2:$S$4)),0) -> 0 | S27: =+ROUND((N27)*(1+SUMIF($R$2:$R$4,Q27,$S$2:$S$4)),0) -> 0
A28: Architect | B28: =+B27 -> Sec 2.1/1 | H28: =+SUM(F28:G28) -> 0 | J28: =+ROUND(I28*H28,2) -> 0 | M28: =+ROUND(L28*H28,2) -> 0 | Q28: A | R28: =+ROUND((K28)*(1+SUMIF($R$2:$R$4,Q28,$S$2:$S$4)),0) -> 0 | S28: =+ROUND((N28)*(1+SUMIF($R$2:$R$4,Q28,$S$2:$S$4)),0) -> 0
A29: Architect | B29: =+B28 -> Sec 2.1/1 | C29: c | D29: Obtain Certificate of Statutory Completion (CSC) /Final Completion Certificate (for non CSC projects)/ handing over completed works to relevant Authorities | E29: 0.05 | G29: 0 | H29: =+SUM(F29:G29) -> 0 | J29: =+ROUND(I29*H29,2) -> 0 | K29: =SUM(J29:J29) -> 0 | M29: =+ROUND(L29*H29,2) -> 0 | N29: =SUM(M29:M29) -> 0 | Q29: A | R29: =+ROUND((K29)*(1+SUMIF($R$2:$R$4,Q29,$S$2:$S$4)),0) -> 0 | S29: =+ROUND((N29)*(1+SUMIF($R$2:$R$4,Q29,$S$2:$S$4)),0) -> 0
A30: Architect | B30: =+B29 -> Sec 2.1/1 | H30: =+SUM(F30:G30) -> 0 | J30: =+ROUND(I30*H30,2) -> 0 | M30: =+ROUND(L30*H30,2) -> 0 | Q30: A | R30: =+ROUND((K30)*(1+SUMIF($R$2:$R$4,Q30,$S$2:$S$4)),0) -> 0 | S30: =+ROUND((N30)*(1+SUMIF($R$2:$R$4,Q30,$S$2:$S$4)),0) -> 0
A31: Collection | B31: =+B30 -> Sec 2.1/1 | D31: To Collection: | K31: =SUM(K8:K30) -> 0 | N31: =SUM(N7:N30) -> 0 | R31: =SUM(R7:R30) -> 0 | S31: =SUM(S7:S30) -> 0
A32: Structure | B32: Sec 2.1/2 | H32: =+SUM(F32:G32) -> 0 | J32: =+ROUND(I32*H32,2) -> 0 | M32: =+ROUND(L32*H32,2) -> 0 | Q32: A | R32: =+ROUND((K32)*(1+SUMIF($R$2:$R$4,Q32,$S$2:$S$4)),0) -> 0 | S32: =+ROUND((N32)*(1+SUMIF($R$2:$R$4,Q32,$S$2:$S$4)),0) -> 0
A33: Structure | B33: Sec 2.1/2 | C33: 2 | D33: CIVIL & STRUCTURAL ENGINEER | H33: =+SUM(F33:G33) -> 0 | J33: =+ROUND(I33*H33,2) -> 0 | M33: =+ROUND(L33*H33,2) -> 0 | Q33: A | R33: =+ROUND((K33)*(1+SUMIF($R$2:$R$4,Q33,$S$2:$S$4)),0) -> 0 | S33: =+ROUND((N33)*(1+SUMIF($R$2:$R$4,Q33,$S$2:$S$4)),0) -> 0
A34: Structure | B34: =+B33 -> Sec 2.1/2 | H34: =+SUM(F34:G34) -> 0 | J34: =+ROUND(I34*H34,2) -> 0 | M34: =+ROUND(L34*H34,2) -> 0 | Q34: A | R34: =+ROUND((K34)*(1+SUMIF($R$2:$R$4,Q34,$S$2:$S$4)),0) -> 0 | S34: =+ROUND((N34)*(1+SUMIF($R$2:$R$4,Q34,$S$2:$S$4)),0) -> 0
A35: Structure | B35: =+B34 -> Sec 2.1/2 | C35: 2.1 | D35: Design Development Stage | H35: =+SUM(F35:G35) -> 0 | J35: =+ROUND(I35*H35,2) -> 0 | M35: =+ROUND(L35*H35,2) -> 0 | Q35: A | R35: =+ROUND((K35)*(1+SUMIF($R$2:$R$4,Q35,$S$2:$S$4)),0) -> 0 | S35: =+ROUND((N35)*(1+SUMIF($R$2:$R$4,Q35,$S$2:$S$4)),0) -> 0
A36: Structure | B36: =+B35 -> Sec 2.1/2 | H36: =+SUM(F36:G36) -> 0 | J36: =+ROUND(I36*H36,2) -> 0 | M36: =+ROUND(L36*H36,2) -> 0 | Q36: A | R36: =+ROUND((K36)*(1+SUMIF($R$2:$R$4,Q36,$S$2:$S$4)),0) -> 0 | S36: =+ROUND((N36)*(1+SUMIF($R$2:$R$4,Q36,$S$2:$S$4)),0) -> 0
A37: Structure | B37: =+B36 -> Sec 2.1/2 | C37: a | D37: Make submission to relevant technical departments (for C&S works) for clearance — 10% | E37: 0.1 | G37: 0 | H37: =+SUM(F37:G37) -> 0 | J37: =+ROUND(I37*H37,2) -> 0 | K37: =SUM(J37:J37) -> 0 | M37: =+ROUND(L37*H37,2) -> 0 | N37: =SUM(M37:M37) -> 0 | Q37: A | R37: =+ROUND((K37)*(1+SUMIF($R$2:$R$4,Q37,$S$2:$S$4)),0) -> 0 | S37: =+ROUND((N37)*(1+SUMIF($R$2:$R$4,Q37,$S$2:$S$4)),0) -> 0
A38: Structure | B38: =+B37 -> Sec 2.1/2 | H38: =+SUM(F38:G38) -> 0 | J38: =+ROUND(I38*H38,2) -> 0 | M38: =+ROUND(L38*H38,2) -> 0 | Q38: A | R38: =+ROUND((K38)*(1+SUMIF($R$2:$R$4,Q38,$S$2:$S$4)),0) -> 0 | S38: =+ROUND((N38)*(1+SUMIF($R$2:$R$4,Q38,$S$2:$S$4)),0) -> 0
A39: Structure | B39: =+B38 -> Sec 2.1/2 | C39: b | D39: Obtain clearance from relevant technical departments (for C&S works) | E39: 0.05 | G39: 0 | H39: =+SUM(F39:G39) -> 0 | J39: =+ROUND(I39*H39,2) -> 0 | K39: =SUM(J39:J39) -> 0 | M39: =+ROUND(L39*H39,2) -> 0 | N39: =SUM(M39:M39) -> 0 | Q39: A | R39: =+ROUND((K39)*(1+SUMIF($R$2:$R$4,Q39,$S$2:$S$4)),0) -> 0 | S39: =+ROUND((N39)*(1+SUMIF($R$2:$R$4,Q39,$S$2:$S$4)),0) -> 0
A40: Structure | B40: =+B39 -> Sec 2.1/2 | H40: =+SUM(F40:G40) -> 0 | J40: =+ROUND(I40*H40,2) -> 0 | M40: =+ROUND(L40*H40,2) -> 0 | Q40: A | R40: =+ROUND((K40)*(1+SUMIF($R$2:$R$4,Q40,$S$2:$S$4)),0) -> 0 | S40: =+ROUND((N40)*(1+SUMIF($R$2:$R$4,Q40,$S$2:$S$4)),0) -> 0
A41: Structure | B41: =+B40 -> Sec 2.1/2 | C41: c | D41: Obtain Foundation Plan approval — 5% | E41: 0.05 | G41: 0 | H41: =+SUM(F41:G41) -> 0 | J41: =+ROUND(I41*H41,2) -> 0 | K41: =SUM(J41:J41) -> 0 | M41: =+ROUND(L41*H41,2) -> 0 | N41: =SUM(M41:M41) -> 0 | Q41: A | R41: =+ROUND((K41)*(1+SUMIF($R$2:$R$4,Q41,$S$2:$S$4)),0) -> 0 | S41: =+ROUND((N41)*(1+SUMIF($R$2:$R$4,Q41,$S$2:$S$4)),0) -> 0
A42: Structure | B42: =+B41 -> Sec 2.1/2 | H42: =+SUM(F42:G42) -> 0 | J42: =+ROUND(I42*H42,2) -> 0 | M42: =+ROUND(L42*H42,2) -> 0 | Q42: A | R42: =+ROUND((K42)*(1+SUMIF($R$2:$R$4,Q42,$S$2:$S$4)),0) -> 0 | S42: =+ROUND((N42)*(1+SUMIF($R$2:$R$4,Q42,$S$2:$S$4)),0) -> 0
A43: Structure | B43: =+B42 -> Sec 2.1/2 | C43: d | D43: Obtain Structural Plan approval (for main project works) — 5% | E43: 5 | G43: 0 | H43: =+SUM(F43:G43) -> 0 | J43: =+ROUND(I43*H43,2) -> 0 | K43: =SUM(J43:J43) -> 0 | M43: =+ROUND(L43*H43,2) -> 0 | N43: =SUM(M43:M43) -> 0 | Q43: A | R43: =+ROUND((K43)*(1+SUMIF($R$2:$R$4,Q43,$S$2:$S$4)),0) -> 0 | S43: =+ROUND((N43)*(1+SUMIF($R$2:$R$4,Q43,$S$2:$S$4)),0) -> 0
A44: Structure | B44: =+B43 -> Sec 2.1/2 | H44: =+SUM(F44:G44) -> 0 | J44: =+ROUND(I44*H44,2) -> 0 | M44: =+ROUND(L44*H44,2) -> 0 | Q44: A | R44: =+ROUND((K44)*(1+SUMIF($R$2:$R$4,Q44,$S$2:$S$4)),0) -> 0 | S44: =+ROUND((N44)*(1+SUMIF($R$2:$R$4,Q44,$S$2:$S$4)),0) -> 0
A45: Structure | B45: =+B44 -> Sec 2.1/2 | C45: e | D45: Obtain Building Plan approval — 5% | E45: 0.05 | G45: 0 | H45: =+SUM(F45:G45) -> 0 | J45: =+ROUND(I45*H45,2) -> 0 | K45: =SUM(J45:J45) -> 0 | M45: =+ROUND(L45*H45,2) -> 0 | N45: =SUM(M45:M45) -> 0 | Q45: A | R45: =+ROUND((K45)*(1+SUMIF($R$2:$R$4,Q45,$S$2:$S$4)),0) -> 0 | S45: =+ROUND((N45)*(1+SUMIF($R$2:$R$4,Q45,$S$2:$S$4)),0) -> 0
A46: Structure | B46: =+B45 -> Sec 2.1/2 | H46: =+SUM(F46:G46) -> 0 | J46: =+ROUND(I46*H46,2) -> 0 | M46: =+ROUND(L46*H46,2) -> 0 | Q46: A | R46: =+ROUND((K46)*(1+SUMIF($R$2:$R$4,Q46,$S$2:$S$4)),0) -> 0 | S46: =+ROUND((N46)*(1+SUMIF($R$2:$R$4,Q46,$S$2:$S$4)),0) -> 0
A47: Structure | B47: =+B46 -> Sec 2.1/2 | C47: 2.2 | D47: Construction Stage | H47: =+SUM(F47:G47) -> 0 | J47: =+ROUND(I47*H47,2) -> 0 | M47: =+ROUND(L47*H47,2) -> 0 | Q47: A | R47: =+ROUND((K47)*(1+SUMIF($R$2:$R$4,Q47,$S$2:$S$4)),0) -> 0 | S47: =+ROUND((N47)*(1+SUMIF($R$2:$R$4,Q47,$S$2:$S$4)),0) -> 0
A48: Structure | B48: =+B47 -> Sec 2.1/2 | H48: =+SUM(F48:G48) -> 0 | J48: =+ROUND(I48*H48,2) -> 0 | M48: =+ROUND(L48*H48,2) -> 0 | Q48: A | R48: =+ROUND((K48)*(1+SUMIF($R$2:$R$4,Q48,$S$2:$S$4)),0) -> 0 | S48: =+ROUND((N48)*(1+SUMIF($R$2:$R$4,Q48,$S$2:$S$4)),0) -> 0
A49: Structure | B49: =+B48 -> Sec 2.1/2 | C49: a | D49: During construction period in monthly instalments | E49: 0.5 | G49: 0 | H49: =+SUM(F49:G49) -> 0 | J49: =+ROUND(I49*H49,2) -> 0 | K49: =SUM(J49:J49) -> 0 | M49: =+ROUND(L49*H49,2) -> 0 | N49: =SUM(M49:M49) -> 0 | Q49: A | R49: =+ROUND((K49)*(1+SUMIF($R$2:$R$4,Q49,$S$2:$S$4)),0) -> 0 | S49: =+ROUND((N49)*(1+SUMIF($R$2:$R$4,Q49,$S$2:$S$4)),0) -> 0
A50: Structure | B50: =+B49 -> Sec 2.1/2 | H50: =+SUM(F50:G50) -> 0 | J50: =+ROUND(I50*H50,2) -> 0 | M50: =+ROUND(L50*H50,2) -> 0 | Q50: A | R50: =+ROUND((K50)*(1+SUMIF($R$2:$R$4,Q50,$S$2:$S$4)),0) -> 0 | S50: =+ROUND((N50)*(1+SUMIF($R$2:$R$4,Q50,$S$2:$S$4)),0) -> 0
A51: Structure | B51: =+B50 -> Sec 2.1/2 | C51: 2.3 | D51: Completion Stage | H51: =+SUM(F51:G51) -> 0 | J51: =+ROUND(I51*H51,2) -> 0 | M51: =+ROUND(L51*H51,2) -> 0 | Q51: A | R51: =+ROUND((K51)*(1+SUMIF($R$2:$R$4,Q51,$S$2:$S$4)),0) -> 0 | S51: =+ROUND((N51)*(1+SUMIF($R$2:$R$4,Q51,$S$2:$S$4)),0) -> 0
A52: Structure | B52: =+B51 -> Sec 2.1/2 | H52: =+SUM(F52:G52) -> 0 | J52: =+ROUND(I52*H52,2) -> 0 | M52: =+ROUND(L52*H52,2) -> 0 | Q52: A | R52: =+ROUND((K52)*(1+SUMIF($R$2:$R$4,Q52,$S$2:$S$4)),0) -> 0 | S52: =+ROUND((N52)*(1+SUMIF($R$2:$R$4,Q52,$S$2:$S$4)),0) -> 0
A53: Structure | B53: =+B52 -> Sec 2.1/2 | C53: a | D53: Upon substantial completion and obtain Temporary Occupation Permit (TOP) — 10% | E53: 0.1 | G53: 0 | H53: =+SUM(F53:G53) -> 0 | J53: =+ROUND(I53*H53,2) -> 0 | K53: =SUM(J53:J53) -> 0 | M53: =+ROUND(L53*H53,2) -> 0 | N53: =SUM(M53:M53) -> 0 | Q53: A | R53: =+ROUND((K53)*(1+SUMIF($R$2:$R$4,Q53,$S$2:$S$4)),0) -> 0 | S53: =+ROUND((N53)*(1+SUMIF($R$2:$R$4,Q53,$S$2:$S$4)),0) -> 0
A54: Structure | B54: =+B53 -> Sec 2.1/2 | H54: =+SUM(F54:G54) -> 0 | J54: =+ROUND(I54*H54,2) -> 0 | M54: =+ROUND(L54*H54,2) -> 0 | Q54: A | R54: =+ROUND((K54)*(1+SUMIF($R$2:$R$4,Q54,$S$2:$S$4)),0) -> 0 | S54: =+ROUND((N54)*(1+SUMIF($R$2:$R$4,Q54,$S$2:$S$4)),0) -> 0
A55: Structure | B55: =+B54 -> Sec 2.1/2 | C55: b | D55: Obtain Certificate of Statutory Completion (CSC) / Final Completion Certificate — 10% | E55: 0.1 | G55: 0 | H55: =+SUM(F55:G55) -> 0 | J55: =+ROUND(I55*H55,2) -> 0 | K55: =SUM(J55:J55) -> 0 | M55: =+ROUND(L55*H55,2) -> 0 | N55: =SUM(M55:M55) -> 0 | Q55: A | R55: =+ROUND((K55)*(1+SUMIF($R$2:$R$4,Q55,$S$2:$S$4)),0) -> 0 | S55: =+ROUND((N55)*(1+SUMIF($R$2:$R$4,Q55,$S$2:$S$4)),0) -> 0
A56: Structure | B56: =+B55 -> Sec 2.1/2 | H56: =+SUM(F56:G56) -> 0 | J56: =+ROUND(I56*H56,2) -> 0 | M56: =+ROUND(L56*H56,2) -> 0 | Q56: A | R56: =+ROUND((K56)*(1+SUMIF($R$2:$R$4,Q56,$S$2:$S$4)),0) -> 0 | S56: =+ROUND((N56)*(1+SUMIF($R$2:$R$4,Q56,$S$2:$S$4)),0) -> 0
A57: Collection | B57: =+B56 -> Sec 2.1/2 | D57: To Collection: | K57: =SUM(K33:K56) -> 0 | N57: =SUM(N33:N56) -> 0 | R57: =SUM(R33:R56) -> 0 | S57: =SUM(S33:S56) -> 0
A58: MNE | B58: Sec 2.1/3 | H58: =+SUM(F58:G58) -> 0 | J58: =+ROUND(I58*H58,2) -> 0 | M58: =+ROUND(L58*H58,2) -> 0 | Q58: A | R58: =+ROUND((K58+N58)*(1+SUMIF($R$2:$R$4,Q58,$S$2:$S$4)),0) -> 0 | S58: =+ROUND((L58+O58)*(1+SUMIF($R$2:$R$4,R58,$S$2:$S$4)),0) -> 0
A59: MNE | B59: Sec 2.1/3 | C59: 3 | D59: MECHANICAL & ELECTRICAL ENGINEER | H59: =+SUM(F59:G59) -> 0 | J59: =+ROUND(I59*H59,2) -> 0 | M59: =+ROUND(L59*H59,2) -> 0 | Q59: A | R59: =+ROUND((K59+N59)*(1+SUMIF($R$2:$R$4,Q59,$S$2:$S$4)),0) -> 0 | S59: =+ROUND((L59+O59)*(1+SUMIF($R$2:$R$4,R59,$S$2:$S$4)),0) -> 0
A60: MNE | B60: =+B59 -> Sec 2.1/3 | H60: =+SUM(F60:G60) -> 0 | J60: =+ROUND(I60*H60,2) -> 0 | M60: =+ROUND(L60*H60,2) -> 0 | Q60: A | R60: =+ROUND((K60+N60)*(1+SUMIF($R$2:$R$4,Q60,$S$2:$S$4)),0) -> 0 | S60: =+ROUND((L60+O60)*(1+SUMIF($R$2:$R$4,R60,$S$2:$S$4)),0) -> 0
A61: MNE | B61: =+B60 -> Sec 2.1/3 | C61: 3.1 | D61: Design Development Stage | H61: =+SUM(F61:G61) -> 0 | J61: =+ROUND(I61*H61,2) -> 0 | M61: =+ROUND(L61*H61,2) -> 0 | Q61: A | R61: =+ROUND((K61+N61)*(1+SUMIF($R$2:$R$4,Q61,$S$2:$S$4)),0) -> 0 | S61: =+ROUND((L61+O61)*(1+SUMIF($R$2:$R$4,R61,$S$2:$S$4)),0) -> 0
A62: MNE | B62: =+B61 -> Sec 2.1/3 | H62: =+SUM(F62:G62) -> 0 | J62: =+ROUND(I62*H62,2) -> 0 | M62: =+ROUND(L62*H62,2) -> 0 | Q62: A | R62: =+ROUND((K62+N62)*(1+SUMIF($R$2:$R$4,Q62,$S$2:$S$4)),0) -> 0 | S62: =+ROUND((L62+O62)*(1+SUMIF($R$2:$R$4,R62,$S$2:$S$4)),0) -> 0
A63: MNE | B63: =+B62 -> Sec 2.1/3 | C63: a | D63: Make submission to relevant technical departments (for M&E works) — 15% | E63: 0.15 | G63: 0 | H63: =+SUM(F63:G63) -> 0 | J63: =+ROUND(I63*H63,2) -> 0 | K63: =SUM(J63:J63) -> 0 | M63: =+ROUND(L63*H63,2) -> 0 | N63: =SUM(M63:M63) -> 0 | Q63: A | R63: =+ROUND((K63+N63)*(1+SUMIF($R$2:$R$4,Q63,$S$2:$S$4)),0) -> 0 | S63: =+ROUND((L63+O63)*(1+SUMIF($R$2:$R$4,R63,$S$2:$S$4)),0) -> 0
A64: MNE | B64: =+B63 -> Sec 2.1/3 | H64: =+SUM(F64:G64) -> 0 | J64: =+ROUND(I64*H64,2) -> 0 | M64: =+ROUND(L64*H64,2) -> 0 | Q64: A | R64: =+ROUND((K64+N64)*(1+SUMIF($R$2:$R$4,Q64,$S$2:$S$4)),0) -> 0 | S64: =+ROUND((L64+O64)*(1+SUMIF($R$2:$R$4,R64,$S$2:$S$4)),0) -> 0
A65: MNE | B65: =+B64 -> Sec 2.1/3 | C65: b | D65: Obtain clearance from relevant technical departments (for M&E works) — 10% | E65: 0.1 | G65: 0 | H65: =+SUM(F65:G65) -> 0 | J65: =+ROUND(I65*H65,2) -> 0 | K65: =SUM(J65:J65) -> 0 | M65: =+ROUND(L65*H65,2) -> 0 | N65: =SUM(M65:M65) -> 0 | Q65: A | R65: =+ROUND((K65+N65)*(1+SUMIF($R$2:$R$4,Q65,$S$2:$S$4)),0) -> 0 | S65: =+ROUND((L65+O65)*(1+SUMIF($R$2:$R$4,R65,$S$2:$S$4)),0) -> 0
A66: MNE | B66: =+B65 -> Sec 2.1/3 | H66: =+SUM(F66:G66) -> 0 | J66: =+ROUND(I66*H66,2) -> 0 | M66: =+ROUND(L66*H66,2) -> 0 | Q66: A | R66: =+ROUND((K66+N66)*(1+SUMIF($R$2:$R$4,Q66,$S$2:$S$4)),0) -> 0 | S66: =+ROUND((L66+O66)*(1+SUMIF($R$2:$R$4,R66,$S$2:$S$4)),0) -> 0
A67: MNE | B67: =+B66 -> Sec 2.1/3 | C67: c | D67: Obtain Building Plan approval (for M&E works) — 5% | E67: 0.05 | G67: 0 | H67: =+SUM(F67:G67) -> 0 | J67: =+ROUND(I67*H67,2) -> 0 | K67: =SUM(J67:J67) -> 0 | M67: =+ROUND(L67*H67,2) -> 0 | N67: =SUM(M67:M67) -> 0 | Q67: A | R67: =+ROUND((K67+N67)*(1+SUMIF($R$2:$R$4,Q67,$S$2:$S$4)),0) -> 0 | S67: =+ROUND((L67+O67)*(1+SUMIF($R$2:$R$4,R67,$S$2:$S$4)),0) -> 0
A68: MNE | B68: =+B67 -> Sec 2.1/3 | H68: =+SUM(F68:G68) -> 0 | J68: =+ROUND(I68*H68,2) -> 0 | M68: =+ROUND(L68*H68,2) -> 0 | Q68: A | R68: =+ROUND((K68+N68)*(1+SUMIF($R$2:$R$4,Q68,$S$2:$S$4)),0) -> 0 | S68: =+ROUND((L68+O68)*(1+SUMIF($R$2:$R$4,R68,$S$2:$S$4)),0) -> 0
A69: MNE | B69: =+B68 -> Sec 2.1/3 | C69: 3.2 | D69: Construction | H69: =+SUM(F69:G69) -> 0 | J69: =+ROUND(I69*H69,2) -> 0 | M69: =+ROUND(L69*H69,2) -> 0 | Q69: A | R69: =+ROUND((K69+N69)*(1+SUMIF($R$2:$R$4,Q69,$S$2:$S$4)),0) -> 0 | S69: =+ROUND((L69+O69)*(1+SUMIF($R$2:$R$4,R69,$S$2:$S$4)),0) -> 0
A70: MNE | B70: =+B69 -> Sec 2.1/3 | H70: =+SUM(F70:G70) -> 0 | J70: =+ROUND(I70*H70,2) -> 0 | M70: =+ROUND(L70*H70,2) -> 0 | Q70: A | R70: =+ROUND((K70+N70)*(1+SUMIF($R$2:$R$4,Q70,$S$2:$S$4)),0) -> 0 | S70: =+ROUND((L70+O70)*(1+SUMIF($R$2:$R$4,R70,$S$2:$S$4)),0) -> 0
A71: MNE | B71: =+B70 -> Sec 2.1/3 | C71: a | D71: During construction period in monthly instalments | E71: 0.5 | G71: 0 | H71: =+SUM(F71:G71) -> 0 | J71: =+ROUND(I71*H71,2) -> 0 | K71: =SUM(J71:J71) -> 0 | M71: =+ROUND(L71*H71,2) -> 0 | N71: =SUM(M71:M71) -> 0 | Q71: A | R71: =+ROUND((K71+N71)*(1+SUMIF($R$2:$R$4,Q71,$S$2:$S$4)),0) -> 0 | S71: =+ROUND((L71+O71)*(1+SUMIF($R$2:$R$4,R71,$S$2:$S$4)),0) -> 0
A72: MNE | B72: =+B71 -> Sec 2.1/3 | H72: =+SUM(F72:G72) -> 0 | J72: =+ROUND(I72*H72,2) -> 0 | M72: =+ROUND(L72*H72,2) -> 0 | Q72: A | R72: =+ROUND((K72+N72)*(1+SUMIF($R$2:$R$4,Q72,$S$2:$S$4)),0) -> 0 | S72: =+ROUND((L72+O72)*(1+SUMIF($R$2:$R$4,R72,$S$2:$S$4)),0) -> 0
A73: MNE | B73: =+B72 -> Sec 2.1/3 | C73: 3.3 | D73: Completion | H73: =+SUM(F73:G73) -> 0 | J73: =+ROUND(I73*H73,2) -> 0 | M73: =+ROUND(L73*H73,2) -> 0 | Q73: A | R73: =+ROUND((K73+N73)*(1+SUMIF($R$2:$R$4,Q73,$S$2:$S$4)),0) -> 0 | S73: =+ROUND((L73+O73)*(1+SUMIF($R$2:$R$4,R73,$S$2:$S$4)),0) -> 0
A74: MNE | B74: =+B73 -> Sec 2.1/3 | H74: =+SUM(F74:G74) -> 0 | J74: =+ROUND(I74*H74,2) -> 0 | M74: =+ROUND(L74*H74,2) -> 0 | Q74: A | R74: =+ROUND((K74+N74)*(1+SUMIF($R$2:$R$4,Q74,$S$2:$S$4)),0) -> 0 | S74: =+ROUND((L74+O74)*(1+SUMIF($R$2:$R$4,R74,$S$2:$S$4)),0) -> 0
A75: MNE | B75: =+B74 -> Sec 2.1/3 | C75: a | D75: Upon substantial completion and obtain Temporary Occupation Permit (TOP) — 10% | E75: 0.1 | G75: 0 | H75: =+SUM(F75:G75) -> 0 | J75: =+ROUND(I75*H75,2) -> 0 | K75: =SUM(J75:J75) -> 0 | M75: =+ROUND(L75*H75,2) -> 0 | N75: =SUM(M75:M75) -> 0 | Q75: A | R75: =+ROUND((K75+N75)*(1+SUMIF($R$2:$R$4,Q75,$S$2:$S$4)),0) -> 0 | S75: =+ROUND((L75+O75)*(1+SUMIF($R$2:$R$4,R75,$S$2:$S$4)),0) -> 0
A76: MNE | B76: =+B75 -> Sec 2.1/3 | H76: =+SUM(F76:G76) -> 0 | J76: =+ROUND(I76*H76,2) -> 0 | M76: =+ROUND(L76*H76,2) -> 0 | Q76: A | R76: =+ROUND((K76+N76)*(1+SUMIF($R$2:$R$4,Q76,$S$2:$S$4)),0) -> 0 | S76: =+ROUND((L76+O76)*(1+SUMIF($R$2:$R$4,R76,$S$2:$S$4)),0) -> 0
A77: MNE | B77: =+B76 -> Sec 2.1/3 | C77: b | D77: Verifying defects rectification and submission of documents (warranties, manuals, as-built drawings, etc) | E77: 0.05 | G77: 0 | H77: =+SUM(F77:G77) -> 0 | J77: =+ROUND(I77*H77,2) -> 0 | K77: =SUM(J77:J77) -> 0 | M77: =+ROUND(L77*H77,2) -> 0 | N77: =SUM(M77:M77) -> 0 | Q77: A | R77: =+ROUND((K77+N77)*(1+SUMIF($R$2:$R$4,Q77,$S$2:$S$4)),0) -> 0 | S77: =+ROUND((L77+O77)*(1+SUMIF($R$2:$R$4,R77,$S$2:$S$4)),0) -> 0
A78: MNE | B78: =+B77 -> Sec 2.1/3 | H78: =+SUM(F78:G78) -> 0 | J78: =+ROUND(I78*H78,2) -> 0 | M78: =+ROUND(L78*H78,2) -> 0 | Q78: A | R78: =+ROUND((K78+N78)*(1+SUMIF($R$2:$R$4,Q78,$S$2:$S$4)),0) -> 0 | S78: =+ROUND((L78+O78)*(1+SUMIF($R$2:$R$4,R78,$S$2:$S$4)),0) -> 0
A79: MNE | B79: =+B78 -> Sec 2.1/3 | C79: c | D79: Obtain Certificate of Statutory Completion (CSC) /Final Completion Certificate (for non CSC projects)/ handing over completed works to relevant Authorities | E79: 0.05 | G79: 0 | H79: =+SUM(F79:G79) -> 0 | J79: =+ROUND(I79*H79,2) -> 0 | K79: =SUM(J79:J79) -> 0 | M79: =+ROUND(L79*H79,2) -> 0 | N79: =SUM(M79:M79) -> 0 | Q79: A | R79: =+ROUND((K79+N79)*(1+SUMIF($R$2:$R$4,Q79,$S$2:$S$4)),0) -> 0 | S79: =+ROUND((L79+O79)*(1+SUMIF($R$2:$R$4,R79,$S$2:$S$4)),0) -> 0
A80: MNE | B80: =+B79 -> Sec 2.1/3 | H80: =+SUM(F80:G80) -> 0 | J80: =+ROUND(I80*H80,2) -> 0 | M80: =+ROUND(L80*H80,2) -> 0 | Q80: A | R80: =+ROUND((K80+N80)*(1+SUMIF($R$2:$R$4,Q80,$S$2:$S$4)),0) -> 0 | S80: =+ROUND((L80+O80)*(1+SUMIF($R$2:$R$4,R80,$S$2:$S$4)),0) -> 0
A81: Collection | B81: =+B80 -> Sec 2.1/3 | D81: To Collection: | K81: =SUM(K59:K80) -> 0 | N81: =SUM(N59:N80) -> 0 | R81: =SUM(R59:R80) -> 0 | S81: =SUM(S59:S80) -> 0
A82: Collection | B82: Sec 2.1/4 | D82: Collection
A83: Collection | B83: =+B82 -> Sec 2.1/4
A84: Collection | B84: =+B83 -> Sec 2.1/4 | D84: Sect 2.1/1 | K84: =+K31 -> 0 | N84: =+N31 -> 0 | R84: =+R31 -> 0 | S84: =+S31 -> 0
A85: Collection | B85: =+B84 -> Sec 2.1/4
A86: Collection | B86: =+B85 -> Sec 2.1/4 | D86: Sect 2.1/2 | K86: =+K57 -> 0 | N86: =+N57 -> 0 | R86: =+R57 -> 0 | S86: =+S57 -> 0
A87: Collection | B87: =+B86 -> Sec 2.1/4
A88: Collection | B88: =+B87 -> Sec 2.1/4 | D88: Sect 2.1/3 | K88: =+K81 -> 0 | N88: =+N81 -> 0 | R88: =+R81 -> 0 | S88: =+S81 -> 0
A89: Collection | B89: =+B88 -> Sec 2.1/4
A90: Collection | B90: =+B89 -> Sec 2.1/4 | K90: =SUM(K84:K89) -> 0 | N90: =SUM(N84:N89) -> 0
A91: Collection | B91: =+B90 -> Sec 2.1/4
A92: Collection | B92: =+B91 -> Sec 2.1/4 | D92: Collection: | K92: =SUM(K82:K91) -> 0 | N92: =SUM(N82:N91) -> 0 | R92: =SUM(R82:R91) -> 0 | S92: =SUM(S82:S91) -> 0
K94: =+K92=K265 -> TRUE
A95: CODE SUMMARY | D95: Trade Code Breakdown — Sec 2 - Professional Fees
A96: CODE | B96: DESCRIPTION | K96: Phase A Amount (S$) | N96: Phase B Amount (S$) | Q96: MARKUP CODE | R96: SUBMISSION AMT (S$) | S96: SUBMISSION AMT (S$)
A97: Prelim | B97: Preliminaries | K97: =SUMIF($A$7:$A$92,A97,$K$7:$K$92) -> 0 | N97: =SUMIF($A$7:$A$92,A97,$N$7:$N$92) -> 0 | Q97: A | R97: =+ROUND((K97+N97)*(1+SUMIF($R$2:$R$4,Q97,$S$2:$S$4)),0) -> 0 | S97: =+ROUND((L97+O97)*(1+SUMIF($R$2:$R$4,R97,$S$2:$S$4)),0) -> 0
A98: Mgmt | B98: Site Management | K98: =SUMIF($A$7:$A$92,A98,$K$7:$K$92) -> 0 | N98: =SUMIF($A$7:$A$92,A98,$N$7:$N$92) -> 0 | Q98: A | R98: =+ROUND((K98+N98)*(1+SUMIF($R$2:$R$4,Q98,$S$2:$S$4)),0) -> 0 | S98: =+ROUND((L98+O98)*(1+SUMIF($R$2:$R$4,R98,$S$2:$S$4)),0) -> 0
A99: Labour | B99: Labour | K99: =SUMIF($A$7:$A$92,A99,$K$7:$K$92) -> 0 | N99: =SUMIF($A$7:$A$92,A99,$N$7:$N$92) -> 0 | Q99: A | R99: =+ROUND((K99+N99)*(1+SUMIF($R$2:$R$4,Q99,$S$2:$S$4)),0) -> 0 | S99: =+ROUND((L99+O99)*(1+SUMIF($R$2:$R$4,R99,$S$2:$S$4)),0) -> 0
A100: Plant | B100: Plants | K100: =SUMIF($A$7:$A$92,A100,$K$7:$K$92) -> 0 | N100: =SUMIF($A$7:$A$92,A100,$N$7:$N$92) -> 0 | Q100: A | R100: =+ROUND((K100+N100)*(1+SUMIF($R$2:$R$4,Q100,$S$2:$S$4)),0) -> 0 | S100: =+ROUND((L100+O100)*(1+SUMIF($R$2:$R$4,R100,$S$2:$S$4)),0) -> 0
A101: Scaf | B101: Scaffolding | K101: =SUMIF($A$7:$A$92,A101,$K$7:$K$92) -> 0 | N101: =SUMIF($A$7:$A$92,A101,$N$7:$N$92) -> 0 | Q101: A | R101: =+ROUND((K101+N101)*(1+SUMIF($R$2:$R$4,Q101,$S$2:$S$4)),0) -> 0 | S101: =+ROUND((L101+O101)*(1+SUMIF($R$2:$R$4,R101,$S$2:$S$4)),0) -> 0
A102: Utilities | B102: Utilities | K102: =SUMIF($A$7:$A$92,A102,$K$7:$K$92) -> 0 | N102: =SUMIF($A$7:$A$92,A102,$N$7:$N$92) -> 0 | Q102: A | R102: =+ROUND((K102+N102)*(1+SUMIF($R$2:$R$4,Q102,$S$2:$S$4)),0) -> 0 | S102: =+ROUND((L102+O102)*(1+SUMIF($R$2:$R$4,R102,$S$2:$S$4)),0) -> 0
...

Sheet Sec 3 - Building Works
A1: Tender No: CE/25/T5/P/896 | Y1: Markup
Y2: A | Z2: 0.2
A3: SECTION 3 | Y3: B | Z3: 0.1 | AA3: PC rate
A4: DESIGN AND BUILD OF COASTAL DORMITORY EXPANSION FOR CHANGI EAST DEVELOPMENT | Y4: C
I5: Type 1 - | J5: 4 | K5: Type 3 - | L5: 2 | P5: Type 1 - | Q5: 2 | R5: Type 3 - | S5: 3
A6: CODE | B6: PAGE | C6: ITEM | D6: DESCRIPTION | E6: UNIT | F6: Material (S$) | G6: Labour (S$) | H6: U/RATE (S$) | I6: Qty per Block | J6: Type 1 Qty | K6: Qty per Block | L6: Type 3 Qty | M6: Phase A Qty | N6: Phase A Sub-Total | O6: Phase A Amount (S$) | P6: Qty per Block | Q6: Type 1 Qty | R6: Qty per Block | S6: Type 3 Qty | T6: Phase B Qty | U6: Phase B Sub-Total | V6: Phase B Amount (S$) | W6: REMARKS | X6: MARKUP CODE | Y6: Phase A SUBMISSION AMOUNT (S$) | Z6: Phase B SUBMISSION AMOUNT (S$)
A7: WP | B7: 3.2/1 | D7: SECTION NO 3.2 — DORMITORY BLOCKS | H7: =+SUM(F7:G7) -> 0 | J7: =+I7*$J$5 -> 0 | L7: =+K7*$L$5 -> 0 | M7: =+J7+L7 -> 0 | N7: =+ROUND(M7*H7,2) -> 0 | Q7: =+P7*$Q$5 -> 0 | S7: =+R7*$S$5 -> 0 | T7: =+Q7+S7 -> 0 | U7: =+ROUND(T7*H7,2) -> 0 | X7: A | Y7: =+ROUND((O7)*(1+SUMIF($Y$2:$Y$4,X7,$Z$2:$Z$4)),0) -> 0 | Z7: =+ROUND((V7)*(1+SUMIF($Y$2:$Y$4,X7,$Z$2:$Z$4)),0) -> 0
A8: WP | B8: =+B7 -> 3.2/1 | D8: Detailed Design, Construct, Supply, Install, Complete, Testing and Commissioning of Workers Dormitory Blocks and Associated Facilities | H8: =+SUM(F8:G8) -> 0 | J8: =+I8*$J$5 -> 0 | L8: =+K8*$L$5 -> 0 | M8: =+J8+L8 -> 0 | N8: =+ROUND(M8*H8,2) -> 0 | Q8: =+P8*$Q$5 -> 0 | S8: =+R8*$S$5 -> 0 | T8: =+Q8+S8 -> 0 | U8: =+ROUND(T8*H8,2) -> 0 | X8: A | Y8: =+ROUND((O8)*(1+SUMIF($Y$2:$Y$4,X8,$Z$2:$Z$4)),0) -> 0 | Z8: =+ROUND((V8)*(1+SUMIF($Y$2:$Y$4,X8,$Z$2:$Z$4)),0) -> 0
A9: WP | B9: =+B8 -> 3.2/1 | C9: 1 | D9: SUBSTRUCTURE | H9: =+SUM(F9:G9) -> 0 | J9: =+I9*$J$5 -> 0 | L9: =+K9*$L$5 -> 0 | M9: =+J9+L9 -> 0 | N9: =+ROUND(M9*H9,2) -> 0 | Q9: =+P9*$Q$5 -> 0 | S9: =+R9*$S$5 -> 0 | T9: =+Q9+S9 -> 0 | U9: =+ROUND(T9*H9,2) -> 0 | X9: A | Y9: =+ROUND((O9)*(1+SUMIF($Y$2:$Y$4,X9,$Z$2:$Z$4)),0) -> 0 | Z9: =+ROUND((V9)*(1+SUMIF($Y$2:$Y$4,X9,$Z$2:$Z$4)),0) -> 0
A10: WP | B10: =+B9 -> 3.2/1 | C10: 1.1 | D10: EarthWorks | H10: =+SUM(F10:G10) -> 0 | J10: =+I10*$J$5 -> 0 | L10: =+K10*$L$5 -> 0 | M10: =+J10+L10 -> 0 | N10: =+ROUND(M10*H10,2) -> 0 | Q10: =+P10*$Q$5 -> 0 | S10: =+R10*$S$5 -> 0 | T10: =+Q10+S10 -> 0 | U10: =+ROUND(T10*H10,2) -> 0 | X10: A | Y10: =+ROUND((O10)*(1+SUMIF($Y$2:$Y$4,X10,$Z$2:$Z$4)),0) -> 0 | Z10: =+ROUND((V10)*(1+SUMIF($Y$2:$Y$4,X10,$Z$2:$Z$4)),0) -> 0
A11: WP | B11: =+B10 -> 3.2/1 | C11: 1.1.1 | D11: Bituminous waterproof membrane | E11: m2 | H11: =+SUM(F11:G11) -> 0 | J11: =+I11*$J$5 -> 0 | L11: =+K11*$L$5 -> 0 | M11: =+J11+L11 -> 0 | N11: =+ROUND(M11*H11,2) -> 0 | O11: =N11 -> 0 | Q11: =+P11*$Q$5 -> 0 | S11: =+R11*$S$5 -> 0 | T11: =+Q11+S11 -> 0 | U11: =+ROUND(T11*H11,2) -> 0 | V11: =U11 -> 0 | X11: A | Y11: =+ROUND((O11)*(1+SUMIF($Y$2:$Y$4,X11,$Z$2:$Z$4)),0) -> 0 | Z11: =+ROUND((V11)*(1+SUMIF($Y$2:$Y$4,X11,$Z$2:$Z$4)),0) -> 0
A12: Termite | B12: =+B11 -> 3.2/1 | C12: 1.1.2 | D12: Anti-termite treatment | E12: LS | H12: =+SUM(F12:G12) -> 0 | J12: =+I12*$J$5 -> 0 | L12: =+K12*$L$5 -> 0 | M12: =+J12+L12 -> 0 | N12: =+ROUND(M12*H12,2) -> 0 | O12: =N12 -> 0 | Q12: =+P12*$Q$5 -> 0 | S12: =+R12*$S$5 -> 0 | T12: =+Q12+S12 -> 0 | U12: =+ROUND(T12*H12,2) -> 0 | V12: =U12 -> 0 | X12: A | Y12: =+ROUND((O12)*(1+SUMIF($Y$2:$Y$4,X12,$Z$2:$Z$4)),0) -> 0 | Z12: =+ROUND((V12)*(1+SUMIF($Y$2:$Y$4,X12,$Z$2:$Z$4)),0) -> 0
A13: Earth | B13: =+B12 -> 3.2/1 | C13: 1.1.3 | D13: Excavation, Backfill and Disposal | H13: =+SUM(F13:G13) -> 0 | J13: =+I13*$J$5 -> 0 | L13: =+K13*$L$5 -> 0 | M13: =+J13+L13 -> 0 | N13: =+ROUND(M13*H13,2) -> 0 | O13: =N13 -> 0 | Q13: =+P13*$Q$5 -> 0 | S13: =+R13*$S$5 -> 0 | T13: =+Q13+S13 -> 0 | U13: =+ROUND(T13*H13,2) -> 0 | V13: =U13 -> 0 | X13: A | Y13: =+ROUND((O13)*(1+SUMIF($Y$2:$Y$4,X13,$Z$2:$Z$4)),0) -> 0 | Z13: =+ROUND((V13)*(1+SUMIF($Y$2:$Y$4,X13,$Z$2:$Z$4)),0) -> 0
A14: Earth | B14: =+B13 -> 3.2/1 | D14: Excavation | E14: m3 | H14: =+SUM(F14:G14) -> 0 | J14: =+I14*$J$5 -> 0 | L14: =+K14*$L$5 -> 0 | M14: =+J14+L14 -> 0 | N14: =+ROUND(M14*H14,2) -> 0 | O14: =N14 -> 0 | Q14: =+P14*$Q$5 -> 0 | S14: =+R14*$S$5 -> 0 | T14: =+Q14+S14 -> 0 | U14: =+ROUND(T14*H14,2) -> 0 | V14: =U14 -> 0 | X14: A | Y14: =+ROUND((O14)*(1+SUMIF($Y$2:$Y$4,X14,$Z$2:$Z$4)),0) -> 0 | Z14: =+ROUND((V14)*(1+SUMIF($Y$2:$Y$4,X14,$Z$2:$Z$4)),0) -> 0
A15: Earth | B15: =+B14 -> 3.2/1 | D15: Backfill | E15: m3 | H15: =+SUM(F15:G15) -> 0 | J15: =+I15*$J$5 -> 0 | L15: =+K15*$L$5 -> 0 | M15: =+J15+L15 -> 0 | N15: =+ROUND(M15*H15,2) -> 0 | O15: =N15 -> 0 | Q15: =+P15*$Q$5 -> 0 | S15: =+R15*$S$5 -> 0 | T15: =+Q15+S15 -> 0 | U15: =+ROUND(T15*H15,2) -> 0 | V15: =U15 -> 0 | X15: A | Y15: =+ROUND((O15)*(1+SUMIF($Y$2:$Y$4,X15,$Z$2:$Z$4)),0) -> 0 | Z15: =+ROUND((V15)*(1+SUMIF($Y$2:$Y$4,X15,$Z$2:$Z$4)),0) -> 0
A16: Earth | B16: =+B15 -> 3.2/1 | D16: Disposal | E16: m3 | H16: =+SUM(F16:G16) -> 0 | J16: =+I16*$J$5 -> 0 | L16: =+K16*$L$5 -> 0 | M16: =+J16+L16 -> 0 | N16: =+ROUND(M16*H16,2) -> 0 | O16: =N16 -> 0 | Q16: =+P16*$Q$5 -> 0 | S16: =+R16*$S$5 -> 0 | T16: =+Q16+S16 -> 0 | U16: =+ROUND(T16*H16,2) -> 0 | V16: =U16 -> 0 | X16: A | Y16: =+ROUND((O16)*(1+SUMIF($Y$2:$Y$4,X16,$Z$2:$Z$4)),0) -> 0 | Z16: =+ROUND((V16)*(1+SUMIF($Y$2:$Y$4,X16,$Z$2:$Z$4)),0) -> 0
A17: SubLean | B17: =+B13 -> 3.2/1 | C17: 1.2 | D17: Raft Foundation | H17: =+SUM(F17:G17) -> 0 | J17: =+I17*$J$5 -> 0 | L17: =+K17*$L$5 -> 0 | M17: =+J17+L17 -> 0 | N17: =+ROUND(M17*H17,2) -> 0 | Q17: =+P17*$Q$5 -> 0 | S17: =+R17*$S$5 -> 0 | T17: =+Q17+S17 -> 0 | U17: =+ROUND(T17*H17,2) -> 0 | X17: A | Y17: =+ROUND((O17)*(1+SUMIF($Y$2:$Y$4,X17,$Z$2:$Z$4)),0) -> 0 | Z17: =+ROUND((V17)*(1+SUMIF($Y$2:$Y$4,X17,$Z$2:$Z$4)),0) -> 0
A18: SubLean | B18: =+B17 -> 3.2/1 | C18: 1.2.1 | D18: Lean concrete | E18: m2 | H18: =+SUM(F18:G18) -> 0 | J18: =+I18*$J$5 -> 0 | L18: =+K18*$L$5 -> 0 | M18: =+J18+L18 -> 0 | N18: =+ROUND(M18*H18,2) -> 0 | O18: =N18 -> 0 | Q18: =+P18*$Q$5 -> 0 | S18: =+R18*$S$5 -> 0 | T18: =+Q18+S18 -> 0 | U18: =+ROUND(T18*H18,2) -> 0 | V18: =U18 -> 0 | X18: A | Y18: =+ROUND((O18)*(1+SUMIF($Y$2:$Y$4,X18,$Z$2:$Z$4)),0) -> 0 | Z18: =+ROUND((V18)*(1+SUMIF($Y$2:$Y$4,X18,$Z$2:$Z$4)),0) -> 0
A19: SubLean | B19: =+B18 -> 3.2/1 | C19: 1.2.2 | D19: Hardcore | E19: m2 | H19: =+SUM(F19:G19) -> 0 | J19: =+I19*$J$5 -> 0 | L19: =+K19*$L$5 -> 0 | M19: =+J19+L19 -> 0 | N19: =+ROUND(M19*H19,2) -> 0 | O19: =N19 -> 0 | Q19: =+P19*$Q$5 -> 0 | S19: =+R19*$S$5 -> 0 | T19: =+Q19+S19 -> 0 | U19: =+ROUND(T19*H19,2) -> 0 | V19: =U19 -> 0 | X19: A | Y19: =+ROUND((O19)*(1+SUMIF($Y$2:$Y$4,X19,$Z$2:$Z$4)),0) -> 0 | Z19: =+ROUND((V19)*(1+SUMIF($Y$2:$Y$4,X19,$Z$2:$Z$4)),0) -> 0
A20: SubConc(H) | B20: =+B19 -> 3.2/1 | C20: 1.2.3 | D20: Concrete | E20: m3 | H20: =+SUM(F20:G20) -> 0 | J20: =+I20*$J$5 -> 0 | L20: =+K20*$L$5 -> 0 | M20: =+J20+L20 -> 0 | N20: =+ROUND(M20*H20,2) -> 0 | O20: =N20 -> 0 | Q20: =+P20*$Q$5 -> 0 | S20: =+R20*$S$5 -> 0 | T20: =+Q20+S20 -> 0 | U20: =+ROUND(T20*H20,2) -> 0 | V20: =U20 -> 0 | X20: A | Y20: =+ROUND((O20)*(1+SUMIF($Y$2:$Y$4,X20,$Z$2:$Z$4)),0) -> 0 | Z20: =+ROUND((V20)*(1+SUMIF($Y$2:$Y$4,X20,$Z$2:$Z$4)),0) -> 0
A21: SubFW(H) | B21: =+B20 -> 3.2/1 | C21: 1.2.4 | D21: Formwork | E21: m2 | H21: =+SUM(F21:G21) -> 0 | J21: =+I21*$J$5 -> 0 | L21: =+K21*$L$5 -> 0 | M21: =+J21+L21 -> 0 | N21: =+ROUND(M21*H21,2) -> 0 | O21: =N21 -> 0 | Q21: =+P21*$Q$5 -> 0 | S21: =+R21*$S$5 -> 0 | T21: =+Q21+S21 -> 0 | U21: =+ROUND(T21*H21,2) -> 0 | V21: =U21 -> 0 | X21: A | Y21: =+ROUND((O21)*(1+SUMIF($Y$2:$Y$4,X21,$Z$2:$Z$4)),0) -> 0 | Z21: =+ROUND((V21)*(1+SUMIF($Y$2:$Y$4,X21,$Z$2:$Z$4)),0) -> 0
A22: SubBar(H) | B22: =+B21 -> 3.2/1 | C22: 1.2.5 | D22: Reinforcement | H22: =+SUM(F22:G22) -> 0 | J22: =+I22*$J$5 -> 0 | L22: =+K22*$L$5 -> 0 | M22: =+J22+L22 -> 0 | N22: =+ROUND(M22*H22,2) -> 0 | O22: =N22 -> 0 | Q22: =+P22*$Q$5 -> 0 | S22: =+R22*$S$5 -> 0 | T22: =+Q22+S22 -> 0 | U22: =+ROUND(T22*H22,2) -> 0 | V22: =U22 -> 0 | X22: A | Y22: =+ROUND((O22)*(1+SUMIF($Y$2:$Y$4,X22,$Z$2:$Z$4)),0) -> 0 | Z22: =+ROUND((V22)*(1+SUMIF($Y$2:$Y$4,X22,$Z$2:$Z$4)),0) -> 0
A23: Other | B23: =+B22 -> 3.2/1 | C23: 1.3 | D23: Plate Load Test | E23: no | H23: =+SUM(F23:G23) -> 0 | J23: =+I23*$J$5 -> 0 | L23: =+K23*$L$5 -> 0 | M23: =+J23+L23 -> 0 | N23: =+ROUND(M23*H23,2) -> 0 | O23: =N23 -> 0 | Q23: =+P23*$Q$5 -> 0 | S23: =+R23*$S$5 -> 0 | T23: =+Q23+S23 -> 0 | U23: =+ROUND(T23*H23,2) -> 0 | V23: =U23 -> 0 | X23: A | Y23: =+ROUND((O23)*(1+SUMIF($Y$2:$Y$4,X23,$Z$2:$Z$4)),0) -> 0 | Z23: =+ROUND((V23)*(1+SUMIF($Y$2:$Y$4,X23,$Z$2:$Z$4)),0) -> 0
A24: Collection | B24: =+B23 -> 3.2/1 | D24: To Collection: | J24: =+I24*$J$5 -> 0 | L24: =+K24*$L$5 -> 0 | M24: =+J24+L24 -> 0 | N24: =SUM(N7:N23) -> 0 | O24: =SUM(O7:O23) -> 0 | Q24: =+P24*$Q$5 -> 0 | S24: =+R24*$S$5 -> 0 | T24: =+Q24+S24 -> 0 | U24: =SUM(U7:U23) -> 0 | V24: =SUM(V7:V23) -> 0 | X24: A | Y24: =SUM(Y7:Y23) -> 0 | Z24: =SUM(Z7:Z23) -> 0
A25: Steel | B25: 3.2/2 | C25: 2 | D25: SUPERSTRUCTURE | H25: =+SUM(F25:G25) -> 0 | J25: =+I25*$J$5 -> 0 | L25: =+K25*$L$5 -> 0 | M25: =+J25+L25 -> 0 | N25: =+ROUND(M25*H25,2) -> 0 | Q25: =+P25*$Q$5 -> 0 | S25: =+R25*$S$5 -> 0 | T25: =+Q25+S25 -> 0 | U25: =+ROUND(T25*H25,2) -> 0 | X25: A | Y25: =+ROUND((O25)*(1+SUMIF($Y$2:$Y$4,X25,$Z$2:$Z$4)),0) -> 0 | Z25: =+ROUND((V25)*(1+SUMIF($Y$2:$Y$4,X25,$Z$2:$Z$4)),0) -> 0
A26: Steel | B26: =+B25 -> 3.2/2 | C26: 2.1 | D26: Frame | H26: =+SUM(F26:G26) -> 0 | J26: =+I26*$J$5 -> 0 | L26: =+K26*$L$5 -> 0 | M26: =+J26+L26 -> 0 | N26: =+ROUND(M26*H26,2) -> 0 | O26: =N26 -> 0 | Q26: =+P26*$Q$5 -> 0 | S26: =+R26*$S$5 -> 0 | T26: =+Q26+S26 -> 0 | U26: =+ROUND(T26*H26,2) -> 0 | V26: =U26 -> 0 | X26: A | Y26: =+ROUND((O26)*(1+SUMIF($Y$2:$Y$4,X26,$Z$2:$Z$4)),0) -> 0 | Z26: =+ROUND((V26)*(1+SUMIF($Y$2:$Y$4,X26,$Z$2:$Z$4)),0) -> 0
A27: Steel | B27: =+B26 -> 3.2/2 | C27: 2.1.1 | D27: Structural Frame including Beam, Column, Trusses and necessary finishes and coating | H27: =+SUM(F27:G27) -> 0 | J27: =+I27*$J$5 -> 0 | L27: =+K27*$L$5 -> 0 | M27: =+J27+L27 -> 0 | N27: =+ROUND(M27*H27,2) -> 0 | O27: =N27 -> 0 | Q27: =+P27*$Q$5 -> 0 | S27: =+R27*$S$5 -> 0 | T27: =+Q27+S27 -> 0 | U27: =+ROUND(T27*H27,2) -> 0 | V27: =U27 -> 0 | X27: A | Y27: =+ROUND((O27)*(1+SUMIF($Y$2:$Y$4,X27,$Z$2:$Z$4)),0) -> 0 | Z27: =+ROUND((V27)*(1+SUMIF($Y$2:$Y$4,X27,$Z$2:$Z$4)),0) -> 0
A28: SuperConc(H) | B28: =+B25 -> 3.2/2 | C28: 2.2 | D28: Upper floors | H28: =+SUM(F28:G28) -> 0 | J28: =+I28*$J$5 -> 0 | L28: =+K28*$L$5 -> 0 | M28: =+J28+L28 -> 0 | N28: =+ROUND(M28*H28,2) -> 0 | O28: =N28 -> 0 | Q28: =+P28*$Q$5 -> 0 | S28: =+R28*$S$5 -> 0 | T28: =+Q28+S28 -> 0 | U28: =+ROUND(T28*H28,2) -> 0 | V28: =U28 -> 0 | X28: A | Y28: =+ROUND((O28)*(1+SUMIF($Y$2:$Y$4,X28,$Z$2:$Z$4)),0) -> 0 | Z28: =+ROUND((V28)*(1+SUMIF($Y$2:$Y$4,X28,$Z$2:$Z$4)),0) -> 0
A29: SuperConc(H) | B29: =+B26 -> 3.2/2 | C29: 2.2.1 | D29: Upper Floor Slabs — Contractor Proposed System (Tenderer to insert the proposed system) | H29: =+SUM(F29:G29) -> 0 | J29: =+I29*$J$5 -> 0 | L29: =+K29*$L$5 -> 0 | M29: =+J29+L29 -> 0 | N29: =+ROUND(M29*H29,2) -> 0 | O29: =N29 -> 0 | Q29: =+P29*$Q$5 -> 0 | S29: =+R29*$S$5 -> 0 | T29: =+Q29+S29 -> 0 | U29: =+ROUND(T29*H29,2) -> 0 | V29: =U29 -> 0 | X29: A | Y29: =+ROUND((O29)*(1+SUMIF($Y$2:$Y$4,X29,$Z$2:$Z$4)),0) -> 0 | Z29: =+ROUND((V29)*(1+SUMIF($Y$2:$Y$4,X29,$Z$2:$Z$4)),0) -> 0
A30: SubConc(H) | B30: =+B29 -> 3.2/2 | D30: Concrete | E30: m3 | H30: =+SUM(F30:G30) -> 0 | J30: =+I30*$J$5 -> 0 | L30: =+K30*$L$5 -> 0 | M30: =+J30+L30 -> 0 | N30: =+ROUND(M30*H30,2) -> 0 | O30: =N30 -> 0 | Q30: =+P30*$Q$5 -> 0 | S30: =+R30*$S$5 -> 0 | T30: =+Q30+S30 -> 0 | U30: =+ROUND(T30*H30,2) -> 0 | V30: =U30 -> 0 | X30: A | Y30: =+ROUND((O30)*(1+SUMIF($Y$2:$Y$4,X30,$Z$2:$Z$4)),0) -> 0 | Z30: =+ROUND((V30)*(1+SUMIF($Y$2:$Y$4,X30,$Z$2:$Z$4)),0) -> 0
A31: SubFW(H) | B31: =+B30 -> 3.2/2 | D31: Formwork | E31: m2 | H31: =+SUM(F31:G31) -> 0 | J31: =+I31*$J$5 -> 0 | L31: =+K31*$L$5 -> 0 | M31: =+J31+L31 -> 0 | N31: =+ROUND(M31*H31,2) -> 0 | O31: =N31 -> 0 | Q31: =+P31*$Q$5 -> 0 | S31: =+R31*$S$5 -> 0 | T31: =+Q31+S31 -> 0 | U31: =+ROUND(T31*H31,2) -> 0 | V31: =U31 -> 0 | X31: A | Y31: =+ROUND((O31)*(1+SUMIF($Y$2:$Y$4,X31,$Z$2:$Z$4)),0) -> 0 | Z31: =+ROUND((V31)*(1+SUMIF($Y$2:$Y$4,X31,$Z$2:$Z$4)),0) -> 0
A32: SubBar(H) | B32: =+B31 -> 3.2/2 | D32: Reinforcement | H32: =+SUM(F32:G32) -> 0 | J32: =+I32*$J$5 -> 0 | L32: =+K32*$L$5 -> 0 | M32: =+J32+L32 -> 0 | N32: =+ROUND(M32*H32,2) -> 0 | O32: =N32 -> 0 | Q32: =+P32*$Q$5 -> 0 | S32: =+R32*$S$5 -> 0 | T32: =+Q32+S32 -> 0 | U32: =+ROUND(T32*H32,2) -> 0 | V32: =U32 -> 0 | X32: A | Y32: =+ROUND((O32)*(1+SUMIF($Y$2:$Y$4,X32,$Z$2:$Z$4)),0) -> 0 | Z32: =+ROUND((V32)*(1+SUMIF($Y$2:$Y$4,X32,$Z$2:$Z$4)),0) -> 0
A33: RWDP | B33: =+B28 -> 3.2/2 | C33: 2.2.2 | D33: Drainage to Corridor | H33: =+SUM(F33:G33) -> 0 | J33: =+I33*$J$5 -> 0 | L33: =+K33*$L$5 -> 0 | M33: =+J33+L33 -> 0 | N33: =+ROUND(M33*H33,2) -> 0 | O33: =N33 -> 0 | Q33: =+P33*$Q$5 -> 0 | S33: =+R33*$S$5 -> 0 | T33: =+Q33+S33 -> 0 | U33: =+ROUND(T33*H33,2) -> 0 | V33: =U33 -> 0 | X33: A | Y33: =+ROUND((O33)*(1+SUMIF($Y$2:$Y$4,X33,$Z$2:$Z$4)),0) -> 0 | Z33: =+ROUND((V33)*(1+SUMIF($Y$2:$Y$4,X33,$Z$2:$Z$4)),0) -> 0
A34: RWDP | B34: =+B29 -> 3.2/2 | C34: 2.2.2.1 | D34: Rainwater pipes | E34: m | H34: =+SUM(F34:G34) -> 0 | J34: =+I34*$J$5 -> 0 | L34: =+K34*$L$5 -> 0 | M34: =+J34+L34 -> 0 | N34: =+ROUND(M34*H34,2) -> 0 | O34: =N34 -> 0 | Q34: =+P34*$Q$5 -> 0 | S34: =+R34*$S$5 -> 0 | T34: =+Q34+S34 -> 0 | U34: =+ROUND(T34*H34,2) -> 0 | V34: =U34 -> 0 | X34: A | Y34: =+ROUND((O34)*(1+SUMIF($Y$2:$Y$4,X34,$Z$2:$Z$4)),0) -> 0 | Z34: =+ROUND((V34)*(1+SUMIF($Y$2:$Y$4,X34,$Z$2:$Z$4)),0) -> 0
A35: RWDP | B35: =+B34 -> 3.2/2 | C35: 2.2.2.2 | D35: Floor outlets | E35: no | H35: =+SUM(F35:G35) -> 0 | J35: =+I35*$J$5 -> 0 | L35: =+K35*$L$5 -> 0 | M35: =+J35+L35 -> 0 | N35: =+ROUND(M35*H35,2) -> 0 | O35: =N35 -> 0 | Q35: =+P35*$Q$5 -> 0 | S35: =+R35*$S$5 -> 0 | T35: =+Q35+S35 -> 0 | U35: =+ROUND(T35*H35,2) -> 0 | V35: =U35 -> 0 | X35: A | Y35: =+ROUND((O35)*(1+SUMIF($Y$2:$Y$4,X35,$Z$2:$Z$4)),0) -> 0 | Z35: =+ROUND((V35)*(1+SUMIF($Y$2:$Y$4,X35,$Z$2:$Z$4)),0) -> 0
A36: RoofStruc | B36: =+B33 -> 3.2/2 | C36: 2.3 | D36: Roof | H36: =+SUM(F36:G36) -> 0 | J36: =+I36*$J$5 -> 0 | L36: =+K36*$L$5 -> 0 | M36: =+J36+L36 -> 0 | N36: =+ROUND(M36*H36,2) -> 0 | O36: =N36 -> 0 | Q36: =+P36*$Q$5 -> 0 | S36: =+R36*$S$5 -> 0 | T36: =+Q36+S36 -> 0 | U36: =+ROUND(T36*H36,2) -> 0 | V36: =U36 -> 0 | X36: A | Y36: =+ROUND((O36)*(1+SUMIF($Y$2:$Y$4,X36,$Z$2:$Z$4)),0) -> 0 | Z36: =+ROUND((V36)*(1+SUMIF($Y$2:$Y$4,X36,$Z$2:$Z$4)),0) -> 0
A37: RoofStruc | B37: =+B34 -> 3.2/2 | C37: 2.3.1 | D37: Roof Structure | H37: =+SUM(F37:G37) -> 0 | J37: =+I37*$J$5 -> 0 | L37: =+K37*$L$5 -> 0 | M37: =+J37+L37 -> 0 | N37: =+ROUND(M37*H37,2) -> 0 | O37: =N37 -> 0 | Q37: =+P37*$Q$5 -> 0 | S37: =+R37*$S$5 -> 0 | T37: =+Q37+S37 -> 0 | U37: =+ROUND(T37*H37,2) -> 0 | V37: =U37 -> 0 | X37: A | Y37: =+ROUND((O37)*(1+SUMIF($Y$2:$Y$4,X37,$Z$2:$Z$4)),0) -> 0 | Z37: =+ROUND((V37)*(1+SUMIF($Y$2:$Y$4,X37,$Z$2:$Z$4)),0) -> 0
A38: RoofStruc | B38: =+B35 -> 3.2/2 | C38: 2.3.1.1 | D38: Pitched Roof | E38: m2 | H38: =+SUM(F38:G38) -> 0 | J38: =+I38*$J$5 -> 0 | L38: =+K38*$L$5 -> 0 | M38: =+J38+L38 -> 0 | N38: =+ROUND(M38*H38,2) -> 0 | O38: =N38 -> 0 | Q38: =+P38*$Q$5 -> 0 | S38: =+R38*$S$5 -> 0 | T38: =+Q38+S38 -> 0 | U38: =+ROUND(T38*H38,2) -> 0 | V38: =U38 -> 0 | X38: A | Y38: =+ROUND((O38)*(1+SUMIF($Y$2:$Y$4,X38,$Z$2:$Z$4)),0) -> 0 | Z38: =+ROUND((V38)*(1+SUMIF($Y$2:$Y$4,X38,$Z$2:$Z$4)),0) -> 0
A39: RoofStruc | B39: =+B38 -> 3.2/2 | C39: 2.3.1.2 | D39: Flat Roof | E39: m2 | H39: =+SUM(F39:G39) -> 0 | J39: =+I39*$J$5 -> 0 | L39: =+K39*$L$5 -> 0 | M39: =+J39+L39 -> 0 | N39: =+ROUND(M39*H39,2) -> 0 | O39: =N39 -> 0 | Q39: =+P39*$Q$5 -> 0 | S39: =+R39*$S$5 -> 0 | T39: =+Q39+S39 -> 0 | U39: =+ROUND(T39*H39,2) -> 0 | V39: =U39 -> 0 | X39: A | Y39: =+ROUND((O39)*(1+SUMIF($Y$2:$Y$4,X39,$Z$2:$Z$4)),0) -> 0 | Z39: =+ROUND((V39)*(1+SUMIF($Y$2:$Y$4,X39,$Z$2:$Z$4)),0) -> 0
A40: Roof | B40: =+B38 -> 3.2/2 | C40: 2.3.2 | D40: Roof Covering | H40: =+SUM(F40:G40) -> 0 | J40: =+I40*$J$5 -> 0 | L40: =+K40*$L$5 -> 0 | M40: =+J40+L40 -> 0 | N40: =+ROUND(M40*H40,2) -> 0 | O40: =N40 -> 0 | Q40: =+P40*$Q$5 -> 0 | S40: =+R40*$S$5 -> 0 | T40: =+Q40+S40 -> 0 | U40: =+ROUND(T40*H40,2) -> 0 | V40: =U40 -> 0 | X40: A | Y40: =+ROUND((O40)*(1+SUMIF($Y$2:$Y$4,X40,$Z$2:$Z$4)),0) -> 0 | Z40: =+ROUND((V40)*(1+SUMIF($Y$2:$Y$4,X40,$Z$2:$Z$4)),0) -> 0
A41: Roof | B41: =+B39 -> 3.2/2 | C41: 2.3.2.1 | D41: Roof coverings, metal sheet roofing | E41: m2 | H41: =+SUM(F41:G41) -> 0 | J41: =+I41*$J$5 -> 0 | L41: =+K41*$L$5 -> 0 | M41: =+J41+L41 -> 0 | N41: =+ROUND(M41*H41,2) -> 0 | O41: =N41 -> 0 | Q41: =+P41*$Q$5 -> 0 | S41: =+R41*$S$5 -> 0 | T41: =+Q41+S41 -> 0 | U41: =+ROUND(T41*H41,2) -> 0 | V41: =U41 -> 0 | X41: A | Y41: =+ROUND((O41)*(1+SUMIF($Y$2:$Y$4,X41,$Z$2:$Z$4)),0) -> 0 | Z41: =+ROUND((V41)*(1+SUMIF($Y$2:$Y$4,X41,$Z$2:$Z$4)),0) -> 0
A42: Roof | B42: =+B41 -> 3.2/2 | C42: 2.3.2.2 | D42: Flashings | E42: m | H42: =+SUM(F42:G42) -> 0 | J42: =+I42*$J$5 -> 0 | L42: =+K42*$L$5 -> 0 | M42: =+J42+L42 -> 0 | N42: =+ROUND(M42*H42,2) -> 0 | O42: =N42 -> 0 | Q42: =+P42*$Q$5 -> 0 | S42: =+R42*$S$5 -> 0 | T42: =+Q42+S42 -> 0 | U42: =+ROUND(T42*H42,2) -> 0 | V42: =U42 -> 0 | X42: A | Y42: =+ROUND((O42)*(1+SUMIF($Y$2:$Y$4,X42,$Z$2:$Z$4)),0) -> 0 | Z42: =+ROUND((V42)*(1+SUMIF($Y$2:$Y$4,X42,$Z$2:$Z$4)),0) -> 0
A43: Roof | B43: =+B41 -> 3.2/2 | C43: 2.3.3 | D43: Roof drainage | H43: =+SUM(F43:G43) -> 0 | J43: =+I43*$J$5 -> 0 | L43: =+K43*$L$5 -> 0 | M43: =+J43+L43 -> 0 | N43: =+ROUND(M43*H43,2) -> 0 | O43: =N43 -> 0 | Q43: =+P43*$Q$5 -> 0 | S43: =+R43*$S$5 -> 0 | T43: =+Q43+S43 -> 0 | U43: =+ROUND(T43*H43,2) -> 0 | V43: =U43 -> 0 | X43: A | Y43: =+ROUND((O43)*(1+SUMIF($Y$2:$Y$4,X43,$Z$2:$Z$4)),0) -> 0 | Z43: =+ROUND((V43)*(1+SUMIF($Y$2:$Y$4,X43,$Z$2:$Z$4)),0) -> 0
A44: RWDP | B44: =+B42 -> 3.2/2 | C44: 2.3.3.1 | D44: Gutters | E44: m | H44: =+SUM(F44:G44) -> 0 | J44: =+I44*$J$5 -> 0 | L44: =+K44*$L$5 -> 0 | M44: =+J44+L44 -> 0 | N44: =+ROUND(M44*H44,2) -> 0 | O44: =N44 -> 0 | Q44: =+P44*$Q$5 -> 0 | S44: =+R44*$S$5 -> 0 | T44: =+Q44+S44 -> 0 | U44: =+ROUND(T44*H44,2) -> 0 | V44: =U44 -> 0 | X44: A | Y44: =+ROUND((O44)*(1+SUMIF($Y$2:$Y$4,X44,$Z$2:$Z$4)),0) -> 0 | Z44: =+ROUND((V44)*(1+SUMIF($Y$2:$Y$4,X44,$Z$2:$Z$4)),0) -> 0
A45: RWDP | B45: =+B44 -> 3.2/2 | C45: 2.3.3.2 | D45: Rainwater pipes | E45: m | H45: =+SUM(F45:G45) -> 0 | J45: =+I45*$J$5 -> 0 | L45: =+K45*$L$5 -> 0 | M45: =+J45+L45 -> 0 | N45: =+ROUND(M45*H45,2) -> 0 | O45: =N45 -> 0 | Q45: =+P45*$Q$5 -> 0 | S45: =+R45*$S$5 -> 0 | T45: =+Q45+S45 -> 0 | U45: =+ROUND(T45*H45,2) -> 0 | V45: =U45 -> 0 | X45: A | Y45: =+ROUND((O45)*(1+SUMIF($Y$2:$Y$4,X45,$Z$2:$Z$4)),0) -> 0 | Z45: =+ROUND((V45)*(1+SUMIF($Y$2:$Y$4,X45,$Z$2:$Z$4)),0) -> 0
A46: Collection | B46: =+B45 -> 3.2/2 | D46: To Collection: | J46: =+I46*$J$5 -> 0 | L46: =+K46*$L$5 -> 0 | M46: =+J46+L46 -> 0 | N46: =SUM(N25:N45) -> 0 | O46: =SUM(O25:O45) -> 0 | Q46: =+P46*$Q$5 -> 0 | S46: =+R46*$S$5 -> 0 | T46: =+Q46+S46 -> 0 | U46: =SUM(U25:U45) -> 0 | V46: =SUM(V25:V45) -> 0 | X46: A | Y46: =+ROUND((O46)*(1+SUMIF($Y$2:$Y$4,X46,$Z$2:$Z$4)),0) -> 0 | Z46: =+ROUND((V46)*(1+SUMIF($Y$2:$Y$4,X46,$Z$2:$Z$4)),0) -> 0
A47: SubConc(H) | B47: 3.2/3 | C47: 2 | D47: SUPERSTRUCTURE (CONT'D) | H47: =+SUM(F47:G47) -> 0 | J47: =+I47*$J$5 -> 0 | L47: =+K47*$L$5 -> 0 | M47: =+J47+L47 -> 0 | N47: =+ROUND(M47*H47,2) -> 0 | Q47: =+P47*$Q$5 -> 0 | S47: =+R47*$S$5 -> 0 | T47: =+Q47+S47 -> 0 | U47: =+ROUND(T47*H47,2) -> 0 | X47: A | Y47: =+ROUND((O47)*(1+SUMIF($Y$2:$Y$4,X47,$Z$2:$Z$4)),0) -> 0 | Z47: =+ROUND((V47)*(1+SUMIF($Y$2:$Y$4,X47,$Z$2:$Z$4)),0) -> 0
A48: SubConc(H) | B48: =+B47 -> 3.2/3 | C48: 2.4 | D48: Stairs and ramps | H48: =+SUM(F48:G48) -> 0 | J48: =+I48*$J$5 -> 0 | L48: =+K48*$L$5 -> 0 | M48: =+J48+L48 -> 0 | N48: =+ROUND(M48*H48,2) -> 0 | O48: =N48 -> 0 | Q48: =+P48*$Q$5 -> 0 | S48: =+R48*$S$5 -> 0 | T48: =+Q48+S48 -> 0 | U48: =+ROUND(T48*H48,2) -> 0 | V48: =U48 -> 0 | X48: A | Y48: =+ROUND((O48)*(1+SUMIF($Y$2:$Y$4,X48,$Z$2:$Z$4)),0) -> 0 | Z48: =+ROUND((V48)*(1+SUMIF($Y$2:$Y$4,X48,$Z$2:$Z$4)),0) -> 0
A49: SubConc(H) | B49: =+B48 -> 3.2/3 | C49: 2.4.1 | D49: Stair / ramp structures | H49: =+SUM(F49:G49) -> 0 | J49: =+I49*$J$5 -> 0 | L49: =+K49*$L$5 -> 0 | M49: =+J49+L49 -> 0 | N49: =+ROUND(M49*H49,2) -> 0 | O49: =N49 -> 0 | Q49: =+P49*$Q$5 -> 0 | S49: =+R49*$S$5 -> 0 | T49: =+Q49+S49 -> 0 | U49: =+ROUND(T49*H49,2) -> 0 | V49: =U49 -> 0 | X49: A | Y49: =+ROUND((O49)*(1+SUMIF($Y$2:$Y$4,X49,$Z$2:$Z$4)),0) -> 0 | Z49: =+ROUND((V49)*(1+SUMIF($Y$2:$Y$4,X49,$Z$2:$Z$4)),0) -> 0
A50: SubConc(H) | B50: =+B49 -> 3.2/3 | C50: 2.4.1.1 | D50: Stair structure | H50: =+SUM(F50:G50) -> 0 | J50: =+I50*$J$5 -> 0 | L50: =+K50*$L$5 -> 0 | M50: =+J50+L50 -> 0 | N50: =+ROUND(M50*H50,2) -> 0 | O50: =N50 -> 0 | Q50: =+P50*$Q$5 -> 0 | S50: =+R50*$S$5 -> 0 | T50: =+Q50+S50 -> 0 | U50: =+ROUND(T50*H50,2) -> 0 | V50: =U50 -> 0 | X50: A | Y50: =+ROUND((O50)*(1+SUMIF($Y$2:$Y$4,X50,$Z$2:$Z$4)),0) -> 0 | Z50: =+ROUND((V50)*(1+SUMIF($Y$2:$Y$4,X50,$Z$2:$Z$4)),0) -> 0
A51: SubConc(H) | B51: =+B50 -> 3.2/3 | D51: Concrete | E51: m3 | H51: =+SUM(F51:G51) -> 0 | J51: =+I51*$J$5 -> 0 | L51: =+K51*$L$5 -> 0 | M51: =+J51+L51 -> 0 | N51: =+ROUND(M51*H51,2) -> 0 | O51: =N51 -> 0 | Q51: =+P51*$Q$5 -> 0 | S51: =+R51*$S$5 -> 0 | T51: =+Q51+S51 -> 0 | U51: =+ROUND(T51*H51,2) -> 0 | V51: =U51 -> 0 | X51: A | Y51: =+ROUND((O51)*(1+SUMIF($Y$2:$Y$4,X51,$Z$2:$Z$4)),0) -> 0 | Z51: =+ROUND((V51)*(1+SUMIF($Y$2:$Y$4,X51,$Z$2:$Z$4)),0) -> 0
A52: SubFW(H) | B52: =+B51 -> 3.2/3 | D52: Formwork | E52: m2 | H52: =+SUM(F52:G52) -> 0 | J52: =+I52*$J$5 -> 0 | L52: =+K52*$L$5 -> 0 | M52: =+J52+L52 -> 0 | N52: =+ROUND(M52*H52,2) -> 0 | O52: =N52 -> 0 | Q52: =+P52*$Q$5 -> 0 | S52: =+R52*$S$5 -> 0 | T52: =+Q52+S52 -> 0 | U52: =+ROUND(T52*H52,2) -> 0 | V52: =U52 -> 0 | X52: A | Y52: =+ROUND((O52)*(1+SUMIF($Y$2:$Y$4,X52,$Z$2:$Z$4)),0) -> 0 | Z52: =+ROUND((V52)*(1+SUMIF($Y$2:$Y$4,X52,$Z$2:$Z$4)),0) -> 0
A53: SubBar(H) | B53: =+B52 -> 3.2/3 | D53: Reinforcement | H53: =+SUM(F53:G53) -> 0 | J53: =+I53*$J$5 -> 0 | L53: =+K53*$L$5 -> 0 | M53: =+J53+L53 -> 0 | N53: =+ROUND(M53*H53,2) -> 0 | O53: =N53 -> 0 | Q53: =+P53*$Q$5 -> 0 | S53: =+R53*$S$5 -> 0 | T53: =+Q53+S53 -> 0 | U53: =+ROUND(T53*H53,2) -> 0 | V53: =U53 -> 0 | X53: A | Y53: =+ROUND((O53)*(1+SUMIF($Y$2:$Y$4,X53,$Z$2:$Z$4)),0) -> 0 | Z53: =+ROUND((V53)*(1+SUMIF($Y$2:$Y$4,X53,$Z$2:$Z$4)),0) -> 0
A54: SubConc(H) | B54: =+B50 -> 3.2/3 | C54: 2.4.1.2 | D54: Ramp structure | H54: =+SUM(F54:G54) -> 0 | J54: =+I54*$J$5 -> 0 | L54: =+K54*$L$5 -> 0 | M54: =+J54+L54 -> 0 | N54: =+ROUND(M54*H54,2) -> 0 | O54: =N54 -> 0 | Q54: =+P54*$Q$5 -> 0 | S54: =+R54*$S$5 -> 0 | T54: =+Q54+S54 -> 0 | U54: =+ROUND(T54*H54,2) -> 0 | V54: =U54 -> 0 | X54: A | Y54: =+ROUND((O54)*(1+SUMIF($Y$2:$Y$4,X54,$Z$2:$Z$4)),0) -> 0 | Z54: =+ROUND((V54)*(1+SUMIF($Y$2:$Y$4,X54,$Z$2:$Z$4)),0) -> 0
A55: SubConc(H) | B55: =+B54 -> 3.2/3 | D55: Concrete | E55: m3 | H55: =+SUM(F55:G55) -> 0 | J55: =+I55*$J$5 -> 0 | L55: =+K55*$L$5 -> 0 | M55: =+J55+L55 -> 0 | N55: =+ROUND(M55*H55,2) -> 0 | O55: =N55 -> 0 | Q55: =+P55*$Q$5 -> 0 | S55: =+R55*$S$5 -> 0 | T55: =+Q55+S55 -> 0 | U55: =+ROUND(T55*H55,2) -> 0 | V55: =U55 -> 0 | X55: A | Y55: =+ROUND((O55)*(1+SUMIF($Y$2:$Y$4,X55,$Z$2:$Z$4)),0) -> 0 | Z55: =+ROUND((V55)*(1+SUMIF($Y$2:$Y$4,X55,$Z$2:$Z$4)),0) -> 0
A56: SubFW(H) | B56: =+B55 -> 3.2/3 | D56: Formwork | E56: m2 | H56: =+SUM(F56:G56) -> 0 | J56: =+I56*$J$5 -> 0 | L56: =+K56*$L$5 -> 0 | M56: =+J56+L56 -> 0 | N56: =+ROUND(M56*H56,2) -> 0 | O56: =N56 -> 0 | Q56: =+P56*$Q$5 -> 0 | S56: =+R56*$S$5 -> 0 | T56: =+Q56+S56 -> 0 | U56: =+ROUND(T56*H56,2) -> 0 | V56: =U56 -> 0 | X56: A | Y56: =+ROUND((O56)*(1+SUMIF($Y$2:$Y$4,X56,$Z$2:$Z$4)),0) -> 0 | Z56: =+ROUND((V56)*(1+SUMIF($Y$2:$Y$4,X56,$Z$2:$Z$4)),0) -> 0
A57: SubBar(H) | B57: =+B56 -> 3.2/3 | D57: Reinforcement | H57: =+SUM(F57:G57) -> 0 | J57: =+I57*$J$5 -> 0 | L57: =+K57*$L$5 -> 0 | M57: =+J57+L57 -> 0 | N57: =+ROUND(M57*H57,2) -> 0 | O57: =N57 -> 0 | Q57: =+P57*$Q$5 -> 0 | S57: =+R57*$S$5 -> 0 | T57: =+Q57+S57 -> 0 | U57: =+ROUND(T57*H57,2) -> 0 | V57: =U57 -> 0 | X57: A | Y57: =+ROUND((O57)*(1+SUMIF($Y$2:$Y$4,X57,$Z$2:$Z$4)),0) -> 0 | Z57: =+ROUND((V57)*(1+SUMIF($Y$2:$Y$4,X57,$Z$2:$Z$4)),0) -> 0
A58: Stair | B58: =+B54 -> 3.2/3 | C58: 2.4.2 | D58: Stair / ramp finishes | H58: =+SUM(F58:G58) -> 0 | J58: =+I58*$J$5 -> 0 | L58: =+K58*$L$5 -> 0 | M58: =+J58+L58 -> 0 | N58: =+ROUND(M58*H58,2) -> 0 | O58: =N58 -> 0 | Q58: =+P58*$Q$5 -> 0 | S58: =+R58*$S$5 -> 0 | T58: =+Q58+S58 -> 0 | U58: =+ROUND(T58*H58,2) -> 0 | V58: =U58 -> 0 | X58: A | Y58: =+ROUND((O58)*(1+SUMIF($Y$2:$Y$4,X58,$Z$2:$Z$4)),0) -> 0 | Z58: =+ROUND((V58)*(1+SUMIF($Y$2:$Y$4,X58,$Z$2:$Z$4)),0) -> 0
A59: Stair | B59: =+B54 -> 3.2/3 | C59: 2.4.2.1 | D59: Stair finishes | H59: =+SUM(F59:G59) -> 0 | J59: =+I59*$J$5 -> 0 | L59: =+K59*$L$5 -> 0 | M59: =+J59+L59 -> 0 | N59: =+ROUND(M59*H59,2) -> 0 | O59: =N59 -> 0 | Q59: =+P59*$Q$5 -> 0 | S59: =+R59*$S$5 -> 0 | T59: =+Q59+S59 -> 0 | U59: =+ROUND(T59*H59,2) -> 0 | V59: =U59 -> 0 | X59: A | Y59: =+ROUND((O59)*(1+SUMIF($Y$2:$Y$4,X59,$Z$2:$Z$4)),0) -> 0 | Z59: =+ROUND((V59)*(1+SUMIF($Y$2:$Y$4,X59,$Z$2:$Z$4)),0) -> 0
A60: Stair | B60: =+B58 -> 3.2/3 | C60: 2.4.2.2 | D60: Ramp finishes | H60: =+SUM(F60:G60) -> 0 | J60: =+I60*$J$5 -> 0 | L60: =+K60*$L$5 -> 0 | M60: =+J60+L60 -> 0 | N60: =+ROUND(M60*H60,2) -> 0 | O60: =N60 -> 0 | Q60: =+P60*$Q$5 -> 0 | S60: =+R60*$S$5 -> 0 | T60: =+Q60+S60 -> 0 | U60: =+ROUND(T60*H60,2) -> 0 | V60: =U60 -> 0 | X60: A | Y60: =+ROUND((O60)*(1+SUMIF($Y$2:$Y$4,X60,$Z$2:$Z$4)),0) -> 0 | Z60: =+ROUND((V60)*(1+SUMIF($Y$2:$Y$4,X60,$Z$2:$Z$4)),0) -> 0
A61: RailSteel | B61: =+B60 -> 3.2/3 | C61: 2.4.3 | D61: Stair / ramp balustrades and handrails | H61: =+SUM(F61:G61) -> 0 | J61: =+I61*$J$5 -> 0 | L61: =+K61*$L$5 -> 0 | M61: =+J61+L61 -> 0 | N61: =+ROUND(M61*H61,2) -> 0 | O61: =N61 -> 0 | Q61: =+P61*$Q$5 -> 0 | S61: =+R61*$S$5 -> 0 | T61: =+Q61+S61 -> 0 | U61: =+ROUND(T61*H61,2) -> 0 | V61: =U61 -> 0 | X61: A | Y61: =+ROUND((O61)*(1+SUMIF($Y$2:$Y$4,X61,$Z$2:$Z$4)),0) -> 0 | Z61: =+ROUND((V61)*(1+SUMIF($Y$2:$Y$4,X61,$Z$2:$Z$4)),0) -> 0
A62: RailSteel | B62: =+B60 -> 3.2/3 | C62: 2.4.3.1 | D62: Stair balustrades and handrails | E62: m | H62: =+SUM(F62:G62) -> 0 | J62: =+I62*$J$5 -> 0 | L62: =+K62*$L$5 -> 0 | M62: =+J62+L62 -> 0 | N62: =+ROUND(M62*H62,2) -> 0 | O62: =N62 -> 0 | Q62: =+P62*$Q$5 -> 0 | S62: =+R62*$S$5 -> 0 | T62: =+Q62+S62 -> 0 | U62: =+ROUND(T62*H62,2) -> 0 | V62: =U62 -> 0 | X62: A | Y62: =+ROUND((O62)*(1+SUMIF($Y$2:$Y$4,X62,$Z$2:$Z$4)),0) -> 0 | Z62: =+ROUND((V62)*(1+SUMIF($Y$2:$Y$4,X62,$Z$2:$Z$4)),0) -> 0
A63: RailSteel | B63: =+B62 -> 3.2/3 | C63: 2.4.3.2 | D63: Ramp balustrades and handrails | E63: m | H63: =+SUM(F63:G63) -> 0 | J63: =+I63*$J$5 -> 0 | L63: =+K63*$L$5 -> 0 | M63: =+J63+L63 -> 0 | N63: =+ROUND(M63*H63,2) -> 0 | O63: =N63 -> 0 | Q63: =+P63*$Q$5 -> 0 | S63: =+R63*$S$5 -> 0 | T63: =+Q63+S63 -> 0 | U63: =+ROUND(T63*H63,2) -> 0 | V63: =U63 -> 0 | X63: A | Y63: =+ROUND((O63)*(1+SUMIF($Y$2:$Y$4,X63,$Z$2:$Z$4)),0) -> 0 | Z63: =+ROUND((V63)*(1+SUMIF($Y$2:$Y$4,X63,$Z$2:$Z$4)),0) -> 0
A64: Metal | B64: =+B63 -> 3.2/3 | C64: 2.4.4 | D64: Ladders / chutes / slides | H64: =+SUM(F64:G64) -> 0 | J64: =+I64*$J$5 -> 0 | L64: =+K64*$L$5 -> 0 | M64: =+J64+L64 -> 0 | N64: =+ROUND(M64*H64,2) -> 0 | O64: =N64 -> 0 | Q64: =+P64*$Q$5 -> 0 | S64: =+R64*$S$5 -> 0 | T64: =+Q64+S64 -> 0 | U64: =+ROUND(T64*H64,2) -> 0 | V64: =U64 -> 0 | X64: A | Y64: =+ROUND((O64)*(1+SUMIF($Y$2:$Y$4,X64,$Z$2:$Z$4)),0) -> 0 | Z64: =+ROUND((V64)*(1+SUMIF($Y$2:$Y$4,X64,$Z$2:$Z$4)),0) -> 0
A65: LWPanel | B65: =+B62 -> 3.2/3 | C65: 2.5 | D65: External walls | H65: =+SUM(F65:G65) -> 0 | J65: =+I65*$J$5 -> 0 | L65: =+K65*$L$5 -> 0 | M65: =+J65+L65 -> 0 | N65: =+ROUND(M65*H65,2) -> 0 | O65: =N65 -> 0 | Q65: =+P65*$Q$5 -> 0 | S65: =+R65*$S$5 -> 0 | T65: =+Q65+S65 -> 0 | U65: =+ROUND(T65*H65,2) -> 0 | V65: =U65 -> 0 | X65: A | Y65: =+ROUND((O65)*(1+SUMIF($Y$2:$Y$4,X65,$Z$2:$Z$4)),0) -> 0 | Z65: =+ROUND((V65)*(1+SUMIF($Y$2:$Y$4,X65,$Z$2:$Z$4)),0) -> 0
A66: LWPanel | B66: =+B64 -> 3.2/3 | C66: 2.5.1 | D66: External wall including external finishes — Contractor Proposed System | H66: =+SUM(F66:G66) -> 0 | J66: =+I66*$J$5 -> 0 | L66: =+K66*$L$5 -> 0 | M66: =+J66+L66 -> 0 | N66: =+ROUND(M66*H66,2) -> 0 | O66: =N66 -> 0 | Q66: =+P66*$Q$5 -> 0 | S66: =+R66*$S$5 -> 0 | T66: =+Q66+S66 -> 0 | U66: =+ROUND(T66*H66,2) -> 0 | V66: =U66 -> 0 | X66: A | Y66: =+ROUND((O66)*(1+SUMIF($Y$2:$Y$4,X66,$Z$2:$Z$4)),0) -> 0 | Z66: =+ROUND((V66)*(1+SUMIF($Y$2:$Y$4,X66,$Z$2:$Z$4)),0) -> 0
A67: LWPanel | B67: =+B66 -> 3.2/3 | D67: External Wall | E67: m2 | H67: =+SUM(F67:G67) -> 0 | J67: =+I67*$J$5 -> 0 | L67: =+K67*$L$5 -> 0 | M67: =+J67+L67 -> 0 | N67: =+ROUND(M67*H67,2) -> 0 | O67: =N67 -> 0 | Q67: =+P67*$Q$5 -> 0 | S67: =+R67*$S$5 -> 0 | T67: =+Q67+S67 -> 0 | U67: =+ROUND(T67*H67,2) -> 0 | V67: =U67 -> 0 | X67: A | Y67: =+ROUND((O67)*(1+SUMIF($Y$2:$Y$4,X67,$Z$2:$Z$4)),0) -> 0 | Z67: =+ROUND((V67)*(1+SUMIF($Y$2:$Y$4,X67,$Z$2:$Z$4)),0) -> 0
A68: WallSkim | B68: =+B67 -> 3.2/3 | D68: Plastering | E68: m2 | H68: =+SUM(F68:G68) -> 0 | J68: =+I68*$J$5 -> 0 | L68: =+K68*$L$5 -> 0 | M68: =+J68+L68 -> 0 | N68: =+ROUND(M68*H68,2) -> 0 | O68: =N68 -> 0 | Q68: =+P68*$Q$5 -> 0 | S68: =+R68*$S$5 -> 0 | T68: =+Q68+S68 -> 0 | U68: =+ROUND(T68*H68,2) -> 0 | V68: =U68 -> 0 | X68: A | Y68: =+ROUND((O68)*(1+SUMIF($Y$2:$Y$4,X68,$Z$2:$Z$4)),0) -> 0 | Z68: =+ROUND((V68)*(1+SUMIF($Y$2:$Y$4,X68,$Z$2:$Z$4)),0) -> 0
A69: Paint | B69: =+B68 -> 3.2/3 | D69: Painting | E69: m2 | H69: =+SUM(F69:G69) -> 0 | I69: =+I68 -> 0 | J69: =+I69*$J$5 -> 0 | K69: =+K68 -> 0 | L69: =+K69*$L$5 -> 0 | M69: =+J69+L69 -> 0 | N69: =+ROUND(M69*H69,2) -> 0 | O69: =N69 -> 0 | Q69: =+P69*$Q$5 -> 0 | S69: =+R69*$S$5 -> 0 | T69: =+Q69+S69 -> 0 | U69: =+ROUND(T69*H69,2) -> 0 | V69: =U69 -> 0 | X69: A | Y69: =+ROUND((O69)*(1+SUMIF($Y$2:$Y$4,X69,$Z$2:$Z$4)),0) -> 0 | Z69: =+ROUND((V69)*(1+SUMIF($Y$2:$Y$4,X69,$Z$2:$Z$4)),0) -> 0
A70: Clad | B70: =+B66 -> 3.2/3 | C70: 2.5.2 | D70: Perforated Screen | H70: =+SUM(F70:G70) -> 0 | J70: =+I70*$J$5 -> 0 | L70: =+K70*$L$5 -> 0 | M70: =+J70+L70 -> 0 | N70: =+ROUND(M70*H70,2) -> 0 | O70: =N70 -> 0 | Q70: =+P70*$Q$5 -> 0 | S70: =+R70*$S$5 -> 0 | T70: =+Q70+S70 -> 0 | U70: =+ROUND(T70*H70,2) -> 0 | V70: =U70 -> 0 | X70: A | Y70: =+ROUND((O70)*(1+SUMIF($Y$2:$Y$4,X70,$Z$2:$Z$4)),0) -> 0 | Z70: =+ROUND((V70)*(1+SUMIF($Y$2:$Y$4,X70,$Z$2:$Z$4)),0) -> 0
A71: Clad | B71: =+B70 -> 3.2/3 | C71: 2.5.3 | D71: Corrugated steel cladding | H71: =+SUM(F71:G71) -> 0 | J71: =+I71*$J$5 -> 0 | L71: =+K71*$L$5 -> 0 | M71: =+J71+L71 -> 0 | N71: =+ROUND(M71*H71,2) -> 0 | O71: =N71 -> 0 | Q71: =+P71*$Q$5 -> 0 | S71: =+R71*$S$5 -> 0 | T71: =+Q71+S71 -> 0 | U71: =+ROUND(T71*H71,2) -> 0 | V71: =U71 -> 0 | X71: A | Y71: =+ROUND((O71)*(1+SUMIF($Y$2:$Y$4,X71,$Z$2:$Z$4)),0) -> 0 | Z71: =+ROUND((V71)*(1+SUMIF($Y$2:$Y$4,X71,$Z$2:$Z$4)),0) -> 0
A72: Collection | B72: =+B71 -> 3.2/3 | D72: To Collection: | H72: =+SUM(F72:G72) -> 0 | J72: =+I72*$J$5 -> 0 | L72: =+K72*$L$5 -> 0 | M72: =+J72+L72 -> 0 | N72: =SUM(N47:N71) -> 0 | O72: =SUM(O47:O71) -> 0 | Q72: =+P72*$Q$5 -> 0 | S72: =+R72*$S$5 -> 0 | T72: =+Q72+S72 -> 0 | U72: =SUM(U47:U71) -> 0 | V72: =SUM(V47:V71) -> 0 | X72: A | Y72: =+ROUND((O72)*(1+SUMIF($Y$2:$Y$4,X72,$Z$2:$Z$4)),0) -> 0 | Z72: =+ROUND((V72)*(1+SUMIF($Y$2:$Y$4,X72,$Z$2:$Z$4)),0) -> 0
A73: Alum | B73: 3.2/4 | C73: 2 | D73: SUPERSTRUCTURE (CONT'D) | H73: =+SUM(F73:G73) -> 0 | J73: =+I73*$J$5 -> 0 | L73: =+K73*$L$5 -> 0 | M73: =+J73+L73 -> 0 | N73: =+ROUND(M73*H73,2) -> 0 | Q73: =+P73*$Q$5 -> 0 | S73: =+R73*$S$5 -> 0 | T73: =+Q73+S73 -> 0 | U73: =+ROUND(T73*H73,2) -> 0 | X73: A | Y73: =+ROUND((O73)*(1+SUMIF($Y$2:$Y$4,X73,$Z$2:$Z$4)),0) -> 0 | Z73: =+ROUND((V73)*(1+SUMIF($Y$2:$Y$4,X73,$Z$2:$Z$4)),0) -> 0
A74: Alum | B74: =+B73 -> 3.2/4 | C74: 2.6 | D74: Windows and external doors | H74: =+SUM(F74:G74) -> 0 | J74: =+I74*$J$5 -> 0 | L74: =+K74*$L$5 -> 0 | M74: =+J74+L74 -> 0 | N74: =+ROUND(M74*H74,2) -> 0 | O74: =N74 -> 0 | Q74: =+P74*$Q$5 -> 0 | S74: =+R74*$S$5 -> 0 | T74: =+Q74+S74 -> 0 | U74: =+ROUND(T74*H74,2) -> 0 | V74: =U74 -> 0 | X74: A | Y74: =+ROUND((O74)*(1+SUMIF($Y$2:$Y$4,X74,$Z$2:$Z$4)),0) -> 0 | Z74: =+ROUND((V74)*(1+SUMIF($Y$2:$Y$4,X74,$Z$2:$Z$4)),0) -> 0
A75: Alum | B75: =+B73 -> 3.2/4 | C75: 2.6.1 | D75: External windows | H75: =+SUM(F75:G75) -> 0 | J75: =+I75*$J$5 -> 0 | L75: =+K75*$L$5 -> 0 | M75: =+J75+L75 -> 0 | N75: =+ROUND(M75*H75,2) -> 0 | O75: =N75 -> 0 | Q75: =+P75*$Q$5 -> 0 | S75: =+R75*$S$5 -> 0 | T75: =+Q75+S75 -> 0 | U75: =+ROUND(T75*H75,2) -> 0 | V75: =U75 -> 0 | X75: A | Y75: =+ROUND((O75)*(1+SUMIF($Y$2:$Y$4,X75,$Z$2:$Z$4)),0) -> 0 | Z75: =+ROUND((V75)*(1+SUMIF($Y$2:$Y$4,X75,$Z$2:$Z$4)),0) -> 0
A76: Alum | B76: =+B74 -> 3.2/4 | C76: 2.6.1.1 | D76: Window | E76: no | H76: =+SUM(F76:G76) -> 0 | J76: =+I76*$J$5 -> 0 | L76: =+K76*$L$5 -> 0 | M76: =+J76+L76 -> 0 | N76: =+ROUND(M76*H76,2) -> 0 | O76: =N76 -> 0 | Q76: =+P76*$Q$5 -> 0 | S76: =+R76*$S$5 -> 0 | T76: =+Q76+S76 -> 0 | U76: =+ROUND(T76*H76,2) -> 0 | V76: =U76 -> 0 | X76: A | Y76: =+ROUND((O76)*(1+SUMIF($Y$2:$Y$4,X76,$Z$2:$Z$4)),0) -> 0 | Z76: =+ROUND((V76)*(1+SUMIF($Y$2:$Y$4,X76,$Z$2:$Z$4)),0) -> 0
A77: Alum | B77: =+B76 -> 3.2/4 | C77: 2.6.1.2 | D77: Louvres | E77: m2 | H77: =+SUM(F77:G77) -> 0 | J77: =+I77*$J$5 -> 0 | L77: =+K77*$L$5 -> 0 | M77: =+J77+L77 -> 0 | N77: =+ROUND(M77*H77,2) -> 0 | O77: =N77 -> 0 | Q77: =+P77*$Q$5 -> 0 | S77: =+R77*$S$5 -> 0 | T77: =+Q77+S77 -> 0 | U77: =+ROUND(T77*H77,2) -> 0 | V77: =U77 -> 0 | X77: A | Y77: =+ROUND((O77)*(1+SUMIF($Y$2:$Y$4,X77,$Z$2:$Z$4)),0) -> 0 | Z77: =+ROUND((V77)*(1+SUMIF($Y$2:$Y$4,X77,$Z$2:$Z$4)),0) -> 0
A78: DoorMetal | B78: =+B77 -> 3.2/4 | C78: 2.6.2.1 | D78: External doors | H78: =+SUM(F78:G78) -> 0 | J78: =+I78*$J$5 -> 0 | L78: =+K78*$L$5 -> 0 | M78: =+J78+L78 -> 0 | N78: =+ROUND(M78*H78,2) -> 0 | O78: =N78 -> 0 | Q78: =+P78*$Q$5 -> 0 | S78: =+R78*$S$5 -> 0 | T78: =+Q78+S78 -> 0 | U78: =+ROUND(T78*H78,2) -> 0 | V78: =U78 -> 0 | X78: A | Y78: =+ROUND((O78)*(1+SUMIF($Y$2:$Y$4,X78,$Z$2:$Z$4)),0) -> 0 | Z78: =+ROUND((V78)*(1+SUMIF($Y$2:$Y$4,X78,$Z$2:$Z$4)),0) -> 0
A79: DoorMetal | B79: =+B78 -> 3.2/4 | D79: Main Door; size: | E79: no | H79: =+SUM(F79:G79) -> 0 | J79: =+I79*$J$5 -> 0 | L79: =+K79*$L$5 -> 0 | M79: =+J79+L79 -> 0 | N79: =+ROUND(M79*H79,2) -> 0 | O79: =N79 -> 0 | Q79: =+P79*$Q$5 -> 0 | S79: =+R79*$S$5 -> 0 | T79: =+Q79+S79 -> 0 | U79: =+ROUND(T79*H79,2) -> 0 | V79: =U79 -> 0 | X79: A | Y79: =+ROUND((O79)*(1+SUMIF($Y$2:$Y$4,X79,$Z$2:$Z$4)),0) -> 0 | Z79: =+ROUND((V79)*(1+SUMIF($Y$2:$Y$4,X79,$Z$2:$Z$4)),0) -> 0
A80: RS | B80: =+B78 -> 3.2/4 | C80: 2.6.2.2 | D80: Roller shutters, sliding shutters and the like to external door openings | H80: =+SUM(F80:G80) -> 0 | J80: =+I80*$J$5 -> 0 | L80: =+K80*$L$5 -> 0 | M80: =+J80+L80 -> 0 | N80: =+ROUND(M80*H80,2) -> 0 | O80: =N80 -> 0 | Q80: =+P80*$Q$5 -> 0 | S80: =+R80*$S$5 -> 0 | T80: =+Q80+S80 -> 0 | U80: =+ROUND(T80*H80,2) -> 0 | V80: =U80 -> 0 | X80: A | Y80: =+ROUND((O80)*(1+SUMIF($Y$2:$Y$4,X80,$Z$2:$Z$4)),0) -> 0 | Z80: =+ROUND((V80)*(1+SUMIF($Y$2:$Y$4,X80,$Z$2:$Z$4)),0) -> 0
A81: RS | B81: =+B80 -> 3.2/4 | D81: RS; size: | E81: no | H81: =+SUM(F81:G81) -> 0 | J81: =+I81*$J$5 -> 0 | L81: =+K81*$L$5 -> 0 | M81: =+J81+L81 -> 0 | N81: =+ROUND(M81*H81,2) -> 0 | O81: =N81 -> 0 | Q81: =+P81*$Q$5 -> 0 | S81: =+R81*$S$5 -> 0 | T81: =+Q81+S81 -> 0 | U81: =+ROUND(T81*H81,2) -> 0 | V81: =U81 -> 0 | X81: A | Y81: =+ROUND((O81)*(1+SUMIF($Y$2:$Y$4,X81,$Z$2:$Z$4)),0) -> 0 | Z81: =+ROUND((V81)*(1+SUMIF($Y$2:$Y$4,X81,$Z$2:$Z$4)),0) -> 0
A82: Partition | B82: =+B80 -> 3.2/4 | C82: 2.7 | D82: Internal walls and partitions | H82: =+SUM(F82:G82) -> 0 | J82: =+I82*$J$5 -> 0 | L82: =+K82*$L$5 -> 0 | M82: =+J82+L82 -> 0 | N82: =+ROUND(M82*H82,2) -> 0 | O82: =N82 -> 0 | Q82: =+P82*$Q$5 -> 0 | S82: =+R82*$S$5 -> 0 | T82: =+Q82+S82 -> 0 | U82: =+ROUND(T82*H82,2) -> 0 | V82: =U82 -> 0 | X82: A | Y82: =+ROUND((O82)*(1+SUMIF($Y$2:$Y$4,X82,$Z$2:$Z$4)),0) -> 0 | Z82: =+ROUND((V82)*(1+SUMIF($Y$2:$Y$4,X82,$Z$2:$Z$4)),0) -> 0
A83: Partition | B83: =+B80 -> 3.2/4 | C83: 2.7.1 | D83: Internal wall partition system — Contractor Proposed System | H83: =+SUM(F83:G83) -> 0 | J83: =+I83*$J$5 -> 0 | L83: =+K83*$L$5 -> 0 | M83: =+J83+L83 -> 0 | N83: =+ROUND(M83*H83,2) -> 0 | O83: =N83 -> 0 | Q83: =+P83*$Q$5 -> 0 | S83: =+R83*$S$5 -> 0 | T83: =+Q83+S83 -> 0 | U83: =+ROUND(T83*H83,2) -> 0 | V83: =U83 -> 0 | X83: A | Y83: =+ROUND((O83)*(1+SUMIF($Y$2:$Y$4,X83,$Z$2:$Z$4)),0) -> 0 | Z83: =+ROUND((V83)*(1+SUMIF($Y$2:$Y$4,X83,$Z$2:$Z$4)),0) -> 0
A84: Partition | B84: =+B83 -> 3.2/4 | D84: Internal Wall | E84: m2 | H84: =+SUM(F84:G84) -> 0 | J84: =+I84*$J$5 -> 0 | L84: =+K84*$L$5 -> 0 | M84: =+J84+L84 -> 0 | N84: =+ROUND(M84*H84,2) -> 0 | O84: =N84 -> 0 | Q84: =+P84*$Q$5 -> 0 | S84: =+R84*$S$5 -> 0 | T84: =+Q84+S84 -> 0 | U84: =+ROUND(T84*H84,2) -> 0 | V84: =U84 -> 0 | X84: A | Y84: =+ROUND((O84)*(1+SUMIF($Y$2:$Y$4,X84,$Z$2:$Z$4)),0) -> 0 | Z84: =+ROUND((V84)*(1+SUMIF($Y$2:$Y$4,X84,$Z$2:$Z$4)),0) -> 0
A85: Paint | B85: =+B84 -> 3.2/4 | D85: Painting | E85: m2 | H85: =+SUM(F85:G85) -> 0 | J85: =+I85*$J$5 -> 0 | L85: =+K85*$L$5 -> 0 | M85: =+J85+L85 -> 0 | N85: =+ROUND(M85*H85,2) -> 0 | O85: =N85 -> 0 | Q85: =+P85*$Q$5 -> 0 | S85: =+R85*$S$5 -> 0 | T85: =+Q85+S85 -> 0 | U85: =+ROUND(T85*H85,2) -> 0 | V85: =U85 -> 0 | X85: A | Y85: =+ROUND((O85)*(1+SUMIF($Y$2:$Y$4,X85,$Z$2:$Z$4)),0) -> 0 | Z85: =+ROUND((V85)*(1+SUMIF($Y$2:$Y$4,X85,$Z$2:$Z$4)),0) -> 0
A86: Tcubicle | B86: =+B83 -> 3.2/4 | C86: 2.7.2 | D86: Phenolic compact laminate board with door and accessories | H86: =+SUM(F86:G86) -> 0 | J86: =+I86*$J$5 -> 0 | L86: =+K86*$L$5 -> 0 | M86: =+J86+L86 -> 0 | N86: =+ROUND(M86*H86,2) -> 0 | O86: =N86 -> 0 | Q86: =+P86*$Q$5 -> 0 | S86: =+R86*$S$5 -> 0 | T86: =+Q86+S86 -> 0 | U86: =+ROUND(T86*H86,2) -> 0 | V86: =U86 -> 0 | X86: A | Y86: =+ROUND((O86)*(1+SUMIF($Y$2:$Y$4,X86,$Z$2:$Z$4)),0) -> 0 | Z86: =+ROUND((V86)*(1+SUMIF($Y$2:$Y$4,X86,$Z$2:$Z$4)),0) -> 0
A87: DoorMetal | B87: =+B86 -> 3.2/4 | C87: 2.8 | D87: Internal doors | H87: =+SUM(F87:G87) -> 0 | J87: =+I87*$J$5 -> 0 | L87: =+K87*$L$5 -> 0 | M87: =+J87+L87 -> 0 | N87: =+ROUND(M87*H87,2) -> 0 | O87: =N87 -> 0 | Q87: =+P87*$Q$5 -> 0 | S87: =+R87*$S$5 -> 0 | T87: =+Q87+S87 -> 0 | U87: =+ROUND(T87*H87,2) -> 0 | V87: =U87 -> 0 | X87: A | Y87: =+ROUND((O87)*(1+SUMIF($Y$2:$Y$4,X87,$Z$2:$Z$4)),0) -> 0 | Z87: =+ROUND((V87)*(1+SUMIF($Y$2:$Y$4,X87,$Z$2:$Z$4)),0) -> 0
A88: DoorMetal | B88: =+B86 -> 3.2/4 | C88: 2.8.1 | D88: Internal doors | H88: =+SUM(F88:G88) -> 0 | J88: =+I88*$J$5 -> 0 | L88: =+K88*$L$5 -> 0 | M88: =+J88+L88 -> 0 | N88: =+ROUND(M88*H88,2) -> 0 | O88: =N88 -> 0 | Q88: =+P88*$Q$5 -> 0 | S88: =+R88*$S$5 -> 0 | T88: =+Q88+S88 -> 0 | U88: =+ROUND(T88*H88,2) -> 0 | V88: =U88 -> 0 | X88: A | Y88: =+ROUND((O88)*(1+SUMIF($Y$2:$Y$4,X88,$Z$2:$Z$4)),0) -> 0 | Z88: =+ROUND((V88)*(1+SUMIF($Y$2:$Y$4,X88,$Z$2:$Z$4)),0) -> 0
A89: DoorMetal | B89: =+B87 -> 3.2/4 | D89: Main Door; size: | E89: no | H89: =+SUM(F89:G89) -> 0 | J89: =+I89*$J$5 -> 0 | L89: =+K89*$L$5 -> 0 | M89: =+J89+L89 -> 0 | N89: =+ROUND(M89*H89,2) -> 0 | O89: =N89 -> 0 | Q89: =+P89*$Q$5 -> 0 | S89: =+R89*$S$5 -> 0 | T89: =+Q89+S89 -> 0 | U89: =+ROUND(T89*H89,2) -> 0 | V89: =U89 -> 0 | X89: A | Y89: =+ROUND((O89)*(1+SUMIF($Y$2:$Y$4,X89,$Z$2:$Z$4)),0) -> 0 | Z89: =+ROUND((V89)*(1+SUMIF($Y$2:$Y$4,X89,$Z$2:$Z$4)),0) -> 0
A90: DoorMetal | B90: =+B88 -> 3.2/4 | H90: =+SUM(F90:G90) -> 0 | J90: =+I90*$J$5 -> 0 | L90: =+K90*$L$5 -> 0 | M90: =+J90+L90 -> 0 | N90: =+ROUND(M90*H90,2) -> 0 | O90: =N90 -> 0 | Q90: =+P90*$Q$5 -> 0 | S90: =+R90*$S$5 -> 0 | T90: =+Q90+S90 -> 0 | U90: =+ROUND(T90*H90,2) -> 0 | V90: =U90 -> 0 | X90: A | Y90: =+ROUND((O90)*(1+SUMIF($Y$2:$Y$4,X90,$Z$2:$Z$4)),0) -> 0 | Z90: =+ROUND((V90)*(1+SUMIF($Y$2:$Y$4,X90,$Z$2:$Z$4)),0) -> 0
A91: Collection | B91: =+B88 -> 3.2/4 | D91: To Collection: | H91: =+SUM(F91:G91) -> 0 | J91: =+I91*$J$5 -> 0 | L91: =+K91*$L$5 -> 0 | M91: =+J91+L91 -> 0 | N91: =SUM(N73:N88) -> 0 | O91: =SUM(O73:O88) -> 0 | Q91: =+P91*$Q$5 -> 0 | S91: =+R91*$S$5 -> 0 | T91: =+Q91+S91 -> 0 | U91: =SUM(U73:U88) -> 0 | V91: =SUM(V73:V88) -> 0 | X91: A | Y91: =+ROUND((O91)*(1+SUMIF($Y$2:$Y$4,X91,$Z$2:$Z$4)),0) -> 0 | Z91: =+ROUND((V91)*(1+SUMIF($Y$2:$Y$4,X91,$Z$2:$Z$4)),0) -> 0
A92: FloorVinyl | B92: 3.2/5 | C92: 3 | D92: INTERNAL FINISHES | H92: =+SUM(F92:G92) -> 0 | J92: =+I92*$J$5 -> 0 | L92: =+K92*$L$5 -> 0 | M92: =+J92+L92 -> 0 | N92: =+ROUND(M92*H92,2) -> 0 | Q92: =+P92*$Q$5 -> 0 | S92: =+R92*$S$5 -> 0 | T92: =+Q92+S92 -> 0 | U92: =+ROUND(T92*H92,2) -> 0 | X92: A | Y92: =+ROUND((O92)*(1+SUMIF($Y$2:$Y$4,X92,$Z$2:$Z$4)),0) -> 0 | Z92: =+ROUND((V92)*(1+SUMIF($Y$2:$Y$4,X92,$Z$2:$Z$4)),0) -> 0
A93: FloorVinyl | B93: =+B92 -> 3.2/5 | C93: 3.1 | D93: Floor Finishes | H93: =+SUM(F93:G93) -> 0 | J93: =+I93*$J$5 -> 0 | L93: =+K93*$L$5 -> 0 | M93: =+J93+L93 -> 0 | N93: =+ROUND(M93*H93,2) -> 0 | O93: =N93 -> 0 | Q93: =+P93*$Q$5 -> 0 | S93: =+R93*$S$5 -> 0 | T93: =+Q93+S93 -> 0 | U93: =+ROUND(T93*H93,2) -> 0 | V93: =U93 -> 0 | X93: A | Y93: =+ROUND((O93)*(1+SUMIF($Y$2:$Y$4,X93,$Z$2:$Z$4)),0) -> 0 | Z93: =+ROUND((V93)*(1+SUMIF($Y$2:$Y$4,X93,$Z$2:$Z$4)),0) -> 0
A94: FloorVinyl | B94: =+B92 -> 3.2/5 | C94: 3.1.1 | D94: Heavy duty vinyl sheet to Dormitory Bedrooms and areas as specified | H94: =+SUM(F94:G94) -> 0 | J94: =+I94*$J$5 -> 0 | L94: =+K94*$L$5 -> 0 | M94: =+J94+L94 -> 0 | N94: =+ROUND(M94*H94,2) -> 0 | O94: =N94 -> 0 | Q94: =+P94*$Q$5 -> 0 | S94: =+R94*$S$5 -> 0 | T94: =+Q94+S94 -> 0 | U94: =+ROUND(T94*H94,2) -> 0 | V94: =U94 -> 0 | X94: A | Y94: =+ROUND((O94)*(1+SUMIF($Y$2:$Y$4,X94,$Z$2:$Z$4)),0) -> 0 | Z94: =+ROUND((V94)*(1+SUMIF($Y$2:$Y$4,X94,$Z$2:$Z$4)),0) -> 0
A95: FloorVinyl | B95: =+B94 -> 3.2/5 | D95: Self-screed levelling | E95: m2 | H95: =+SUM(F95:G95) -> 0 | J95: =+I95*$J$5 -> 0 | L95: =+K95*$L$5 -> 0 | M95: =+J95+L95 -> 0 | N95: =+ROUND(M95*H95,2) -> 0 | O95: =N95 -> 0 | Q95: =+P95*$Q$5 -> 0 | S95: =+R95*$S$5 -> 0 | T95: =+Q95+S95 -> 0 | U95: =+ROUND(T95*H95,2) -> 0 | V95: =U95 -> 0 | X95: A | Y95: =+ROUND((O95)*(1+SUMIF($Y$2:$Y$4,X95,$Z$2:$Z$4)),0) -> 0 | Z95: =+ROUND((V95)*(1+SUMIF($Y$2:$Y$4,X95,$Z$2:$Z$4)),0) -> 0
A96: FloorVinyl | B96: =+B95 -> 3.2/5 | D96: Vinyl | E96: m2 | H96: =+SUM(F96:G96) -> 0 | J96: =+I96*$J$5 -> 0 | L96: =+K96*$L$5 -> 0 | M96: =+J96+L96 -> 0 | N96: =+ROUND(M96*H96,2) -> 0 | O96: =N96 -> 0 | Q96: =+P96*$Q$5 -> 0 | S96: =+R96*$S$5 -> 0 | T96: =+Q96+S96 -> 0 | U96: =+ROUND(T96*H96,2) -> 0 | V96: =U96 -> 0 | X96: A | Y96: =+ROUND((O96)*(1+SUMIF($Y$2:$Y$4,X96,$Z$2:$Z$4)),0) -> 0 | Z96: =+ROUND((V96)*(1+SUMIF($Y$2:$Y$4,X96,$Z$2:$Z$4)),0) -> 0
A97: FloorVinyl | B97: =+B96 -> 3.2/5 | D97: Upturn skirting | E97: m | H97: =+SUM(F97:G97) -> 0 | J97: =+I97*$J$5 -> 0 | L97: =+K97*$L$5 -> 0 | M97: =+J97+L97 -> 0 | N97: =+ROUND(M97*H97,2) -> 0 | O97: =N97 -> 0 | Q97: =+P97*$Q$5 -> 0 | S97: =+R97*$S$5 -> 0 | T97: =+Q97+S97 -> 0 | U97: =+ROUND(T97*H97,2) -> 0 | V97: =U97 -> 0 | X97: A | Y97: =+ROUND((O97)*(1+SUMIF($Y$2:$Y$4,X97,$Z$2:$Z$4)),0) -> 0 | Z97: =+ROUND((V97)*(1+SUMIF($Y$2:$Y$4,X97,$Z$2:$Z$4)),0) -> 0
A98: SupplyTile | B98: =+B94 -> 3.2/5 | C98: 3.1.2 | D98: Slip-resistance ceramic tiles to Dormitory Toilets and areas as specified | H98: =+SUM(F98:G98) -> 0 | J98: =+I98*$J$5 -> 0 | L98: =+K98*$L$5 -> 0 | M98: =+J98+L98 -> 0 | N98: =+ROUND(M98*H98,2) -> 0 | O98: =N98 -> 0 | Q98: =+P98*$Q$5 -> 0 | S98: =+R98*$S$5 -> 0 | T98: =+Q98+S98 -> 0 | U98: =+ROUND(T98*H98,2) -> 0 | V98: =U98 -> 0 | X98: A | Y98: =+ROUND((O98)*(1+SUMIF($Y$2:$Y$4,X98,$Z$2:$Z$4)),0) -> 0 | Z98: =+ROUND((V98)*(1+SUMIF($Y$2:$Y$4,X98,$Z$2:$Z$4)),0) -> 0
A99: SupplyTile | B99: =+B98 -> 3.2/5 | D99: Supply only for toilet floor tiles | E99: m2 | H99: =+SUM(F99:G99) -> 0 | J99: =+I99*$J$5 -> 0 | L99: =+K99*$L$5 -> 0 | M99: =+J99+L99 -> 0 | N99: =+ROUND(M99*H99,2) -> 0 | O99: =N99 -> 0 | Q99: =+P99*$Q$5 -> 0 | S99: =+R99*$S$5 -> 0 | T99: =+Q99+S99 -> 0 | U99: =+ROUND(T99*H99,2) -> 0 | V99: =U99 -> 0 | X99: A | Y99: =+ROUND((O99)*(1+SUMIF($Y$2:$Y$4,X99,$Z$2:$Z$4)),0) -> 0 | Z99: =+ROUND((V99)*(1+SUMIF($Y$2:$Y$4,X99,$Z$2:$Z$4)),0) -> 0
A100: FloorTile | B100: =+B99 -> 3.2/5 | D100: Lay only for toilet floor tiles | E100: m2 | H100: =+SUM(F100:G100) -> 0 | J100: =+I100*$J$5 -> 0 | L100: =+K100*$L$5 -> 0 | M100: =+J100+L100 -> 0 | N100: =+ROUND(M100*H100,2) -> 0 | O100: =N100 -> 0 | Q100: =+P100*$Q$5 -> 0 | S100: =+R100*$S$5 -> 0 | T100: =+Q100+S100 -> 0 | U100: =+ROUND(T100*H100,2) -> 0 | V100: =U100 -> 0 | X100: A | Y100: =+ROUND((O100)*(1+SUMIF($Y$2:$Y$4,X100,$Z$2:$Z$4)),0) -> 0 | Z100: =+ROUND((V100)*(1+SUMIF($Y$2:$Y$4,X100,$Z$2:$Z$4)),0) -> 0
...

Sheet Sec 4 - External Works
A1: Tender No: CE/25/T5/P/896 | L1: Generally | Q1: Markup
Q2: A | R2: 0.2
A3: SECTION 4 | Q3: B | R3: 0.1 | S3: PC rate
A4: DESIGN AND BUILD OF COASTAL DORMITORY EXPANSION FOR CHANGI EAST DEVELOPMENT | Q4: C
A6: CODE | B6: PAGE | C6: ITEM | D6: DESCRIPTION | E6: UNIT | F6: Material (S$) | G6: Labour (S$) | H6: U/RATE (S$) | I6: Phase A Qty | J6: Phase A Sub-Total | K6: Phase A Amount (S$) | L6: Phase B Qty | M6: Phase B Sub-Total | N6: Phase B Amount (S$) | O6: REMARKS | P6: MARKUP CODE | Q6: Phase A SUBMISSION AMOUNT (S$) | R6: Phase B SUBMISSION AMOUNT (S$)
A7: Ext | B7: 4.2/7 | D7: SECTION NO 4.2 — EXTERNAL WORKS | H7: =+SUM(F7:G7) -> 0 | J7: =+ROUND(I7*H7,2) -> 0 | K7: =SUM(J7:J7) -> 0 | M7: =+ROUND(L7*H7,2) -> 0 | N7: =SUM(M7:M7) -> 0 | P7: A | Q7: =+ROUND((K7)*(1+SUMIF($Q$2:$Q$4,P7,$R$2:$R$4)),0) -> 0 | R7: =+ROUND((N7)*(1+SUMIF($Q$2:$Q$4,P7,$R$2:$R$4)),0) -> 0
A8: Ext | B8: =+B7 -> 4.2/7 | C8: 1 | D8: SITE PREPARATION WORKS | H8: =+SUM(F8:G8) -> 0 | J8: =+ROUND(I8*H8,2) -> 0 | K8: =SUM(J8:J8) -> 0 | M8: =+ROUND(L8*H8,2) -> 0 | N8: =SUM(M8:M8) -> 0 | P8: A | Q8: =+ROUND((K8)*(1+SUMIF($Q$2:$Q$4,P8,$R$2:$R$4)),0) -> 0 | R8: =+ROUND((N8)*(1+SUMIF($Q$2:$Q$4,P8,$R$2:$R$4)),0) -> 0
A9: Ext | B9: =+B8 -> 4.2/7 | C9: 1.1 | D9: Site Clearance | H9: =+SUM(F9:G9) -> 0 | J9: =+ROUND(I9*H9,2) -> 0 | K9: =SUM(J9:J9) -> 0 | M9: =+ROUND(L9*H9,2) -> 0 | N9: =SUM(M9:M9) -> 0 | P9: A | Q9: =+ROUND((K9)*(1+SUMIF($Q$2:$Q$4,P9,$R$2:$R$4)),0) -> 0 | R9: =+ROUND((N9)*(1+SUMIF($Q$2:$Q$4,P9,$R$2:$R$4)),0) -> 0
A10: Ext | B10: =+B7 -> 4.2/7 | C10: 1.1.1 | D10: Provision of all machinery, equipment, labour, materials, tools including transportation for carting off excess earth and importing suitable earth necessary for the cut, fill, top up, consolidate and level up of existing ground to the proposed platform levels. | E10: Item | H10: =+SUM(F10:G10) -> 0 | J10: =+ROUND(I10*H10,2) -> 0 | K10: =SUM(J10:J10) -> 0 | M10: =+ROUND(L10*H10,2) -> 0 | N10: =SUM(M10:M10) -> 0 | P10: A | Q10: =+ROUND((K10)*(1+SUMIF($Q$2:$Q$4,P10,$R$2:$R$4)),0) -> 0 | R10: =+ROUND((N10)*(1+SUMIF($Q$2:$Q$4,P10,$R$2:$R$4)),0) -> 0
A11: Termite | B11: =+B10 -> 4.2/7 | C11: 1.1.2 | D11: Anti-termite treatment system to external areas. | E11: Item | H11: =+SUM(F11:G11) -> 0 | J11: =+ROUND(I11*H11,2) -> 0 | K11: =SUM(J11:J11) -> 0 | M11: =+ROUND(L11*H11,2) -> 0 | N11: =SUM(M11:M11) -> 0 | P11: A | Q11: =+ROUND((K11)*(1+SUMIF($Q$2:$Q$4,P11,$R$2:$R$4)),0) -> 0 | R11: =+ROUND((N11)*(1+SUMIF($Q$2:$Q$4,P11,$R$2:$R$4)),0) -> 0
A12: Earth | B12: =+B11 -> 4.2/7 | C12: 2 | D12: EARTHWORKS | H12: =+SUM(F12:G12) -> 0 | J12: =+ROUND(I12*H12,2) -> 0 | K12: =SUM(J12:J12) -> 0 | M12: =+ROUND(L12*H12,2) -> 0 | N12: =SUM(M12:M12) -> 0 | P12: A | Q12: =+ROUND((K12)*(1+SUMIF($Q$2:$Q$4,P12,$R$2:$R$4)),0) -> 0 | R12: =+ROUND((N12)*(1+SUMIF($Q$2:$Q$4,P12,$R$2:$R$4)),0) -> 0
A13: Earth | B13: =+B12 -> 4.2/7 | C13: 2.1 | D13: Excavation and Backfilling | H13: =+SUM(F13:G13) -> 0 | J13: =+ROUND(I13*H13,2) -> 0 | K13: =SUM(J13:J13) -> 0 | M13: =+ROUND(L13*H13,2) -> 0 | N13: =SUM(M13:M13) -> 0 | P13: A | Q13: =+ROUND((K13)*(1+SUMIF($Q$2:$Q$4,P13,$R$2:$R$4)),0) -> 0 | R13: =+ROUND((N13)*(1+SUMIF($Q$2:$Q$4,P13,$R$2:$R$4)),0) -> 0
A14: Earth | B14: =+B11 -> 4.2/7 | C14: 2.1.1 | D14: To carry out excavation and backfilling works to the required design platform levels of RL106.50. All fill material shall be properly graded to the required fall and compacted to the Minimum AASHTO density of 90% and any deviation in backfill material will subject to S.O. approval. All fill material shall conform to the Specifications and shall be subjected to the approval of the S.O. All fill material shall be supplied from the Contractor's own source, unless otherwise instructed by the S.O. | E14: Item | H14: =+SUM(F14:G14) -> 0 | J14: =+ROUND(I14*H14,2) -> 0 | K14: =SUM(J14:J14) -> 0 | M14: =+ROUND(L14*H14,2) -> 0 | N14: =SUM(M14:M14) -> 0 | P14: A | Q14: =+ROUND((K14)*(1+SUMIF($Q$2:$Q$4,P14,$R$2:$R$4)),0) -> 0 | R14: =+ROUND((N14)*(1+SUMIF($Q$2:$Q$4,P14,$R$2:$R$4)),0) -> 0
A15: Road | B15: =+B14 -> 4.2/7 | C15: 3 | D15: ROADS / PAVINGS WORKS | H15: =+SUM(F15:G15) -> 0 | J15: =+ROUND(I15*H15,2) -> 0 | K15: =SUM(J15:J15) -> 0 | M15: =+ROUND(L15*H15,2) -> 0 | N15: =SUM(M15:M15) -> 0 | P15: A | Q15: =+ROUND((K15)*(1+SUMIF($Q$2:$Q$4,P15,$R$2:$R$4)),0) -> 0 | R15: =+ROUND((N15)*(1+SUMIF($Q$2:$Q$4,P15,$R$2:$R$4)),0) -> 0
A16: Road | B16: =+B15 -> 4.2/7 | C16: 3.1 | D16: Roads, paths and pavings | H16: =+SUM(F16:G16) -> 0 | J16: =+ROUND(I16*H16,2) -> 0 | K16: =SUM(J16:J16) -> 0 | M16: =+ROUND(L16*H16,2) -> 0 | N16: =SUM(M16:M16) -> 0 | P16: A | Q16: =+ROUND((K16)*(1+SUMIF($Q$2:$Q$4,P16,$R$2:$R$4)),0) -> 0 | R16: =+ROUND((N16)*(1+SUMIF($Q$2:$Q$4,P16,$R$2:$R$4)),0) -> 0
A17: Road | B17: =+B14 -> 4.2/7 | C17: D | D17: To carry out road/paving works including Fire Engine Access and Carriageways, Traffic Ingress/Egress etc. as per design (all necessary road marking, directional signages and finishes are deemed to be included in the tender) complying to LTA standards, laid on graded aggregate base, sub-base and compacted earth sub-grade, all as specified in the drawings | E17: Item | H17: =+SUM(F17:G17) -> 0 | J17: =+ROUND(I17*H17,2) -> 0 | K17: =SUM(J17:J17) -> 0 | M17: =+ROUND(L17*H17,2) -> 0 | N17: =SUM(M17:M17) -> 0 | P17: A | Q17: =+ROUND((K17)*(1+SUMIF($Q$2:$Q$4,P17,$R$2:$R$4)),0) -> 0 | R17: =+ROUND((N17)*(1+SUMIF($Q$2:$Q$4,P17,$R$2:$R$4)),0) -> 0
A18: MiscExt | B18: =+B17 -> 4.2/7 | C18: 4 | D18: VEHICLE DOP/ BUS BAY WORKS | H18: =+SUM(F18:G18) -> 0 | J18: =+ROUND(I18*H18,2) -> 0 | K18: =SUM(J18:J18) -> 0 | M18: =+ROUND(L18*H18,2) -> 0 | N18: =SUM(M18:M18) -> 0 | P18: A | Q18: =+ROUND((K18)*(1+SUMIF($Q$2:$Q$4,P18,$R$2:$R$4)),0) -> 0 | R18: =+ROUND((N18)*(1+SUMIF($Q$2:$Q$4,P18,$R$2:$R$4)),0) -> 0
A19: MiscExt | B19: =+B18 -> 4.2/7 | C19: 4.1 | D19: Vehicle DOP/Bus Bay Works | H19: =+SUM(F19:G19) -> 0 | J19: =+ROUND(I19*H19,2) -> 0 | K19: =SUM(J19:J19) -> 0 | M19: =+ROUND(L19*H19,2) -> 0 | N19: =SUM(M19:M19) -> 0 | P19: A | Q19: =+ROUND((K19)*(1+SUMIF($Q$2:$Q$4,P19,$R$2:$R$4)),0) -> 0 | R19: =+ROUND((N19)*(1+SUMIF($Q$2:$Q$4,P19,$R$2:$R$4)),0) -> 0
A20: MiscExt | B20: =+B17 -> 4.2/7 | C20: 4.1.1 | D20: To construct bus bays for pickup/drop off including substructure and superstructure, sheltered linkways, rain shelters and benches. | E20: Item | H20: =+SUM(F20:G20) -> 0 | J20: =+ROUND(I20*H20,2) -> 0 | K20: =SUM(J20:J20) -> 0 | M20: =+ROUND(L20*H20,2) -> 0 | N20: =SUM(M20:M20) -> 0 | P20: A | Q20: =+ROUND((K20)*(1+SUMIF($Q$2:$Q$4,P20,$R$2:$R$4)),0) -> 0 | R20: =+ROUND((N20)*(1+SUMIF($Q$2:$Q$4,P20,$R$2:$R$4)),0) -> 0
A21: Collection | B21: =+B20 -> 4.2/7 | D21: To Collection: | J21: =SUM(J7:J20) -> 0 | K21: =SUM(K7:K20) -> 0 | M21: =SUM(M7:M20) -> 0 | N21: =SUM(N7:N20) -> 0 | P21: A | Q21: =SUM(Q7:Q20) -> 0 | R21: =SUM(R7:R20) -> 0
A22: Struct | B22: 4.2/8 | H22: =+SUM(F22:G22) -> 0 | J22: =+ROUND(I22*H22,2) -> 0 | K22: =SUM(J22:J22) -> 0 | M22: =+ROUND(L22*H22,2) -> 0 | N22: =SUM(M22:M22) -> 0 | P22: A | Q22: =+ROUND((K22)*(1+SUMIF($Q$2:$Q$4,P22,$R$2:$R$4)),0) -> 0 | R22: =+ROUND((N22)*(1+SUMIF($Q$2:$Q$4,P22,$R$2:$R$4)),0) -> 0
A23: Struct | B23: 4.2/8 | C23: 5 | D23: CONCRETE WORKS | H23: =+SUM(F23:G23) -> 0 | J23: =+ROUND(I23*H23,2) -> 0 | K23: =SUM(J23:J23) -> 0 | M23: =+ROUND(L23*H23,2) -> 0 | N23: =SUM(M23:M23) -> 0 | P23: A | Q23: =+ROUND((K23)*(1+SUMIF($Q$2:$Q$4,P23,$R$2:$R$4)),0) -> 0 | R23: =+ROUND((N23)*(1+SUMIF($Q$2:$Q$4,P23,$R$2:$R$4)),0) -> 0
A24: Struct | B24: =+B23 -> 4.2/8 | C24: 5.1 | D24: Concrete Works | E24: Item | H24: =+SUM(F24:G24) -> 0 | J24: =+ROUND(I24*H24,2) -> 0 | K24: =SUM(J24:J24) -> 0 | M24: =+ROUND(L24*H24,2) -> 0 | N24: =SUM(M24:M24) -> 0 | P24: A | Q24: =+ROUND((K24)*(1+SUMIF($Q$2:$Q$4,P24,$R$2:$R$4)),0) -> 0 | R24: =+ROUND((N24)*(1+SUMIF($Q$2:$Q$4,P24,$R$2:$R$4)),0) -> 0
A25: Struct | B25: =+B24 -> 4.2/8 | C25: 5.1.1 | D25: To construct concrete works such as slabs, footpaths, pavement, structure for multi-purpose hall hard courts, football/games pitches, outdoor fitness areas with all necessary painting and finishes. | E25: Item | H25: =+SUM(F25:G25) -> 0 | J25: =+ROUND(I25*H25,2) -> 0 | K25: =SUM(J25:J25) -> 0 | M25: =+ROUND(L25*H25,2) -> 0 | N25: =SUM(M25:M25) -> 0 | P25: A | Q25: =+ROUND((K25)*(1+SUMIF($Q$2:$Q$4,P25,$R$2:$R$4)),0) -> 0 | R25: =+ROUND((N25)*(1+SUMIF($Q$2:$Q$4,P25,$R$2:$R$4)),0) -> 0
A26: SignOthers | B26: =+B25 -> 4.2/8 | C26: 6 | D26: SIGNAGE | H26: =+SUM(F26:G26) -> 0 | J26: =+ROUND(I26*H26,2) -> 0 | K26: =SUM(J26:J26) -> 0 | M26: =+ROUND(L26*H26,2) -> 0 | N26: =SUM(M26:M26) -> 0 | P26: A | Q26: =+ROUND((K26)*(1+SUMIF($Q$2:$Q$4,P26,$R$2:$R$4)),0) -> 0 | R26: =+ROUND((N26)*(1+SUMIF($Q$2:$Q$4,P26,$R$2:$R$4)),0) -> 0
A27: SignOthers | B27: =+B26 -> 4.2/8 | C27: 6.1 | D27: Signage | E27: Item | H27: =+SUM(F27:G27) -> 0 | J27: =+ROUND(I27*H27,2) -> 0 | K27: =SUM(J27:J27) -> 0 | M27: =+ROUND(L27*H27,2) -> 0 | N27: =SUM(M27:M27) -> 0 | P27: A | Q27: =+ROUND((K27)*(1+SUMIF($Q$2:$Q$4,P27,$R$2:$R$4)),0) -> 0 | R27: =+ROUND((N27)*(1+SUMIF($Q$2:$Q$4,P27,$R$2:$R$4)),0) -> 0
A28: SignOthers | B28: =+B27 -> 4.2/8 | C28: 6.1.1 | D28: To supply and install all directional signages/traffic sign, mandatory signages required for TOP and obtaining FEDA licence, signboards and safety | E28: Item | H28: =+SUM(F28:G28) -> 0 | J28: =+ROUND(I28*H28,2) -> 0 | K28: =SUM(J28:J28) -> 0 | M28: =+ROUND(L28*H28,2) -> 0 | N28: =SUM(M28:M28) -> 0 | P28: A | Q28: =+ROUND((K28)*(1+SUMIF($Q$2:$Q$4,P28,$R$2:$R$4)),0) -> 0 | R28: =+ROUND((N28)*(1+SUMIF($Q$2:$Q$4,P28,$R$2:$R$4)),0) -> 0
A29: Soft | B29: =+B28 -> 4.2/8 | C29: 7 | D29: GRADING AND TURFING WORKS | H29: =+SUM(F29:G29) -> 0 | J29: =+ROUND(I29*H29,2) -> 0 | K29: =SUM(J29:J29) -> 0 | M29: =+ROUND(L29*H29,2) -> 0 | N29: =SUM(M29:M29) -> 0 | P29: A | Q29: =+ROUND((K29)*(1+SUMIF($Q$2:$Q$4,P29,$R$2:$R$4)),0) -> 0 | R29: =+ROUND((N29)*(1+SUMIF($Q$2:$Q$4,P29,$R$2:$R$4)),0) -> 0
A30: Soft | B30: =+B29 -> 4.2/8 | C30: 7.1 | D30: Grading and Turfing Works | E30: Item | H30: =+SUM(F30:G30) -> 0 | J30: =+ROUND(I30*H30,2) -> 0 | K30: =SUM(J30:J30) -> 0 | M30: =+ROUND(L30*H30,2) -> 0 | N30: =SUM(M30:M30) -> 0 | P30: A | Q30: =+ROUND((K30)*(1+SUMIF($Q$2:$Q$4,P30,$R$2:$R$4)),0) -> 0 | R30: =+ROUND((N30)*(1+SUMIF($Q$2:$Q$4,P30,$R$2:$R$4)),0) -> 0
A31: Soft | B31: =+B28 -> 4.2/8 | C31: 7.1.1 | D31: To grade and close turf all unpaved areas within the Contract boundary complete with necessary drainage and sumps (where required) | E31: m2 | H31: =+SUM(F31:G31) -> 0 | J31: =+ROUND(I31*H31,2) -> 0 | K31: =SUM(J31:J31) -> 0 | M31: =+ROUND(L31*H31,2) -> 0 | N31: =SUM(M31:M31) -> 0 | P31: A | Q31: =+ROUND((K31)*(1+SUMIF($Q$2:$Q$4,P31,$R$2:$R$4)),0) -> 0 | R31: =+ROUND((N31)*(1+SUMIF($Q$2:$Q$4,P31,$R$2:$R$4)),0) -> 0
A32: Soft | B32: =+B31 -> 4.2/8 | C32: 7.1.2 | D32: To re-grade and re-turf and reinstate all unpaved areas outside the Contract boundary disturbed in the process of the works. | E32: m2 | H32: =+SUM(F32:G32) -> 0 | J32: =+ROUND(I32*H32,2) -> 0 | K32: =SUM(J32:J32) -> 0 | M32: =+ROUND(L32*H32,2) -> 0 | N32: =SUM(M32:M32) -> 0 | P32: A | Q32: =+ROUND((K32)*(1+SUMIF($Q$2:$Q$4,P32,$R$2:$R$4)),0) -> 0 | R32: =+ROUND((N32)*(1+SUMIF($Q$2:$Q$4,P32,$R$2:$R$4)),0) -> 0
A33: Drain | B33: =+B32 -> 4.2/8 | C33: 8 | D33: DRAINAGE | H33: =+SUM(F33:G33) -> 0 | J33: =+ROUND(I33*H33,2) -> 0 | K33: =SUM(J33:J33) -> 0 | M33: =+ROUND(L33*H33,2) -> 0 | N33: =SUM(M33:M33) -> 0 | P33: A | Q33: =+ROUND((K33)*(1+SUMIF($Q$2:$Q$4,P33,$R$2:$R$4)),0) -> 0 | R33: =+ROUND((N33)*(1+SUMIF($Q$2:$Q$4,P33,$R$2:$R$4)),0) -> 0
A34: Drain | B34: =+B33 -> 4.2/8 | C34: 8.1 | D34: Drainage | E34: Item | H34: =+SUM(F34:G34) -> 0 | J34: =+ROUND(I34*H34,2) -> 0 | K34: =SUM(J34:J34) -> 0 | M34: =+ROUND(L34*H34,2) -> 0 | N34: =SUM(M34:M34) -> 0 | P34: A | Q34: =+ROUND((K34)*(1+SUMIF($Q$2:$Q$4,P34,$R$2:$R$4)),0) -> 0 | R34: =+ROUND((N34)*(1+SUMIF($Q$2:$Q$4,P34,$R$2:$R$4)),0) -> 0
A35: Drain | B35: =+B32 -> 4.2/8 | C35: 8.1.1 | D35: To design and construct, including all necessary markings, associated drainage for the open field to be functional and fit for purpose. | E35: Item | H35: =+SUM(F35:G35) -> 0 | J35: =+ROUND(I35*H35,2) -> 0 | K35: =SUM(J35:J35) -> 0 | M35: =+ROUND(L35*H35,2) -> 0 | N35: =SUM(M35:M35) -> 0 | P35: A | Q35: =+ROUND((K35)*(1+SUMIF($Q$2:$Q$4,P35,$R$2:$R$4)),0) -> 0 | R35: =+ROUND((N35)*(1+SUMIF($Q$2:$Q$4,P35,$R$2:$R$4)),0) -> 0
A36: Drain | B36: =+B35 -> 4.2/8 | D36: Surface drain; 300mm wide | E36: m | H36: =+SUM(F36:G36) -> 0 | J36: =+ROUND(I36*H36,2) -> 0 | K36: =SUM(J36:J36) -> 0 | M36: =+ROUND(L36*H36,2) -> 0 | N36: =SUM(M36:M36) -> 0 | P36: A | Q36: =+ROUND((K36)*(1+SUMIF($Q$2:$Q$4,P36,$R$2:$R$4)),0) -> 0 | R36: =+ROUND((N36)*(1+SUMIF($Q$2:$Q$4,P36,$R$2:$R$4)),0) -> 0
A37: Drain | B37: =+B36 -> 4.2/8 | D37: Surface drain; 600mm wide | E37: m | H37: =+SUM(F37:G37) -> 0 | J37: =+ROUND(I37*H37,2) -> 0 | K37: =SUM(J37:J37) -> 0 | M37: =+ROUND(L37*H37,2) -> 0 | N37: =SUM(M37:M37) -> 0 | P37: A | Q37: =+ROUND((K37)*(1+SUMIF($Q$2:$Q$4,P37,$R$2:$R$4)),0) -> 0 | R37: =+ROUND((N37)*(1+SUMIF($Q$2:$Q$4,P37,$R$2:$R$4)),0) -> 0
A38: Drain | B38: =+B37 -> 4.2/8 | D38: Sump pit | E38: nr | H38: =+SUM(F38:G38) -> 0 | J38: =+ROUND(I38*H38,2) -> 0 | K38: =SUM(J38:J38) -> 0 | M38: =+ROUND(L38*H38,2) -> 0 | N38: =SUM(M38:M38) -> 0 | P38: A | Q38: =+ROUND((K38)*(1+SUMIF($Q$2:$Q$4,P38,$R$2:$R$4)),0) -> 0 | R38: =+ROUND((N38)*(1+SUMIF($Q$2:$Q$4,P38,$R$2:$R$4)),0) -> 0
A39: Drain | B39: =+B37 -> 4.2/8 | D39: Drain cover/grating | E39: m2 | H39: =+SUM(F39:G39) -> 0 | J39: =+ROUND(I39*H39,2) -> 0 | K39: =SUM(J39:J39) -> 0 | M39: =+ROUND(L39*H39,2) -> 0 | N39: =SUM(M39:M39) -> 0 | P39: A | Q39: =+ROUND((K39)*(1+SUMIF($Q$2:$Q$4,P39,$R$2:$R$4)),0) -> 0 | R39: =+ROUND((N39)*(1+SUMIF($Q$2:$Q$4,P39,$R$2:$R$4)),0) -> 0
A40: Drain | B40: =+B38 -> 4.2/8 | H40: =+SUM(F40:G40) -> 0 | J40: =+ROUND(I40*H40,2) -> 0 | K40: =SUM(J40:J40) -> 0 | M40: =+ROUND(L40*H40,2) -> 0 | N40: =SUM(M40:M40) -> 0 | P40: A | Q40: =+ROUND((K40)*(1+SUMIF($Q$2:$Q$4,P40,$R$2:$R$4)),0) -> 0 | R40: =+ROUND((N40)*(1+SUMIF($Q$2:$Q$4,P40,$R$2:$R$4)),0) -> 0
A41: Collection | B41: =+B40 -> 4.2/8 | D41: To Collection: | J41: =SUM(J23:J40) -> 0 | K41: =SUM(K23:K40) -> 0 | M41: =SUM(M23:M40) -> 0 | N41: =SUM(N23:N40) -> 0 | P41: A | Q41: =SUM(Q23:Q40) -> 0 | R41: =SUM(R23:R40) -> 0
A42: SportCourt | B42: =+B40 -> 4.2/8 | H42: =+SUM(F42:G42) -> 0 | J42: =+ROUND(I42*H42,2) -> 0 | K42: =SUM(J42:J42) -> 0 | M42: =+ROUND(L42*H42,2) -> 0 | N42: =SUM(M42:M42) -> 0 | P42: A | Q42: =+ROUND((K42)*(1+SUMIF($Q$2:$Q$4,P42,$R$2:$R$4)),0) -> 0 | R42: =+ROUND((N42)*(1+SUMIF($Q$2:$Q$4,P42,$R$2:$R$4)),0) -> 0
A43: SportCourt | B43: =+B41 -> 4.2/8 | C43: 9 | D43: COURTS | H43: =+SUM(F43:G43) -> 0 | J43: =+ROUND(I43*H43,2) -> 0 | K43: =SUM(J43:J43) -> 0 | M43: =+ROUND(L43*H43,2) -> 0 | N43: =SUM(M43:M43) -> 0 | P43: A | Q43: =+ROUND((K43)*(1+SUMIF($Q$2:$Q$4,P43,$R$2:$R$4)),0) -> 0 | R43: =+ROUND((N43)*(1+SUMIF($Q$2:$Q$4,P43,$R$2:$R$4)),0) -> 0
A44: SportCourt | B44: =+B43 -> 4.2/8 | C44: 9.1 | D44: Courts | E44: Item | H44: =+SUM(F44:G44) -> 0 | J44: =+ROUND(I44*H44,2) -> 0 | K44: =SUM(J44:J44) -> 0 | M44: =+ROUND(L44*H44,2) -> 0 | N44: =SUM(M44:M44) -> 0 | P44: A | Q44: =+ROUND((K44)*(1+SUMIF($Q$2:$Q$4,P44,$R$2:$R$4)),0) -> 0 | R44: =+ROUND((N44)*(1+SUMIF($Q$2:$Q$4,P44,$R$2:$R$4)),0) -> 0
A45: SportCourt | B45: 4.2/9 | C45: 9.1.1 | D45: Hard Court - for games | E45: m2 | H45: =+SUM(F45:G45) -> 0 | J45: =+ROUND(I45*H45,2) -> 0 | K45: =SUM(J45:J45) -> 0 | M45: =+ROUND(L45*H45,2) -> 0 | N45: =SUM(M45:M45) -> 0 | P45: A | Q45: =+ROUND((K45)*(1+SUMIF($Q$2:$Q$4,P45,$R$2:$R$4)),0) -> 0 | R45: =+ROUND((N45)*(1+SUMIF($Q$2:$Q$4,P45,$R$2:$R$4)),0) -> 0
A46: SportCourt | B46: =+B45 -> 4.2/9 | C46: 9.1.2 | D46: Game Court – for mini football pitch | E46: m2 | H46: =+SUM(F46:G46) -> 0 | J46: =+ROUND(I46*H46,2) -> 0 | K46: =SUM(J46:J46) -> 0 | M46: =+ROUND(L46*H46,2) -> 0 | N46: =SUM(M46:M46) -> 0 | P46: A | Q46: =+ROUND((K46)*(1+SUMIF($Q$2:$Q$4,P46,$R$2:$R$4)),0) -> 0 | R46: =+ROUND((N46)*(1+SUMIF($Q$2:$Q$4,P46,$R$2:$R$4)),0) -> 0
A47: Gym | B47: =+B46 -> 4.2/9 | C47: 9.1.3 | D47: Fitness Corner including equipment | E47: LS | H47: =+SUM(F47:G47) -> 0 | J47: =+ROUND(I47*H47,2) -> 0 | K47: =SUM(J47:J47) -> 0 | M47: =+ROUND(L47*H47,2) -> 0 | N47: =SUM(M47:M47) -> 0 | P47: A | Q47: =+ROUND((K47)*(1+SUMIF($Q$2:$Q$4,P47,$R$2:$R$4)),0) -> 0 | R47: =+ROUND((N47)*(1+SUMIF($Q$2:$Q$4,P47,$R$2:$R$4)),0) -> 0
A48: BoundaryW | B48: =+B47 -> 4.2/9 | C48: 10 | D48: SECURITY FENCE | H48: =+SUM(F48:G48) -> 0 | J48: =+ROUND(I48*H48,2) -> 0 | K48: =SUM(J48:J48) -> 0 | M48: =+ROUND(L48*H48,2) -> 0 | N48: =SUM(M48:M48) -> 0 | P48: A | Q48: =+ROUND((K48)*(1+SUMIF($Q$2:$Q$4,P48,$R$2:$R$4)),0) -> 0 | R48: =+ROUND((N48)*(1+SUMIF($Q$2:$Q$4,P48,$R$2:$R$4)),0) -> 0
A49: BoundaryW | B49: =+B48 -> 4.2/9 | C49: 10.1 | D49: Security Fence | H49: =+SUM(F49:G49) -> 0 | J49: =+ROUND(I49*H49,2) -> 0 | K49: =SUM(J49:J49) -> 0 | M49: =+ROUND(L49*H49,2) -> 0 | N49: =SUM(M49:M49) -> 0 | P49: A | Q49: =+ROUND((K49)*(1+SUMIF($Q$2:$Q$4,P49,$R$2:$R$4)),0) -> 0 | R49: =+ROUND((N49)*(1+SUMIF($Q$2:$Q$4,P49,$R$2:$R$4)),0) -> 0
A50: BoundaryW | B50: =+B49 -> 4.2/9 | C50: 10.1.1 | D50: To carry of design, construct, complete with testing and commissioning of (where applicable) perimeter security dormitory fencing and gates including all associated civil works, using welded mesh fence with anti-climb features, with a minimum height of 2.5 metres including PE endorsement. | H50: =+SUM(F50:G50) -> 0 | J50: =+ROUND(I50*H50,2) -> 0 | K50: =SUM(J50:J50) -> 0 | M50: =+ROUND(L50*H50,2) -> 0 | N50: =SUM(M50:M50) -> 0 | P50: A | Q50: =+ROUND((K50)*(1+SUMIF($Q$2:$Q$4,P50,$R$2:$R$4)),0) -> 0 | R50: =+ROUND((N50)*(1+SUMIF($Q$2:$Q$4,P50,$R$2:$R$4)),0) -> 0
A51: BoundaryW | B51: =+B50 -> 4.2/9 | D51: Perimeter welded mesh fence; min 2500mm H | E51: m | H51: =+SUM(F51:G51) -> 0 | J51: =+ROUND(I51*H51,2) -> 0 | K51: =SUM(J51:J51) -> 0 | M51: =+ROUND(L51*H51,2) -> 0 | N51: =SUM(M51:M51) -> 0 | P51: A | Q51: =+ROUND((K51)*(1+SUMIF($Q$2:$Q$4,P51,$R$2:$R$4)),0) -> 0 | R51: =+ROUND((N51)*(1+SUMIF($Q$2:$Q$4,P51,$R$2:$R$4)),0) -> 0
A52: BoundaryW | B52: =+B51 -> 4.2/9 | D52: Main entrance gate (motorised) | E52: nr | H52: =+SUM(F52:G52) -> 0 | J52: =+ROUND(I52*H52,2) -> 0 | K52: =SUM(J52:J52) -> 0 | M52: =+ROUND(L52*H52,2) -> 0 | N52: =SUM(M52:M52) -> 0 | P52: A | Q52: =+ROUND((K52)*(1+SUMIF($Q$2:$Q$4,P52,$R$2:$R$4)),0) -> 0 | R52: =+ROUND((N52)*(1+SUMIF($Q$2:$Q$4,P52,$R$2:$R$4)),0) -> 0
A53: BoundaryW | B53: =+B52 -> 4.2/9 | D53: Pedestrian gate | E53: nr | H53: =+SUM(F53:G53) -> 0 | J53: =+ROUND(I53*H53,2) -> 0 | K53: =SUM(J53:J53) -> 0 | M53: =+ROUND(L53*H53,2) -> 0 | N53: =SUM(M53:M53) -> 0 | P53: A | Q53: =+ROUND((K53)*(1+SUMIF($Q$2:$Q$4,P53,$R$2:$R$4)),0) -> 0 | R53: =+ROUND((N53)*(1+SUMIF($Q$2:$Q$4,P53,$R$2:$R$4)),0) -> 0
A54: BoundaryW | B54: =+B53 -> 4.2/9 | D54: Vehicle barrier / boom gate | E54: nr | H54: =+SUM(F54:G54) -> 0 | J54: =+ROUND(I54*H54,2) -> 0 | K54: =SUM(J54:J54) -> 0 | M54: =+ROUND(L54*H54,2) -> 0 | N54: =SUM(M54:M54) -> 0 | P54: A | Q54: =+ROUND((K54)*(1+SUMIF($Q$2:$Q$4,P54,$R$2:$R$4)),0) -> 0 | R54: =+ROUND((N54)*(1+SUMIF($Q$2:$Q$4,P54,$R$2:$R$4)),0) -> 0
A55: BoundaryW | B55: =+B54 -> 4.2/9 | H55: =+SUM(F55:G55) -> 0 | J55: =+ROUND(I55*H55,2) -> 0 | K55: =SUM(J55:J55) -> 0 | M55: =+ROUND(L55*H55,2) -> 0 | N55: =SUM(M55:M55) -> 0 | P55: A | Q55: =+ROUND((K55)*(1+SUMIF($Q$2:$Q$4,P55,$R$2:$R$4)),0) -> 0 | R55: =+ROUND((N55)*(1+SUMIF($Q$2:$Q$4,P55,$R$2:$R$4)),0) -> 0
A56: Collection | B56: =+B55 -> 4.2/9 | D56: To Collection: | J56: =SUM(J43:J55) -> 0 | K56: =SUM(K43:K55) -> 0 | M56: =SUM(M43:M55) -> 0 | N56: =SUM(N43:N55) -> 0 | P56: A | Q56: =SUM(Q43:Q55) -> 0 | R56: =SUM(R43:R55) -> 0
A57: Collection | B57: 4.2/10
A58: Collection | B58: =+B57 -> 4.2/10 | D58: Sec 4.2/1 | K58: 0 | N58: 0 | Q58: 0 | R58: 0
A59: Collection | B59: =+B58 -> 4.2/10 | D59: Sec 4.2/2 | K59: 0 | N59: 0 | Q59: 0 | R59: 0
A60: Collection | B60: =+B59 -> 4.2/10 | D60: Sec 4.2/3 | K60: 0 | N60: 0 | Q60: 0 | R60: 0
A61: Collection | B61: =+B60 -> 4.2/10 | D61: Sec 4.2/4 | K61: 0 | N61: 0 | Q61: 0 | R61: 0
A62: Collection | B62: =+B61 -> 4.2/10 | D62: Sec 4.2/5 | K62: 0 | N62: 0 | Q62: 0 | R62: 0
A63: Collection | B63: =+B62 -> 4.2/10 | D63: Sec 4.2/6 | K63: 0 | N63: 0 | Q63: 0 | R63: 0
A64: Collection | B64: =+B63 -> 4.2/10 | D64: Sec 4.2/7 | K64: =K21 -> 0 | N64: =N21 -> 0 | Q64: =Q21 -> 0 | R64: =R21 -> 0
A65: Collection | B65: =+B64 -> 4.2/10 | D65: Sec 4.2/8 | K65: =K41 -> 0 | N65: =N41 -> 0 | Q65: =Q41 -> 0 | R65: =R41 -> 0
A66: Collection | B66: =+B65 -> 4.2/10 | D66: Sec 4.2/9 | K66: =K56 -> 0 | N66: =N56 -> 0 | Q66: =Q56 -> 0 | R66: =R56 -> 0
A67: Collection | B67: =+B59 -> 4.2/10
A68: Collection | D68: TO FINAL SUMMARY (excluding GST) | K68: =SUM(K57:K67) -> 0 | L68: =+K68=SUM(J7:J57)/2 -> TRUE | N68: =SUM(N57:N67) -> 0 | O68: =+N68=SUM(M7:M57)/2 -> TRUE | Q68: =SUM(Q57:Q67) -> 0 | R68: =SUM(R57:R67) -> 0
K73: =+K68=K235 -> TRUE | N73: =+N68=N235 -> TRUE | Q73: =+Q68=Q235 -> TRUE | R73: =+R68=R235 -> TRUE
A74: CODE SUMMARY | D74: Trade Code Breakdown — Sec 4
A75: CODE | B75: DESCRIPTION | K75: Phase A Amount (S$) | N75: Phase B Amount (S$) | P75: MARKUP CODE | Q75: Phase A SUBMISSION AMOUNT (S$) | R75: Phase B SUBMISSION AMOUNT (S$)
A76: PC | B76: PC & Provional Sum | K76: =SUMIF($A$7:$A$56,A76,$K$7:$K$56) -> 0 | N76: =SUMIF($A$7:$A$56,A76,$N$7:$N$56) -> 0 | P76: A | Q76: =+ROUND((K76)*(1+SUMIF($Q$2:$Q$4,P76,$R$2:$R$4)),0) -> 0 | R76: =+ROUND((N76)*(1+SUMIF($Q$2:$Q$4,P76,$R$2:$R$4)),0) -> 0
A77: Instru | B77: Instrumentation | K77: =SUMIF($A$7:$A$56,A77,$K$7:$K$56) -> 0 | N77: =SUMIF($A$7:$A$56,A77,$N$7:$N$56) -> 0 | P77: A | Q77: =+ROUND((K77)*(1+SUMIF($Q$2:$Q$4,P77,$R$2:$R$4)),0) -> 0 | R77: =+ROUND((N77)*(1+SUMIF($Q$2:$Q$4,P77,$R$2:$R$4)),0) -> 0
A78: Demo | B78: Demolition Works | K78: =SUMIF($A$7:$A$56,A78,$K$7:$K$56) -> 0 | N78: =SUMIF($A$7:$A$56,A78,$N$7:$N$56) -> 0 | P78: A | Q78: =+ROUND((K78)*(1+SUMIF($Q$2:$Q$4,P78,$R$2:$R$4)),0) -> 0 | R78: =+ROUND((N78)*(1+SUMIF($Q$2:$Q$4,P78,$R$2:$R$4)),0) -> 0
A79: Earth | B79: Earth Works | K79: =SUMIF($A$7:$A$56,A79,$K$7:$K$56) -> 0 | N79: =SUMIF($A$7:$A$56,A79,$N$7:$N$56) -> 0 | P79: A | Q79: =+ROUND((K79)*(1+SUMIF($Q$2:$Q$4,P79,$R$2:$R$4)),0) -> 0 | R79: =+ROUND((N79)*(1+SUMIF($Q$2:$Q$4,P79,$R$2:$R$4)),0) -> 0
A80: Pile | B80: Piling Works | K80: =SUMIF($A$7:$A$56,A80,$K$7:$K$56) -> 0 | N80: =SUMIF($A$7:$A$56,A80,$N$7:$N$56) -> 0 | P80: A | Q80: =+ROUND((K80)*(1+SUMIF($Q$2:$Q$4,P80,$R$2:$R$4)),0) -> 0 | R80: =+ROUND((N80)*(1+SUMIF($Q$2:$Q$4,P80,$R$2:$R$4)),0) -> 0
A81: CBP | B81: Contiguous bored pile, Secant pile | K81: =SUMIF($A$7:$A$56,A81,$K$7:$K$56) -> 0 | N81: =SUMIF($A$7:$A$56,A81,$N$7:$N$56) -> 0 | P81: A | Q81: =+ROUND((K81)*(1+SUMIF($Q$2:$Q$4,P81,$R$2:$R$4)),0) -> 0 | R81: =+ROUND((N81)*(1+SUMIF($Q$2:$Q$4,P81,$R$2:$R$4)),0) -> 0
A82: BakauPile | B82: Bakau pile | K82: =SUMIF($A$7:$A$56,A82,$K$7:$K$56) -> 0 | N82: =SUMIF($A$7:$A$56,A82,$N$7:$N$56) -> 0 | P82: A | Q82: =+ROUND((K82)*(1+SUMIF($Q$2:$Q$4,P82,$R$2:$R$4)),0) -> 0 | R82: =+ROUND((N82)*(1+SUMIF($Q$2:$Q$4,P82,$R$2:$R$4)),0) -> 0
A83: SI | B83: Soil Improvement Works | K83: =SUMIF($A$7:$A$56,A83,$K$7:$K$56) -> 0 | N83: =SUMIF($A$7:$A$56,A83,$N$7:$N$56) -> 0 | P83: A | Q83: =+ROUND((K83)*(1+SUMIF($Q$2:$Q$4,P83,$R$2:$R$4)),0) -> 0 | R83: =+ROUND((N83)*(1+SUMIF($Q$2:$Q$4,P83,$R$2:$R$4)),0) -> 0
A84: Dwall | B84: Diaphragm wall | K84: =SUMIF($A$7:$A$56,A84,$K$7:$K$56) -> 0 | N84: =SUMIF($A$7:$A$56,A84,$N$7:$N$56) -> 0 | P84: A | Q84: =+ROUND((K84)*(1+SUMIF($Q$2:$Q$4,P84,$R$2:$R$4)),0) -> 0 | R84: =+ROUND((N84)*(1+SUMIF($Q$2:$Q$4,P84,$R$2:$R$4)),0) -> 0
A85: PileOther | B85: Others piling system | K85: =SUMIF($A$7:$A$56,A85,$K$7:$K$56) -> 0 | N85: =SUMIF($A$7:$A$56,A85,$N$7:$N$56) -> 0 | P85: A | Q85: =+ROUND((K85)*(1+SUMIF($Q$2:$Q$4,P85,$R$2:$R$4)),0) -> 0 | R85: =+ROUND((N85)*(1+SUMIF($Q$2:$Q$4,P85,$R$2:$R$4)),0) -> 0
A86: Temp | B86: Temporary Works | K86: =SUMIF($A$7:$A$56,A86,$K$7:$K$56) -> 0 | N86: =SUMIF($A$7:$A$56,A86,$N$7:$N$56) -> 0 | P86: A | Q86: =+ROUND((K86)*(1+SUMIF($Q$2:$Q$4,P86,$R$2:$R$4)),0) -> 0 | R86: =+ROUND((N86)*(1+SUMIF($Q$2:$Q$4,P86,$R$2:$R$4)),0) -> 0
A87: Sheetpile | B87: Sheet pile / Soldier Pile with lagging | K87: =SUMIF($A$7:$A$56,A87,$K$7:$K$56) -> 0 | N87: =SUMIF($A$7:$A$56,A87,$N$7:$N$56) -> 0 | P87: A | Q87: =+ROUND((K87)*(1+SUMIF($Q$2:$Q$4,P87,$R$2:$R$4)),0) -> 0 | R87: =+ROUND((N87)*(1+SUMIF($Q$2:$Q$4,P87,$R$2:$R$4)),0) -> 0
... A234: AC | B234: Accreditated checkers | K234: =SUMIF($A$7:$A$56,A234,$K$7:$K$56) -> 0 | N234: =SUMIF($A$7:$A$56,A234,$N$7:$N$56) -> 0 | P234: A | Q234: =+ROUND((K234)*(1+SUMIF($Q$2:$Q$4,P234,$R$2:$R$4)),0) -> 0 | R234: =+ROUND((N234)*(1+SUMIF($Q$2:$Q$4,P234,$R$2:$R$4)),0) -> 0
A235: TOTAL | B235: GRAND TOTAL — ALL CODES | K235: =SUM(K76:K234) -> 0 | N235: =SUM(N76:N234) -> 0 | Q235: =SUM(Q76:Q234) -> 0 | R235: =SUM(R76:R234) -> 0

Sheet Sec 5 - M&E Works
A1: Tender No: CE/25/T5/P/896 | L1: Generally | Q1: Markup
Q2: A | R2: 0.2
A3: SECTION 5 | Q3: B | R3: 0.1
A4: DESIGN AND BUILD OF COASTAL DORMITORY EXPANSION FOR CHANGI EAST DEVELOPMENT | Q4: C
A6: CODE | B6: PAGE | C6: ITEM | D6: DESCRIPTION | E6: UNIT | F6: Material (S$) | G6: Labour (S$) | H6: U/RATE (S$) | I6: Phase A Qty | J6: Phase A Sub-Total | K6: Phase A Amount (S$) | L6: Phase B Qty | M6: Phase B Sub-Total | N6: Phase B Amount (S$) | O6: REMARKS | P6: MARKUP CODE | Q6: Phase A SUBMISSION AMOUNT (S$) | R6: Phase B SUBMISSION AMOUNT (S$) | S6: PC rate
A7: SP | B7: SECT5.2/7 | D7: SECTION NO 5.2 - RESIDENTIAL BLOCKS | H7: =+SUM(F7:G7) -> 0 | J7: =+ROUND(I7*H7,2) -> 0 | K7: =J7 -> 0 | M7: =+ROUND(L7*H7,2) -> 0 | N7: =M7 -> 0 | P7: A | Q7: =+ROUND((K7)*(1+SUMIF($Q$2:$Q$4,P7,$R$2:$R$4)),0) -> 0 | R7: =+ROUND((N7)*(1+SUMIF($Q$2:$Q$4,P7,$R$2:$R$4)),0) -> 0
A8: SP | B8: SECT5.2/7 | C8: 1 | D8: Plumbing, Sanitary and Gas | H8: =+SUM(F8:G8) -> 0 | J8: =+ROUND(I8*H8,2) -> 0 | K8: =J8 -> 0 | M8: =+ROUND(L8*H8,2) -> 0 | N8: =M8 -> 0 | P8: A | Q8: =+ROUND((K8)*(1+SUMIF($Q$2:$Q$4,P8,$R$2:$R$4)),0) -> 0 | R8: =+ROUND((N8)*(1+SUMIF($Q$2:$Q$4,P8,$R$2:$R$4)),0) -> 0
A9: SP | B9: =+B8 -> SECT5.2/7 | C9: 1.1 | D9: Sanitary System | H9: =+SUM(F9:G9) -> 0 | J9: =+ROUND(I9*H9,2) -> 0 | K9: =J9 -> 0 | M9: =+ROUND(L9*H9,2) -> 0 | N9: =M9 -> 0 | P9: A | Q9: =+ROUND((K9)*(1+SUMIF($Q$2:$Q$4,P9,$R$2:$R$4)),0) -> 0 | R9: =+ROUND((N9)*(1+SUMIF($Q$2:$Q$4,P9,$R$2:$R$4)),0) -> 0
A10: SP | B10: =+B9 -> SECT5.2/7 | C10: 1.1.1 | D10: Above ground sanitary pipes including vent cowl, floor trap, floor waste and all necessary accessories | E10: Item | H10: =+SUM(F10:G10) -> 0 | J10: =+ROUND(I10*H10,2) -> 0 | K10: =J10 -> 0 | M10: =+ROUND(L10*H10,2) -> 0 | N10: =M10 -> 0 | P10: A | Q10: =+ROUND((K10)*(1+SUMIF($Q$2:$Q$4,P10,$R$2:$R$4)),0) -> 0 | R10: =+ROUND((N10)*(1+SUMIF($Q$2:$Q$4,P10,$R$2:$R$4)),0) -> 0
A11: SP | B11: =+B10 -> SECT5.2/7 | C11: 1.1.2 | D11: Take delivery and installation of plumbing and sanitary fixtures | E11: Item | H11: =+SUM(F11:G11) -> 0 | J11: =+ROUND(I11*H11,2) -> 0 | K11: =J11 -> 0 | M11: =+ROUND(L11*H11,2) -> 0 | N11: =M11 -> 0 | P11: A | Q11: =+ROUND((K11)*(1+SUMIF($Q$2:$Q$4,P11,$R$2:$R$4)),0) -> 0 | R11: =+ROUND((N11)*(1+SUMIF($Q$2:$Q$4,P11,$R$2:$R$4)),0) -> 0
A12: SP | B12: =+B11 -> SECT5.2/7 | C12: 1.2 | D12: Plumbing System | H12: =+SUM(F12:G12) -> 0 | J12: =+ROUND(I12*H12,2) -> 0 | K12: =J12 -> 0 | M12: =+ROUND(L12*H12,2) -> 0 | N12: =M12 -> 0 | P12: A | Q12: =+ROUND((K12)*(1+SUMIF($Q$2:$Q$4,P12,$R$2:$R$4)),0) -> 0 | R12: =+ROUND((N12)*(1+SUMIF($Q$2:$Q$4,P12,$R$2:$R$4)),0) -> 0
A13: SP | B13: =+B12 -> SECT5.2/7 | C13: 1.2.1 | D13: Above ground domestic cold water pipes including sub water meter, valves, bib taps and all necessary accessories | E13: Item | H13: =+SUM(F13:G13) -> 0 | J13: =+ROUND(I13*H13,2) -> 0 | K13: =J13 -> 0 | M13: =+ROUND(L13*H13,2) -> 0 | N13: =M13 -> 0 | P13: A | Q13: =+ROUND((K13)*(1+SUMIF($Q$2:$Q$4,P13,$R$2:$R$4)),0) -> 0 | R13: =+ROUND((N13)*(1+SUMIF($Q$2:$Q$4,P13,$R$2:$R$4)),0) -> 0
A14: SP | B14: =+B13 -> SECT5.2/7 | C14: 1.3 | D14: Gas System | H14: =+SUM(F14:G14) -> 0 | J14: =+ROUND(I14*H14,2) -> 0 | K14: =J14 -> 0 | M14: =+ROUND(L14*H14,2) -> 0 | N14: =M14 -> 0 | P14: A | Q14: =+ROUND((K14)*(1+SUMIF($Q$2:$Q$4,P14,$R$2:$R$4)),0) -> 0 | R14: =+ROUND((N14)*(1+SUMIF($Q$2:$Q$4,P14,$R$2:$R$4)),0) -> 0
A15: SP | B15: SECT5.2/7 | C15: 1.3.1 | D15: Gas pipes including valves, gas meter and all necessaary accessories | E15: Item | H15: =+SUM(F15:G15) -> 0 | J15: =+ROUND(I15*H15,2) -> 0 | K15: =J15 -> 0 | M15: =+ROUND(L15*H15,2) -> 0 | N15: =M15 -> 0 | P15: A | Q15: =+ROUND((K15)*(1+SUMIF($Q$2:$Q$4,P15,$R$2:$R$4)),0) -> 0 | R15: =+ROUND((N15)*(1+SUMIF($Q$2:$Q$4,P15,$R$2:$R$4)),0) -> 0
A16: SP | B16: SECT5.2/7 | C16: 1.3.2 | D16: Gas detection system | E16: Item | H16: =+SUM(F16:G16) -> 0 | J16: =+ROUND(I16*H16,2) -> 0 | K16: =J16 -> 0 | M16: =+ROUND(L16*H16,2) -> 0 | N16: =M16 -> 0 | P16: A | Q16: =+ROUND((K16)*(1+SUMIF($Q$2:$Q$4,P16,$R$2:$R$4)),0) -> 0 | R16: =+ROUND((N16)*(1+SUMIF($Q$2:$Q$4,P16,$R$2:$R$4)),0) -> 0
A17: SP | B17: SECT5.2/7 | C17: 1.4 | D17: Others (Please specify) | H17: =+SUM(F17:G17) -> 0 | J17: =+ROUND(I17*H17,2) -> 0 | K17: =J17 -> 0 | M17: =+ROUND(L17*H17,2) -> 0 | N17: =M17 -> 0 | P17: A | Q17: =+ROUND((K17)*(1+SUMIF($Q$2:$Q$4,P17,$R$2:$R$4)),0) -> 0 | R17: =+ROUND((N17)*(1+SUMIF($Q$2:$Q$4,P17,$R$2:$R$4)),0) -> 0
A18: SP | B18: SECT5.2/7 | C18: i) | D18: ____________________________________ | E18: Item | H18: =+SUM(F18:G18) -> 0 | J18: =+ROUND(I18*H18,2) -> 0 | K18: =J18 -> 0 | M18: =+ROUND(L18*H18,2) -> 0 | N18: =M18 -> 0 | P18: A | Q18: =+ROUND((K18)*(1+SUMIF($Q$2:$Q$4,P18,$R$2:$R$4)),0) -> 0 | R18: =+ROUND((N18)*(1+SUMIF($Q$2:$Q$4,P18,$R$2:$R$4)),0) -> 0
A19: SP | B19: SECT5.2/7 | C19: ii) | D19: ____________________________________ | E19: Item | H19: =+SUM(F19:G19) -> 0 | J19: =+ROUND(I19*H19,2) -> 0 | K19: =J19 -> 0 | M19: =+ROUND(L19*H19,2) -> 0 | N19: =M19 -> 0 | P19: A | Q19: =+ROUND((K19)*(1+SUMIF($Q$2:$Q$4,P19,$R$2:$R$4)),0) -> 0 | R19: =+ROUND((N19)*(1+SUMIF($Q$2:$Q$4,P19,$R$2:$R$4)),0) -> 0
A20: SP | B20: SECT5.2/7 | C20: iii) | D20: ____________________________________ | E20: Item | H20: =+SUM(F20:G20) -> 0 | J20: =+ROUND(I20*H20,2) -> 0 | K20: =J20 -> 0 | M20: =+ROUND(L20*H20,2) -> 0 | N20: =M20 -> 0 | P20: A | Q20: =+ROUND((K20)*(1+SUMIF($Q$2:$Q$4,P20,$R$2:$R$4)),0) -> 0 | R20: =+ROUND((N20)*(1+SUMIF($Q$2:$Q$4,P20,$R$2:$R$4)),0) -> 0
A21: Collection | B21: SECT5.2/7 | D21: To Collection (S$) | J21: =SUM(J8:J20) -> 0 | K21: =SUM(K8:K20) -> 0 | M21: =SUM(M8:M20) -> 0 | N21: =SUM(N8:N20) -> 0 | Q21: =SUM(Q8:Q20) -> 0 | R21: =SUM(R8:R20) -> 0
A22: ACMV | B22: SECT5.2/8 | C22: 2 | D22: Air-Conditioning and Mechanical Ventilation | H22: =+SUM(F22:G22) -> 0 | J22: =+ROUND(I22*H22,2) -> 0 | K22: =J22 -> 0 | M22: =+ROUND(L22*H22,2) -> 0 | N22: =M22 -> 0 | P22: A | Q22: =+ROUND((K22)*(1+SUMIF($Q$2:$Q$4,P22,$R$2:$R$4)),0) -> 0 | R22: =+ROUND((N22)*(1+SUMIF($Q$2:$Q$4,P22,$R$2:$R$4)),0) -> 0
A23: ACMV | B23: SECT5.2/8 | C23: 2.1 | D23: Exhaust Fan | E23: Item | H23: =+SUM(F23:G23) -> 0 | J23: =+ROUND(I23*H23,2) -> 0 | K23: =J23 -> 0 | M23: =+ROUND(L23*H23,2) -> 0 | N23: =M23 -> 0 | P23: A | Q23: =+ROUND((K23)*(1+SUMIF($Q$2:$Q$4,P23,$R$2:$R$4)),0) -> 0 | R23: =+ROUND((N23)*(1+SUMIF($Q$2:$Q$4,P23,$R$2:$R$4)),0) -> 0
A24: ACMV | B24: SECT5.2/8 | C24: 2.2 | D24: Others (Please specify) | H24: =+SUM(F24:G24) -> 0 | J24: =+ROUND(I24*H24,2) -> 0 | K24: =J24 -> 0 | M24: =+ROUND(L24*H24,2) -> 0 | N24: =M24 -> 0 | P24: A | Q24: =+ROUND((K24)*(1+SUMIF($Q$2:$Q$4,P24,$R$2:$R$4)),0) -> 0 | R24: =+ROUND((N24)*(1+SUMIF($Q$2:$Q$4,P24,$R$2:$R$4)),0) -> 0
A25: ACMV | B25: SECT5.2/8 | C25: i) | D25: ____________________________________ | E25: Item | H25: =+SUM(F25:G25) -> 0 | J25: =+ROUND(I25*H25,2) -> 0 | K25: =J25 -> 0 | M25: =+ROUND(L25*H25,2) -> 0 | N25: =M25 -> 0 | P25: A | Q25: =+ROUND((K25)*(1+SUMIF($Q$2:$Q$4,P25,$R$2:$R$4)),0) -> 0 | R25: =+ROUND((N25)*(1+SUMIF($Q$2:$Q$4,P25,$R$2:$R$4)),0) -> 0
A26: ACMV | B26: SECT5.2/8 | C26: ii) | D26: ____________________________________ | E26: Item | H26: =+SUM(F26:G26) -> 0 | J26: =+ROUND(I26*H26,2) -> 0 | K26: =J26 -> 0 | M26: =+ROUND(L26*H26,2) -> 0 | N26: =M26 -> 0 | P26: A | Q26: =+ROUND((K26)*(1+SUMIF($Q$2:$Q$4,P26,$R$2:$R$4)),0) -> 0 | R26: =+ROUND((N26)*(1+SUMIF($Q$2:$Q$4,P26,$R$2:$R$4)),0) -> 0
A27: ACMV | B27: SECT5.2/8 | C27: iii) | D27: ____________________________________ | E27: Item | H27: =+SUM(F27:G27) -> 0 | J27: =+ROUND(I27*H27,2) -> 0 | K27: =J27 -> 0 | M27: =+ROUND(L27*H27,2) -> 0 | N27: =M27 -> 0 | P27: A | Q27: =+ROUND((K27)*(1+SUMIF($Q$2:$Q$4,P27,$R$2:$R$4)),0) -> 0 | R27: =+ROUND((N27)*(1+SUMIF($Q$2:$Q$4,P27,$R$2:$R$4)),0) -> 0
A28: Collection | B28: SECT5.2/8 | D28: To Collection (S$) | J28: =SUM(J22:J27) -> 0 | K28: =SUM(K22:K27) -> 0 | M28: =SUM(M22:M27) -> 0 | N28: =SUM(N22:N27) -> 0 | Q28: =SUM(Q22:Q27) -> 0 | R28: =SUM(R22:R27) -> 0
A29: Elect | B29: SECT5.2/9 | C29: 3 | D29: Electrical and ELV | H29: =+SUM(F29:G29) -> 0 | J29: =+ROUND(I29*H29,2) -> 0 | K29: =J29 -> 0 | M29: =+ROUND(L29*H29,2) -> 0 | N29: =M29 -> 0 | P29: A | Q29: =+ROUND((K29)*(1+SUMIF($Q$2:$Q$4,P29,$R$2:$R$4)),0) -> 0 | R29: =+ROUND((N29)*(1+SUMIF($Q$2:$Q$4,P29,$R$2:$R$4)),0) -> 0
A30: Elect | B30: SECT5.2/9 | C30: 3.1 | D30: Electrical System | H30: =+SUM(F30:G30) -> 0 | J30: =+ROUND(I30*H30,2) -> 0 | K30: =J30 -> 0 | M30: =+ROUND(L30*H30,2) -> 0 | N30: =M30 -> 0 | P30: A | Q30: =+ROUND((K30)*(1+SUMIF($Q$2:$Q$4,P30,$R$2:$R$4)),0) -> 0 | R30: =+ROUND((N30)*(1+SUMIF($Q$2:$Q$4,P30,$R$2:$R$4)),0) -> 0
A31: Elect | B31: SECT5.2/9 | C31: 3.1.1 | D31: Electrical Panel | H31: =+SUM(F31:G31) -> 0 | J31: =+ROUND(I31*H31,2) -> 0 | K31: =J31 -> 0 | M31: =+ROUND(L31*H31,2) -> 0 | N31: =M31 -> 0 | P31: A | Q31: =+ROUND((K31)*(1+SUMIF($Q$2:$Q$4,P31,$R$2:$R$4)),0) -> 0 | R31: =+ROUND((N31)*(1+SUMIF($Q$2:$Q$4,P31,$R$2:$R$4)),0) -> 0
A32: Elect | B32: SECT5.2/9 | C32: 3.1.1.1 | D32: Sub-Switchboard and distribution board | E32: Item | H32: =+SUM(F32:G32) -> 0 | J32: =+ROUND(I32*H32,2) -> 0 | K32: =J32 -> 0 | M32: =+ROUND(L32*H32,2) -> 0 | N32: =M32 -> 0 | P32: A | Q32: =+ROUND((K32)*(1+SUMIF($Q$2:$Q$4,P32,$R$2:$R$4)),0) -> 0 | R32: =+ROUND((N32)*(1+SUMIF($Q$2:$Q$4,P32,$R$2:$R$4)),0) -> 0
A33: Elect | B33: SECT5.2/9 | C33: 3.1.2 | D33: Power | H33: =+SUM(F33:G33) -> 0 | J33: =+ROUND(I33*H33,2) -> 0 | K33: =J33 -> 0 | M33: =+ROUND(L33*H33,2) -> 0 | N33: =M33 -> 0 | P33: A | Q33: =+ROUND((K33)*(1+SUMIF($Q$2:$Q$4,P33,$R$2:$R$4)),0) -> 0 | R33: =+ROUND((N33)*(1+SUMIF($Q$2:$Q$4,P33,$R$2:$R$4)),0) -> 0
A34: Elect | B34: SECT5.2/9 | C34: 3.1.2.1 | D34: SSO | E34: Item | H34: =+SUM(F34:G34) -> 0 | J34: =+ROUND(I34*H34,2) -> 0 | K34: =J34 -> 0 | M34: =+ROUND(L34*H34,2) -> 0 | N34: =M34 -> 0 | P34: A | Q34: =+ROUND((K34)*(1+SUMIF($Q$2:$Q$4,P34,$R$2:$R$4)),0) -> 0 | R34: =+ROUND((N34)*(1+SUMIF($Q$2:$Q$4,P34,$R$2:$R$4)),0) -> 0
A35: Elect | B35: SECT5.2/9 | C35: 3.1.2.2 | D35: Isolators | E35: Item | H35: =+SUM(F35:G35) -> 0 | J35: =+ROUND(I35*H35,2) -> 0 | K35: =J35 -> 0 | M35: =+ROUND(L35*H35,2) -> 0 | N35: =M35 -> 0 | P35: A | Q35: =+ROUND((K35)*(1+SUMIF($Q$2:$Q$4,P35,$R$2:$R$4)),0) -> 0 | R35: =+ROUND((N35)*(1+SUMIF($Q$2:$Q$4,P35,$R$2:$R$4)),0) -> 0
A36: Elect | B36: SECT5.2/9 | C36: 3.1.2.3 | D36: Power wiring point | E36: Item | H36: =+SUM(F36:G36) -> 0 | J36: =+ROUND(I36*H36,2) -> 0 | K36: =J36 -> 0 | M36: =+ROUND(L36*H36,2) -> 0 | N36: =M36 -> 0 | P36: A | Q36: =+ROUND((K36)*(1+SUMIF($Q$2:$Q$4,P36,$R$2:$R$4)),0) -> 0 | R36: =+ROUND((N36)*(1+SUMIF($Q$2:$Q$4,P36,$R$2:$R$4)),0) -> 0
A37: LightUnit | B37: SECT5.2/9 | C37: 3.1.3 | D37: Lighting | H37: =+SUM(F37:G37) -> 0 | J37: =+ROUND(I37*H37,2) -> 0 | K37: =J37 -> 0 | M37: =+ROUND(L37*H37,2) -> 0 | N37: =M37 -> 0 | P37: A | Q37: =+ROUND((K37)*(1+SUMIF($Q$2:$Q$4,P37,$R$2:$R$4)),0) -> 0 | R37: =+ROUND((N37)*(1+SUMIF($Q$2:$Q$4,P37,$R$2:$R$4)),0) -> 0
A38: LightUnit | B38: SECT5.2/9 | C38: 3.1.3.1 | D38: Lighting fixtures | E38: Item | H38: =+SUM(F38:G38) -> 0 | J38: =+ROUND(I38*H38,2) -> 0 | K38: =J38 -> 0 | M38: =+ROUND(L38*H38,2) -> 0 | N38: =M38 -> 0 | P38: A | Q38: =+ROUND((K38)*(1+SUMIF($Q$2:$Q$4,P38,$R$2:$R$4)),0) -> 0 | R38: =+ROUND((N38)*(1+SUMIF($Q$2:$Q$4,P38,$R$2:$R$4)),0) -> 0
A39: Switches | B39: SECT5.2/9 | C39: 3.1.3.2 | D39: Lighting switch | E39: Item | H39: =+SUM(F39:G39) -> 0 | J39: =+ROUND(I39*H39,2) -> 0 | K39: =J39 -> 0 | M39: =+ROUND(L39*H39,2) -> 0 | N39: =M39 -> 0 | P39: A | Q39: =+ROUND((K39)*(1+SUMIF($Q$2:$Q$4,P39,$R$2:$R$4)),0) -> 0 | R39: =+ROUND((N39)*(1+SUMIF($Q$2:$Q$4,P39,$R$2:$R$4)),0) -> 0
A40: LightUnit | B40: SECT5.2/9 | C40: 3.1.3.3 | D40: Lighting wiring point | E40: Item | H40: =+SUM(F40:G40) -> 0 | J40: =+ROUND(I40*H40,2) -> 0 | K40: =J40 -> 0 | M40: =+ROUND(L40*H40,2) -> 0 | N40: =M40 -> 0 | P40: A | Q40: =+ROUND((K40)*(1+SUMIF($Q$2:$Q$4,P40,$R$2:$R$4)),0) -> 0 | R40: =+ROUND((N40)*(1+SUMIF($Q$2:$Q$4,P40,$R$2:$R$4)),0) -> 0
A41: Elect | B41: SECT5.2/9 | C41: 3.1.4 | D41: Fan | H41: =+SUM(F41:G41) -> 0 | J41: =+ROUND(I41*H41,2) -> 0 | K41: =J41 -> 0 | M41: =+ROUND(L41*H41,2) -> 0 | N41: =M41 -> 0 | P41: A | Q41: =+ROUND((K41)*(1+SUMIF($Q$2:$Q$4,P41,$R$2:$R$4)),0) -> 0 | R41: =+ROUND((N41)*(1+SUMIF($Q$2:$Q$4,P41,$R$2:$R$4)),0) -> 0
A42: Elect | B42: SECT5.2/9 | C42: 3.1.4.1 | D42: Ceiling Fan | E42: Item | H42: =+SUM(F42:G42) -> 0 | J42: =+ROUND(I42*H42,2) -> 0 | K42: =J42 -> 0 | M42: =+ROUND(L42*H42,2) -> 0 | N42: =M42 -> 0 | P42: A | Q42: =+ROUND((K42)*(1+SUMIF($Q$2:$Q$4,P42,$R$2:$R$4)),0) -> 0 | R42: =+ROUND((N42)*(1+SUMIF($Q$2:$Q$4,P42,$R$2:$R$4)),0) -> 0
A43: Elect | B43: SECT5.2/9 | C43: 3.1.4.2 | D43: Wall Fan | E43: Item | H43: =+SUM(F43:G43) -> 0 | J43: =+ROUND(I43*H43,2) -> 0 | K43: =J43 -> 0 | M43: =+ROUND(L43*H43,2) -> 0 | N43: =M43 -> 0 | P43: A | Q43: =+ROUND((K43)*(1+SUMIF($Q$2:$Q$4,P43,$R$2:$R$4)),0) -> 0 | R43: =+ROUND((N43)*(1+SUMIF($Q$2:$Q$4,P43,$R$2:$R$4)),0) -> 0
A44: Elect | B44: SECT5.2/9 | C44: 3.1.4.3 | D44: Fan wiring point | E44: Item | H44: =+SUM(F44:G44) -> 0 | J44: =+ROUND(I44*H44,2) -> 0 | K44: =J44 -> 0 | M44: =+ROUND(L44*H44,2) -> 0 | N44: =M44 -> 0 | P44: A | Q44: =+ROUND((K44)*(1+SUMIF($Q$2:$Q$4,P44,$R$2:$R$4)),0) -> 0 | R44: =+ROUND((N44)*(1+SUMIF($Q$2:$Q$4,P44,$R$2:$R$4)),0) -> 0
A45: Elect | B45: SECT5.2/9 | C45: 3.1.5 | D45: Lightning Protection System | H45: =+SUM(F45:G45) -> 0 | J45: =+ROUND(I45*H45,2) -> 0 | K45: =J45 -> 0 | M45: =+ROUND(L45*H45,2) -> 0 | N45: =M45 -> 0 | P45: A | Q45: =+ROUND((K45)*(1+SUMIF($Q$2:$Q$4,P45,$R$2:$R$4)),0) -> 0 | R45: =+ROUND((N45)*(1+SUMIF($Q$2:$Q$4,P45,$R$2:$R$4)),0) -> 0
A46: Elect | B46: SECT5.2/9 | C46: 3.1.5.1 | D46: Air terminal | E46: Item | H46: =+SUM(F46:G46) -> 0 | J46: =+ROUND(I46*H46,2) -> 0 | K46: =J46 -> 0 | M46: =+ROUND(L46*H46,2) -> 0 | N46: =M46 -> 0 | P46: A | Q46: =+ROUND((K46)*(1+SUMIF($Q$2:$Q$4,P46,$R$2:$R$4)),0) -> 0 | R46: =+ROUND((N46)*(1+SUMIF($Q$2:$Q$4,P46,$R$2:$R$4)),0) -> 0
A47: Elect | B47: SECT5.2/9 | C47: 3.1.5.2 | D47: Lightning tape | E47: Item | H47: =+SUM(F47:G47) -> 0 | J47: =+ROUND(I47*H47,2) -> 0 | K47: =J47 -> 0 | M47: =+ROUND(L47*H47,2) -> 0 | N47: =M47 -> 0 | P47: A | Q47: =+ROUND((K47)*(1+SUMIF($Q$2:$Q$4,P47,$R$2:$R$4)),0) -> 0 | R47: =+ROUND((N47)*(1+SUMIF($Q$2:$Q$4,P47,$R$2:$R$4)),0) -> 0
A48: Elect | B48: SECT5.2/9 | C48: 3.1.5.3 | D48: Earth pit including earth rods and all necessaary accessories | E48: Item | H48: =+SUM(F48:G48) -> 0 | J48: =+ROUND(I48*H48,2) -> 0 | K48: =J48 -> 0 | M48: =+ROUND(L48*H48,2) -> 0 | N48: =M48 -> 0 | P48: A | Q48: =+ROUND((K48)*(1+SUMIF($Q$2:$Q$4,P48,$R$2:$R$4)),0) -> 0 | R48: =+ROUND((N48)*(1+SUMIF($Q$2:$Q$4,P48,$R$2:$R$4)),0) -> 0
A49: Elect | B49: SECT5.2/9 | C49: 3.1.6 | D49: Cable | H49: =+SUM(F49:G49) -> 0 | J49: =+ROUND(I49*H49,2) -> 0 | K49: =J49 -> 0 | M49: =+ROUND(L49*H49,2) -> 0 | N49: =M49 -> 0 | P49: A | Q49: =+ROUND((K49)*(1+SUMIF($Q$2:$Q$4,P49,$R$2:$R$4)),0) -> 0 | R49: =+ROUND((N49)*(1+SUMIF($Q$2:$Q$4,P49,$R$2:$R$4)),0) -> 0
A50: Elect | B50: SECT5.2/9 | C50: 3.1.6.1 | D50: Sub-main cable | E50: Item | H50: =+SUM(F50:G50) -> 0 | J50: =+ROUND(I50*H50,2) -> 0 | K50: =J50 -> 0 | M50: =+ROUND(L50*H50,2) -> 0 | N50: =M50 -> 0 | P50: A | Q50: =+ROUND((K50)*(1+SUMIF($Q$2:$Q$4,P50,$R$2:$R$4)),0) -> 0 | R50: =+ROUND((N50)*(1+SUMIF($Q$2:$Q$4,P50,$R$2:$R$4)),0) -> 0
A51: Elect | B51: SECT5.2/9 | C51: 3.1.7 | D51: Cable containment | E51: Item | H51: =+SUM(F51:G51) -> 0 | J51: =+ROUND(I51*H51,2) -> 0 | K51: =J51 -> 0 | M51: =+ROUND(L51*H51,2) -> 0 | N51: =M51 -> 0 | P51: A | Q51: =+ROUND((K51)*(1+SUMIF($Q$2:$Q$4,P51,$R$2:$R$4)),0) -> 0 | R51: =+ROUND((N51)*(1+SUMIF($Q$2:$Q$4,P51,$R$2:$R$4)),0) -> 0
A52: Elect | B52: SECT5.2/9 | C52: 3.2 | D52: ELV System | H52: =+SUM(F52:G52) -> 0 | J52: =+ROUND(I52*H52,2) -> 0 | K52: =J52 -> 0 | M52: =+ROUND(L52*H52,2) -> 0 | N52: =M52 -> 0 | P52: A | Q52: =+ROUND((K52)*(1+SUMIF($Q$2:$Q$4,P52,$R$2:$R$4)),0) -> 0 | R52: =+ROUND((N52)*(1+SUMIF($Q$2:$Q$4,P52,$R$2:$R$4)),0) -> 0
A53: Security | B53: SECT5.2/9 | C53: 3.2.1 | D53: CCTV System | H53: =+SUM(F53:G53) -> 0 | J53: =+ROUND(I53*H53,2) -> 0 | K53: =J53 -> 0 | M53: =+ROUND(L53*H53,2) -> 0 | N53: =M53 -> 0 | P53: A | Q53: =+ROUND((K53)*(1+SUMIF($Q$2:$Q$4,P53,$R$2:$R$4)),0) -> 0 | R53: =+ROUND((N53)*(1+SUMIF($Q$2:$Q$4,P53,$R$2:$R$4)),0) -> 0
A54: Security | B54: SECT5.2/9 | C54: 3.2.1.1 | D54: CCTV camera | E54: Item | H54: =+SUM(F54:G54) -> 0 | J54: =+ROUND(I54*H54,2) -> 0 | K54: =J54 -> 0 | M54: =+ROUND(L54*H54,2) -> 0 | N54: =M54 -> 0 | P54: A | Q54: =+ROUND((K54)*(1+SUMIF($Q$2:$Q$4,P54,$R$2:$R$4)),0) -> 0 | R54: =+ROUND((N54)*(1+SUMIF($Q$2:$Q$4,P54,$R$2:$R$4)),0) -> 0
A55: Security | B55: SECT5.2/9 | C55: 3.2.1.2 | D55: CCTV wiring point | E55: Item | H55: =+SUM(F55:G55) -> 0 | J55: =+ROUND(I55*H55,2) -> 0 | K55: =J55 -> 0 | M55: =+ROUND(L55*H55,2) -> 0 | N55: =M55 -> 0 | P55: A | Q55: =+ROUND((K55)*(1+SUMIF($Q$2:$Q$4,P55,$R$2:$R$4)),0) -> 0 | R55: =+ROUND((N55)*(1+SUMIF($Q$2:$Q$4,P55,$R$2:$R$4)),0) -> 0
A56: Security | B56: SECT5.2/9 | C56: 3.2.1.3 | D56: PoE switch | E56: Item | H56: =+SUM(F56:G56) -> 0 | J56: =+ROUND(I56*H56,2) -> 0 | K56: =J56 -> 0 | M56: =+ROUND(L56*H56,2) -> 0 | N56: =M56 -> 0 | P56: A | Q56: =+ROUND((K56)*(1+SUMIF($Q$2:$Q$4,P56,$R$2:$R$4)),0) -> 0 | R56: =+ROUND((N56)*(1+SUMIF($Q$2:$Q$4,P56,$R$2:$R$4)),0) -> 0
A57: Security | B57: SECT5.2/9 | C57: 3.2.1.4 | D57: UPS | E57: Item | H57: =+SUM(F57:G57) -> 0 | J57: =+ROUND(I57*H57,2) -> 0 | K57: =J57 -> 0 | M57: =+ROUND(L57*H57,2) -> 0 | N57: =M57 -> 0 | P57: A | Q57: =+ROUND((K57)*(1+SUMIF($Q$2:$Q$4,P57,$R$2:$R$4)),0) -> 0 | R57: =+ROUND((N57)*(1+SUMIF($Q$2:$Q$4,P57,$R$2:$R$4)),0) -> 0
A58: AV | B58: SECT5.2/9 | C58: 3.2.2 | D58: Public Address System | H58: =+SUM(F58:G58) -> 0 | J58: =+ROUND(I58*H58,2) -> 0 | K58: =J58 -> 0 | M58: =+ROUND(L58*H58,2) -> 0 | N58: =M58 -> 0 | P58: A | Q58: =+ROUND((K58)*(1+SUMIF($Q$2:$Q$4,P58,$R$2:$R$4)),0) -> 0 | R58: =+ROUND((N58)*(1+SUMIF($Q$2:$Q$4,P58,$R$2:$R$4)),0) -> 0
A59: AV | B59: SECT5.2/9 | C59: 3.2.2.1 | D59: PA speaker | E59: Item | H59: =+SUM(F59:G59) -> 0 | J59: =+ROUND(I59*H59,2) -> 0 | K59: =J59 -> 0 | M59: =+ROUND(L59*H59,2) -> 0 | N59: =M59 -> 0 | P59: A | Q59: =+ROUND((K59)*(1+SUMIF($Q$2:$Q$4,P59,$R$2:$R$4)),0) -> 0 | R59: =+ROUND((N59)*(1+SUMIF($Q$2:$Q$4,P59,$R$2:$R$4)),0) -> 0
A60: AV | B60: SECT5.2/9 | C60: 3.2.2.2 | D60: PA wiring point | E60: Item | H60: =+SUM(F60:G60) -> 0 | J60: =+ROUND(I60*H60,2) -> 0 | K60: =J60 -> 0 | M60: =+ROUND(L60*H60,2) -> 0 | N60: =M60 -> 0 | P60: A | Q60: =+ROUND((K60)*(1+SUMIF($Q$2:$Q$4,P60,$R$2:$R$4)),0) -> 0 | R60: =+ROUND((N60)*(1+SUMIF($Q$2:$Q$4,P60,$R$2:$R$4)),0) -> 0
A61: AV | B61: SECT5.2/9 | C61: 3.2.2.3 | D61: PoE switch | E61: Item | H61: =+SUM(F61:G61) -> 0 | J61: =+ROUND(I61*H61,2) -> 0 | K61: =J61 -> 0 | M61: =+ROUND(L61*H61,2) -> 0 | N61: =M61 -> 0 | P61: A | Q61: =+ROUND((K61)*(1+SUMIF($Q$2:$Q$4,P61,$R$2:$R$4)),0) -> 0 | R61: =+ROUND((N61)*(1+SUMIF($Q$2:$Q$4,P61,$R$2:$R$4)),0) -> 0
A62: AV | B62: SECT5.2/9 | C62: 3.2.3 | D62: Data System | H62: =+SUM(F62:G62) -> 0 | J62: =+ROUND(I62*H62,2) -> 0 | K62: =J62 -> 0 | M62: =+ROUND(L62*H62,2) -> 0 | N62: =M62 -> 0 | P62: A | Q62: =+ROUND((K62)*(1+SUMIF($Q$2:$Q$4,P62,$R$2:$R$4)),0) -> 0 | R62: =+ROUND((N62)*(1+SUMIF($Q$2:$Q$4,P62,$R$2:$R$4)),0) -> 0
A63: AV | B63: SECT5.2/9 | C63: 3.2.3.1 | D63: Wifi Access point | E63: Item | H63: =+SUM(F63:G63) -> 0 | J63: =+ROUND(I63*H63,2) -> 0 | K63: =J63 -> 0 | M63: =+ROUND(L63*H63,2) -> 0 | N63: =M63 -> 0 | P63: A | Q63: =+ROUND((K63)*(1+SUMIF($Q$2:$Q$4,P63,$R$2:$R$4)),0) -> 0 | R63: =+ROUND((N63)*(1+SUMIF($Q$2:$Q$4,P63,$R$2:$R$4)),0) -> 0
A64: AV | B64: SECT5.2/9 | C64: 3.2.3.2 | D64: Wifi wiring point | E64: Item | H64: =+SUM(F64:G64) -> 0 | J64: =+ROUND(I64*H64,2) -> 0 | K64: =J64 -> 0 | M64: =+ROUND(L64*H64,2) -> 0 | N64: =M64 -> 0 | P64: A | Q64: =+ROUND((K64)*(1+SUMIF($Q$2:$Q$4,P64,$R$2:$R$4)),0) -> 0 | R64: =+ROUND((N64)*(1+SUMIF($Q$2:$Q$4,P64,$R$2:$R$4)),0) -> 0
A65: AV | B65: SECT5.2/9 | C65: 3.2.4 | D65: Cable containment | E65: Item | H65: =+SUM(F65:G65) -> 0 | J65: =+ROUND(I65*H65,2) -> 0 | K65: =J65 -> 0 | M65: =+ROUND(L65*H65,2) -> 0 | N65: =M65 -> 0 | P65: A | Q65: =+ROUND((K65)*(1+SUMIF($Q$2:$Q$4,P65,$R$2:$R$4)),0) -> 0 | R65: =+ROUND((N65)*(1+SUMIF($Q$2:$Q$4,P65,$R$2:$R$4)),0) -> 0
A66: AV | B66: SECT5.2/9 | C66: 3.2.5 | D66: Others (Please specify) | H66: =+SUM(F66:G66) -> 0 | J66: =+ROUND(I66*H66,2) -> 0 | K66: =J66 -> 0 | M66: =+ROUND(L66*H66,2) -> 0 | N66: =M66 -> 0 | P66: A | Q66: =+ROUND((K66)*(1+SUMIF($Q$2:$Q$4,P66,$R$2:$R$4)),0) -> 0 | R66: =+ROUND((N66)*(1+SUMIF($Q$2:$Q$4,P66,$R$2:$R$4)),0) -> 0
A67: AV | B67: SECT5.2/9 | C67: i) | D67: ____________________________________ | E67: Item | H67: =+SUM(F67:G67) -> 0 | J67: =+ROUND(I67*H67,2) -> 0 | K67: =J67 -> 0 | M67: =+ROUND(L67*H67,2) -> 0 | N67: =M67 -> 0 | P67: A | Q67: =+ROUND((K67)*(1+SUMIF($Q$2:$Q$4,P67,$R$2:$R$4)),0) -> 0 | R67: =+ROUND((N67)*(1+SUMIF($Q$2:$Q$4,P67,$R$2:$R$4)),0) -> 0
A68: AV | B68: SECT5.2/9 | C68: ii) | D68: ____________________________________ | E68: Item | H68: =+SUM(F68:G68) -> 0 | J68: =+ROUND(I68*H68,2) -> 0 | K68: =J68 -> 0 | M68: =+ROUND(L68*H68,2) -> 0 | N68: =M68 -> 0 | P68: A | Q68: =+ROUND((K68)*(1+SUMIF($Q$2:$Q$4,P68,$R$2:$R$4)),0) -> 0 | R68: =+ROUND((N68)*(1+SUMIF($Q$2:$Q$4,P68,$R$2:$R$4)),0) -> 0
A69: AV | B69: SECT5.2/9 | C69: iii) | D69: ____________________________________ | E69: Item | H69: =+SUM(F69:G69) -> 0 | J69: =+ROUND(I69*H69,2) -> 0 | K69: =J69 -> 0 | M69: =+ROUND(L69*H69,2) -> 0 | N69: =M69 -> 0 | P69: A | Q69: =+ROUND((K69)*(1+SUMIF($Q$2:$Q$4,P69,$R$2:$R$4)),0) -> 0 | R69: =+ROUND((N69)*(1+SUMIF($Q$2:$Q$4,P69,$R$2:$R$4)),0) -> 0
A70: Collection | B70: SECT5.2/9 | D70: To Collection (S$) | J70: =SUM(J29:J69) -> 0 | K70: =SUM(K29:K69) -> 0 | M70: =SUM(M29:M69) -> 0 | N70: =SUM(N29:N69) -> 0 | Q70: =SUM(Q29:Q69) -> 0 | R70: =SUM(R29:R69) -> 0
A71: FireP | B71: SECT5.2/10 | C71: 4 | D71: Fire Protection System | H71: =+SUM(F71:G71) -> 0 | J71: =+ROUND(I71*H71,2) -> 0 | K71: =J71 -> 0 | M71: =+ROUND(L71*H71,2) -> 0 | N71: =M71 -> 0 | P71: A | Q71: =+ROUND((K71)*(1+SUMIF($Q$2:$Q$4,P71,$R$2:$R$4)),0) -> 0 | R71: =+ROUND((N71)*(1+SUMIF($Q$2:$Q$4,P71,$R$2:$R$4)),0) -> 0
A72: FireP | B72: SECT5.2/10 | C72: 4.1 | D72: Hosereel System | H72: =+SUM(F72:G72) -> 0 | J72: =+ROUND(I72*H72,2) -> 0 | K72: =J72 -> 0 | M72: =+ROUND(L72*H72,2) -> 0 | N72: =M72 -> 0 | P72: A | Q72: =+ROUND((K72)*(1+SUMIF($Q$2:$Q$4,P72,$R$2:$R$4)),0) -> 0 | R72: =+ROUND((N72)*(1+SUMIF($Q$2:$Q$4,P72,$R$2:$R$4)),0) -> 0
A73: FireP | B73: SECT5.2/10 | C73: 4.1.1 | D73: Hose reel | E73: Item | H73: =+SUM(F73:G73) -> 0 | J73: =+ROUND(I73*H73,2) -> 0 | K73: =J73 -> 0 | M73: =+ROUND(L73*H73,2) -> 0 | N73: =M73 -> 0 | P73: A | Q73: =+ROUND((K73)*(1+SUMIF($Q$2:$Q$4,P73,$R$2:$R$4)),0) -> 0 | R73: =+ROUND((N73)*(1+SUMIF($Q$2:$Q$4,P73,$R$2:$R$4)),0) -> 0
A74: FireP | B74: SECT5.2/10 | C74: 4.1.2 | D74: Above ground hose reel pipes including valves and all necessary accessories | E74: Item | H74: =+SUM(F74:G74) -> 0 | J74: =+ROUND(I74*H74,2) -> 0 | K74: =J74 -> 0 | M74: =+ROUND(L74*H74,2) -> 0 | N74: =M74 -> 0 | P74: A | Q74: =+ROUND((K74)*(1+SUMIF($Q$2:$Q$4,P74,$R$2:$R$4)),0) -> 0 | R74: =+ROUND((N74)*(1+SUMIF($Q$2:$Q$4,P74,$R$2:$R$4)),0) -> 0
A75: FireP | B75: SECT5.2/10 | C75: 4.2 | D75: Fire Extinguishers | E75: Item | H75: =+SUM(F75:G75) -> 0 | J75: =+ROUND(I75*H75,2) -> 0 | K75: =J75 -> 0 | M75: =+ROUND(L75*H75,2) -> 0 | N75: =M75 -> 0 | P75: A | Q75: =+ROUND((K75)*(1+SUMIF($Q$2:$Q$4,P75,$R$2:$R$4)),0) -> 0 | R75: =+ROUND((N75)*(1+SUMIF($Q$2:$Q$4,P75,$R$2:$R$4)),0) -> 0
A76: FireP | B76: SECT5.2/10 | C76: 4.3 | D76: Fire Alarm System | H76: =+SUM(F76:G76) -> 0 | J76: =+ROUND(I76*H76,2) -> 0 | K76: =J76 -> 0 | M76: =+ROUND(L76*H76,2) -> 0 | N76: =M76 -> 0 | P76: A | Q76: =+ROUND((K76)*(1+SUMIF($Q$2:$Q$4,P76,$R$2:$R$4)),0) -> 0 | R76: =+ROUND((N76)*(1+SUMIF($Q$2:$Q$4,P76,$R$2:$R$4)),0) -> 0
A77: FireP | B77: SECT5.2/10 | C77: 4.3.1 | D77: FIre Alarm panel | E77: Item | H77: =+SUM(F77:G77) -> 0 | J77: =+ROUND(I77*H77,2) -> 0 | K77: =J77 -> 0 | M77: =+ROUND(L77*H77,2) -> 0 | N77: =M77 -> 0 | P77: A | Q77: =+ROUND((K77)*(1+SUMIF($Q$2:$Q$4,P77,$R$2:$R$4)),0) -> 0 | R77: =+ROUND((N77)*(1+SUMIF($Q$2:$Q$4,P77,$R$2:$R$4)),0) -> 0
A78: FireP | B78: SECT5.2/10 | C78: 4.3.2 | D78: Fire alarm detector and devices | E78: Item | H78: =+SUM(F78:G78) -> 0 | J78: =+ROUND(I78*H78,2) -> 0 | K78: =J78 -> 0 | M78: =+ROUND(L78*H78,2) -> 0 | N78: =M78 -> 0 | P78: A | Q78: =+ROUND((K78)*(1+SUMIF($Q$2:$Q$4,P78,$R$2:$R$4)),0) -> 0 | R78: =+ROUND((N78)*(1+SUMIF($Q$2:$Q$4,P78,$R$2:$R$4)),0) -> 0
A79: FireP | B79: SECT5.2/10 | C79: 4.3.3 | D79: Fire alarm wiring point | E79: Item | H79: =+SUM(F79:G79) -> 0 | J79: =+ROUND(I79*H79,2) -> 0 | K79: =J79 -> 0 | M79: =+ROUND(L79*H79,2) -> 0 | N79: =M79 -> 0 | P79: A | Q79: =+ROUND((K79)*(1+SUMIF($Q$2:$Q$4,P79,$R$2:$R$4)),0) -> 0 | R79: =+ROUND((N79)*(1+SUMIF($Q$2:$Q$4,P79,$R$2:$R$4)),0) -> 0
A80: FireP | B80: SECT5.2/10 | C80: 4.3.4 | D80: Cable containment | E80: Item | H80: =+SUM(F80:G80) -> 0 | J80: =+ROUND(I80*H80,2) -> 0 | K80: =J80 -> 0 | M80: =+ROUND(L80*H80,2) -> 0 | N80: =M80 -> 0 | P80: A | Q80: =+ROUND((K80)*(1+SUMIF($Q$2:$Q$4,P80,$R$2:$R$4)),0) -> 0 | R80: =+ROUND((N80)*(1+SUMIF($Q$2:$Q$4,P80,$R$2:$R$4)),0) -> 0
A81: FireP | B81: SECT5.2/10 | C81: 4.4 | D81: Others (Please specify) | H81: =+SUM(F81:G81) -> 0 | J81: =+ROUND(I81*H81,2) -> 0 | K81: =J81 -> 0 | M81: =+ROUND(L81*H81,2) -> 0 | N81: =M81 -> 0 | P81: A | Q81: =+ROUND((K81)*(1+SUMIF($Q$2:$Q$4,P81,$R$2:$R$4)),0) -> 0 | R81: =+ROUND((N81)*(1+SUMIF($Q$2:$Q$4,P81,$R$2:$R$4)),0) -> 0
A82: FireP | B82: SECT5.2/10 | C82: i) | D82: ____________________________________ | E82: Item | H82: =+SUM(F82:G82) -> 0 | J82: =+ROUND(I82*H82,2) -> 0 | K82: =J82 -> 0 | M82: =+ROUND(L82*H82,2) -> 0 | N82: =M82 -> 0 | P82: A | Q82: =+ROUND((K82)*(1+SUMIF($Q$2:$Q$4,P82,$R$2:$R$4)),0) -> 0 | R82: =+ROUND((N82)*(1+SUMIF($Q$2:$Q$4,P82,$R$2:$R$4)),0) -> 0
A83: FireP | B83: SECT5.2/10 | C83: ii) | D83: ____________________________________ | E83: Item | H83: =+SUM(F83:G83) -> 0 | J83: =+ROUND(I83*H83,2) -> 0 | K83: =J83 -> 0 | M83: =+ROUND(L83*H83,2) -> 0 | N83: =M83 -> 0 | P83: A | Q83: =+ROUND((K83)*(1+SUMIF($Q$2:$Q$4,P83,$R$2:$R$4)),0) -> 0 | R83: =+ROUND((N83)*(1+SUMIF($Q$2:$Q$4,P83,$R$2:$R$4)),0) -> 0
A84: FireP | B84: SECT5.2/10 | C84: iii) | D84: ____________________________________ | E84: Item | H84: =+SUM(F84:G84) -> 0 | J84: =+ROUND(I84*H84,2) -> 0 | K84: =J84 -> 0 | M84: =+ROUND(L84*H84,2) -> 0 | N84: =M84 -> 0 | P84: A | Q84: =+ROUND((K84)*(1+SUMIF($Q$2:$Q$4,P84,$R$2:$R$4)),0) -> 0 | R84: =+ROUND((N84)*(1+SUMIF($Q$2:$Q$4,P84,$R$2:$R$4)),0) -> 0
A85: Collection | B85: SECT5.2/10 | D85: To Collection (S$) | J85: =SUM(J71:J84) -> 0 | K85: =SUM(K71:K84) -> 0 | M85: =SUM(M71:M84) -> 0 | N85: =SUM(N71:N84) -> 0 | Q85: =SUM(Q71:Q84) -> 0 | R85: =SUM(R71:R84) -> 0
A86: Collection | B86: SECT5.2/11 | D86: SECTION NO 5 - RESIDENTIAL BLOCKS COLLECTION
A87: Collection | B87: SECT5.2/11 | D87: Pg Sect 5.2/7 | J87: =J21 -> 0 | K87: =K21 -> 0 | M87: =M21 -> 0 | N87: =N21 -> 0 | Q87: =Q21 -> 0 | R87: =R21 -> 0
A88: Collection | B88: SECT5.2/11 | D88: Pg Sect 5.2/8 | J88: =J28 -> 0 | K88: =K28 -> 0 | M88: =M28 -> 0 | N88: =N28 -> 0 | Q88: =Q28 -> 0 | R88: =R28 -> 0
A89: Collection | B89: SECT5.2/11 | D89: Pg Sect 5.2/9 | J89: =J70 -> 0 | K89: =K70 -> 0 | M89: =M70 -> 0 | N89: =N70 -> 0 | Q89: =Q70 -> 0 | R89: =R70 -> 0
A90: Collection | B90: SECT5.2/11 | D90: Pg Sect 5.2/10 | J90: =J85 -> 0 | K90: =K85 -> 0 | M90: =M85 -> 0 | N90: =N85 -> 0 | Q90: =Q85 -> 0 | R90: =R85 -> 0
A91: Collection | B91: SECT5.2/11 | D91: To Collection (S$) | J91: =SUM(J87:J90) -> 0 | K91: =SUM(K87:K90) -> 0 | M91: =SUM(M87:M90) -> 0 | N91: =SUM(N87:N90) -> 0 | Q91: =SUM(Q87:Q90) -> 0 | R91: =SUM(R87:R90) -> 0
A92: SP | B92: SECT5.3/12 | D92: SECTION NO 5.3 — FACILITIES BLOCK | H92: =+SUM(F92:G92) -> 0 | J92: =+ROUND(I92*H92,2) -> 0 | K92: =J92 -> 0 | M92: =+ROUND(L92*H92,2) -> 0 | N92: =M92 -> 0 | P92: A | Q92: =+ROUND((K92)*(1+SUMIF($Q$2:$Q$4,P92,$R$2:$R$4)),0) -> 0 | R92: =+ROUND((N92)*(1+SUMIF($Q$2:$Q$4,P92,$R$2:$R$4)),0) -> 0
A93: SP | B93: =+B92 -> SECT5.3/12 | C93: 1 | D93: Plumbing, Sanitary and Gas | H93: =+SUM(F93:G93) -> 0 | J93: =+ROUND(I93*H93,2) -> 0 | K93: =J93 -> 0 | M93: =+ROUND(L93*H93,2) -> 0 | N93: =M93 -> 0 | P93: A | Q93: =+ROUND((K93)*(1+SUMIF($Q$2:$Q$4,P93,$R$2:$R$4)),0) -> 0 | R93: =+ROUND((N93)*(1+SUMIF($Q$2:$Q$4,P93,$R$2:$R$4)),0) -> 0
A94: SP | B94: =+B93 -> SECT5.3/12 | C94: 1.1 | D94: Sanitary System | H94: =+SUM(F94:G94) -> 0 | J94: =+ROUND(I94*H94,2) -> 0 | K94: =J94 -> 0 | M94: =+ROUND(L94*H94,2) -> 0 | N94: =M94 -> 0 | P94: A | Q94: =+ROUND((K94)*(1+SUMIF($Q$2:$Q$4,P94,$R$2:$R$4)),0) -> 0 | R94: =+ROUND((N94)*(1+SUMIF($Q$2:$Q$4,P94,$R$2:$R$4)),0) -> 0
A95: SP | B95: =+B94 -> SECT5.3/12 | C95: 1.1.1 | D95: Above ground sanitary pipes including vent cowl, floor trap, floor waste and all necessary accessories | E95: Item | H95: =+SUM(F95:G95) -> 0 | J95: =+ROUND(I95*H95,2) -> 0 | K95: =J95 -> 0 | M95: =+ROUND(L95*H95,2) -> 0 | N95: =M95 -> 0 | P95: A | Q95: =+ROUND((K95)*(1+SUMIF($Q$2:$Q$4,P95,$R$2:$R$4)),0) -> 0 | R95: =+ROUND((N95)*(1+SUMIF($Q$2:$Q$4,P95,$R$2:$R$4)),0) -> 0
A96: SP | B96: =+B95 -> SECT5.3/12 | C96: 1.1.2 | D96: Take delivery and installation of plumbing and sanitary fixtures | E96: Item | H96: =+SUM(F96:G96) -> 0 | J96: =+ROUND(I96*H96,2) -> 0 | K96: =J96 -> 0 | M96: =+ROUND(L96*H96,2) -> 0 | N96: =M96 -> 0 | P96: A | Q96: =+ROUND((K96)*(1+SUMIF($Q$2:$Q$4,P96,$R$2:$R$4)),0) -> 0 | R96: =+ROUND((N96)*(1+SUMIF($Q$2:$Q$4,P96,$R$2:$R$4)),0) -> 0
A97: SP | B97: =+B96 -> SECT5.3/12 | C97: 1.2 | D97: Plumbing System | H97: =+SUM(F97:G97) -> 0 | J97: =+ROUND(I97*H97,2) -> 0 | K97: =J97 -> 0 | M97: =+ROUND(L97*H97,2) -> 0 | N97: =M97 -> 0 | P97: A | Q97: =+ROUND((K97)*(1+SUMIF($Q$2:$Q$4,P97,$R$2:$R$4)),0) -> 0 | R97: =+ROUND((N97)*(1+SUMIF($Q$2:$Q$4,P97,$R$2:$R$4)),0) -> 0
A98: SP | B98: =+B97 -> SECT5.3/12 | C98: 1.2.1 | D98: Above ground domestic cold water pipes including sub water meter, valves, bib taps and all necessary accessories | E98: Item | H98: =+SUM(F98:G98) -> 0 | J98: =+ROUND(I98*H98,2) -> 0 | K98: =J98 -> 0 | M98: =+ROUND(L98*H98,2) -> 0 | N98: =M98 -> 0 | P98: A | Q98: =+ROUND((K98)*(1+SUMIF($Q$2:$Q$4,P98,$R$2:$R$4)),0) -> 0 | R98: =+ROUND((N98)*(1+SUMIF($Q$2:$Q$4,P98,$R$2:$R$4)),0) -> 0
A99: SP | B99: =+B98 -> SECT5.3/12 | C99: 1.3 | D99: Gas System | H99: =+SUM(F99:G99) -> 0 | J99: =+ROUND(I99*H99,2) -> 0 | K99: =J99 -> 0 | M99: =+ROUND(L99*H99,2) -> 0 | N99: =M99 -> 0 | P99: A | Q99: =+ROUND((K99)*(1+SUMIF($Q$2:$Q$4,P99,$R$2:$R$4)),0) -> 0 | R99: =+ROUND((N99)*(1+SUMIF($Q$2:$Q$4,P99,$R$2:$R$4)),0) -> 0
A100: SP | B100: =+B99 -> SECT5.3/12 | C100: 1.3.1 | D100: Gas pipes including valves, gas meter and all necessaary accessories | E100: Item | H100: =+SUM(F100:G100) -> 0 | J100: =+ROUND(I100*H100,2) -> 0 | K100: =J100 -> 0 | M100: =+ROUND(L100*H100,2) -> 0 | N100: =M100 -> 0 | P100: A | Q100: =+ROUND((K100)*(1+SUMIF($Q$2:$Q$4,P100,$R$2:$R$4)),0) -> 0 | R100: =+ROUND((N100)*(1+SUMIF($Q$2:$Q$4,P100,$R$2:$R$4)),0) -> 0
A101: SP | B101: =+B100 -> SECT5.3/12 | C101: 1.4 | D101: Others (Please specify) | H101: =+SUM(F101:G101) -> 0 | J101: =+ROUND(I101*H101,2) -> 0 | K101: =J101 -> 0 | M101: =+ROUND(L101*H101,2) -> 0 | N101: =M101 -> 0 | P101: A | Q101: =+ROUND((K101)*(1+SUMIF($Q$2:$Q$4,P101,$R$2:$R$4)),0) -> 0 | R101: =+ROUND((N101)*(1+SUMIF($Q$2:$Q$4,P101,$R$2:$R$4)),0) -> 0
...
